Workbook
Name P35_: #REF!
Name P35_: #REF!
Name P35_: #REF!
Name P35_: #REF!
Name P35_: #REF!
Name P35_: #REF!
Name P35_: #REF!
Name P35_: #REF!
Name P35_: #REF!
Name P35_: #REF!
Name P35_: #REF!
Name P35_: #REF!
Name P35_: #REF!
Name P35_: #REF!
Name P35_Percent: #REF!
Name P35_Percent: #REF!
Name P35_Percent: #REF!
Name P35_Percent: #REF!
Name P35_Percent: #REF!
Name P35_Percent: #REF!
Name P35_Percent: #REF!
Name P35_Percent: #REF!
Name P35_Percent: #REF!
Name P35_Percent: #REF!
Name P35_Percent: #REF!
Name P35_Percent: #REF!
Name P35_Percent: #REF!
Name P35_Percent: #REF!
Name P35Percent: #REF!
Name P35Percent: #REF!
Name P35Percent: #REF!
Name P35Percent: #REF!
Name P35Percent: #REF!
Name P35Percent: #REF!
Name P35Percent: #REF!
Name P35Percent: #REF!
Name P35Percent: #REF!
Name P35Percent: #REF!
Name P35Percent: #REF!
Name P35Percent: #REF!
Name P35Percent: #REF!
Name P35Percent: #REF!

Sheet Log Sales Data
A1: Year | B1: Month | C1: Forest Name | D1: Grade Breakdown | E1: Lengh | F1: Species | G1: Market | H1: Customer | I1: Tonnes # | J1: Conversion Rate | K1: JAS # | L1: At mill/port Door Price | M1: Amount in NZ$ | AA1: Grade | AB1: Conversion Rate
A2: 2025 | B2: 45658 | C2: Eastfork | D2: P40 | E2: 5.9 | F2: Radiata | G2: Export | H2: FCO | I2: 200 | J2: =_xlfn.XLOOKUP(Table223[[#This Row],[Grade Breakdown]],AA:AA,AB:AB,0,0) -> 1.09 | K2: =Table223[[#This Row],[Tonnes '#]]*Table223[[#This Row],[Conversion Rate]] -> 218 | L2: 195 | M2: =Table223[[#This Row],[Tonnes '#]]*Table223[[#This Row],[At mill/port Door Price]] -> 39000 | AA2: S40 | AB2: 1.06
A3: 2025 | B3: 45658 | C3: Eastfork | D3: A | E3: 5.9 | F3: Radiata | G3: Export | H3: FCO | I3: 400 | J3: =_xlfn.XLOOKUP(Table223[[#This Row],[Grade Breakdown]],AA:AA,AB:AB,0,0) -> 1.03 | K3: =Table223[[#This Row],[Tonnes '#]]*Table223[[#This Row],[Conversion Rate]] -> 412 | L3: 127 | M3: =Table223[[#This Row],[Tonnes '#]]*Table223[[#This Row],[At mill/port Door Price]] -> 50800 | AA3: S30 | AB3: 1.03
A4: 2025 | B4: 45658 | C4: Eastfork | D4: K | E4: 5.9 | F4: Radiata | G4: Export | H4: FCO | I4: 600 | J4: =_xlfn.XLOOKUP(Table223[[#This Row],[Grade Breakdown]],AA:AA,AB:AB,0,0) -> 0.99 | K4: =Table223[[#This Row],[Tonnes '#]]*Table223[[#This Row],[Conversion Rate]] -> 594 | L4: 120 | M4: =Table223[[#This Row],[Tonnes '#]]*Table223[[#This Row],[At mill/port Door Price]] -> 72000 | AA4: S20 | AB4: 0.99
A5: 2025 | B5: 45658 | C5: Eastfork | D5: P40 | E5: 5.9 | F5: Radiata | G5: Export | H5: FCO | I5: 250 | J5: =_xlfn.XLOOKUP(Table223[[#This Row],[Grade Breakdown]],AA:AA,AB:AB,0,0) -> 1.09 | K5: =Table223[[#This Row],[Tonnes '#]]*Table223[[#This Row],[Conversion Rate]] -> 272.5 | L5: 195 | M5: =Table223[[#This Row],[Tonnes '#]]*Table223[[#This Row],[At mill/port Door Price]] -> 48750 | AA5: Domestic Pulp | AB5: 0.88
A6: 2025 | B6: 45658 | C6: Eastfork | D6: A | E6: 5.9 | F6: Radiata | G6: Export | H6: FCO | I6: 450 | J6: =_xlfn.XLOOKUP(Table223[[#This Row],[Grade Breakdown]],AA:AA,AB:AB,0,0) -> 1.03 | K6: =Table223[[#This Row],[Tonnes '#]]*Table223[[#This Row],[Conversion Rate]] -> 463.5 | L6: 127 | M6: =Table223[[#This Row],[Tonnes '#]]*Table223[[#This Row],[At mill/port Door Price]] -> 57150 | AA6: Eucalyptus | AB6: 0.95
A7: 2025 | B7: 45658 | C7: Eastfork | D7: K | E7: 5.9 | F7: Radiata | G7: Export | H7: FCO | I7: 650 | J7: =_xlfn.XLOOKUP(Table223[[#This Row],[Grade Breakdown]],AA:AA,AB:AB,0,0) -> 0.99 | K7: =Table223[[#This Row],[Tonnes '#]]*Table223[[#This Row],[Conversion Rate]] -> 643.5 | L7: 120 | M7: =Table223[[#This Row],[Tonnes '#]]*Table223[[#This Row],[At mill/port Door Price]] -> 78000 | AA7: FW | AB7: 0.95
A8: 2025 | B8: 45658 | C8: Eastfork | D8: P35 | E8: 5.9 | F8: Radiata | G8: Domestic | H8: FCO | I8: 190 | J8: =_xlfn.XLOOKUP(Table223[[#This Row],[Grade Breakdown]],AA:AA,AB:AB,0,0) -> 1.08 | K8: =Table223[[#This Row],[Tonnes '#]]*Table223[[#This Row],[Conversion Rate]] -> 205.2 | L8: 195 | M8: =Table223[[#This Row],[Tonnes '#]]*Table223[[#This Row],[At mill/port Door Price]] -> 37050 | AA8: Euc Pulp | AB8: 0.88
A9: 2025 | B9: 45658 | C9: Eastfork | D9: S30 | E9: 5.9 | F9: Radiata | G9: Domestic | H9: FCO | I9: 390 | J9: =_xlfn.XLOOKUP(Table223[[#This Row],[Grade Breakdown]],AA:AA,AB:AB,0,0) -> 1.03 | K9: =Table223[[#This Row],[Tonnes '#]]*Table223[[#This Row],[Conversion Rate]] -> 401.7 | L9: 127 | M9: =Table223[[#This Row],[Tonnes '#]]*Table223[[#This Row],[At mill/port Door Price]] -> 49530 | AA9: Binwood | AB9: 0.88
A10: 2025 | B10: 45658 | C10: Eastfork | D10: S20 | E10: 5.9 | F10: Radiata | G10: Domestic | H10: FCO | I10: 590 | J10: =_xlfn.XLOOKUP(Table223[[#This Row],[Grade Breakdown]],AA:AA,AB:AB,0,0) -> 0.99 | K10: =Table223[[#This Row],[Tonnes '#]]*Table223[[#This Row],[Conversion Rate]] -> 584.1 | L10: 120 | M10: =Table223[[#This Row],[Tonnes '#]]*Table223[[#This Row],[At mill/port Door Price]] -> 70800 | AA10: P40 | AB10: 1.09
A11: 2025 | B11: 45658 | C11: Eastfork | D11: P35 | E11: 5.9 | F11: Radiata | G11: Domestic | H11: FCO | I11: 240 | J11: =_xlfn.XLOOKUP(Table223[[#This Row],[Grade Breakdown]],AA:AA,AB:AB,0,0) -> 1.08 | K11: =Table223[[#This Row],[Tonnes '#]]*Table223[[#This Row],[Conversion Rate]] -> 259.2 | L11: 195 | M11: =Table223[[#This Row],[Tonnes '#]]*Table223[[#This Row],[At mill/port Door Price]] -> 46800 | AA11: P35 | AB11: 1.08
A12: 2025 | B12: 45658 | C12: Eastfork | D12: S30 | E12: 5.9 | F12: Radiata | G12: Domestic | H12: FCO | I12: 440 | J12: =_xlfn.XLOOKUP(Table223[[#This Row],[Grade Breakdown]],AA:AA,AB:AB,0,0) -> 1.03 | K12: =Table223[[#This Row],[Tonnes '#]]*Table223[[#This Row],[Conversion Rate]] -> 453.2 | L12: 127 | M12: =Table223[[#This Row],[Tonnes '#]]*Table223[[#This Row],[At mill/port Door Price]] -> 55880 | AA12: P30 | AB12: 1.07
A13: 2025 | B13: 45658 | C13: Eastfork | D13: S20 | E13: 5.9 | F13: Radiata | G13: Domestic | H13: FCO | I13: 640 | J13: =_xlfn.XLOOKUP(Table223[[#This Row],[Grade Breakdown]],AA:AA,AB:AB,0,0) -> 0.99 | K13: =Table223[[#This Row],[Tonnes '#]]*Table223[[#This Row],[Conversion Rate]] -> 633.6 | L13: 120 | M13: =Table223[[#This Row],[Tonnes '#]]*Table223[[#This Row],[At mill/port Door Price]] -> 76800 | AA13: AO | AB13: 1.03
A14: 2025 | J14: =_xlfn.XLOOKUP(Table223[[#This Row],[Grade Breakdown]],AA:AA,AB:AB,0,0) -> 0 | K14: =Table223[[#This Row],[Tonnes '#]]*Table223[[#This Row],[Conversion Rate]] -> 0 | M14: =Table223[[#This Row],[Tonnes '#]]*Table223[[#This Row],[At mill/port Door Price]] -> 0 | AA14: A | AB14: 1.03
A15: 2025 | J15: =_xlfn.XLOOKUP(Table223[[#This Row],[Grade Breakdown]],AA:AA,AB:AB,0,0) -> 0 | K15: =Table223[[#This Row],[Tonnes '#]]*Table223[[#This Row],[Conversion Rate]] -> 0 | M15: =Table223[[#This Row],[Tonnes '#]]*Table223[[#This Row],[At mill/port Door Price]] -> 0 | AA15: K | AB15: 0.99
A16: 2025 | J16: =_xlfn.XLOOKUP(Table223[[#This Row],[Grade Breakdown]],AA:AA,AB:AB,0,0) -> 0 | K16: =Table223[[#This Row],[Tonnes '#]]*Table223[[#This Row],[Conversion Rate]] -> 0 | M16: =Table223[[#This Row],[Tonnes '#]]*Table223[[#This Row],[At mill/port Door Price]] -> 0 | AA16: KI | AB16: 0.97
A17: 2025 | J17: =_xlfn.XLOOKUP(Table223[[#This Row],[Grade Breakdown]],AA:AA,AB:AB,0,0) -> 0 | K17: =Table223[[#This Row],[Tonnes '#]]*Table223[[#This Row],[Conversion Rate]] -> 0 | M17: =Table223[[#This Row],[Tonnes '#]]*Table223[[#This Row],[At mill/port Door Price]] -> 0 | AA17: KIS | AB17: 0.88
A18: 2025 | J18: =_xlfn.XLOOKUP(Table223[[#This Row],[Grade Breakdown]],AA:AA,AB:AB,0,0) -> 0 | K18: =Table223[[#This Row],[Tonnes '#]]*Table223[[#This Row],[Conversion Rate]] -> 0 | M18: =Table223[[#This Row],[Tonnes '#]]*Table223[[#This Row],[At mill/port Door Price]] -> 0 | AA18: KI stub | AB18: 0.97
A19: 2025 | J19: =_xlfn.XLOOKUP(Table223[[#This Row],[Grade Breakdown]],AA:AA,AB:AB,0,0) -> 0 | K19: =Table223[[#This Row],[Tonnes '#]]*Table223[[#This Row],[Conversion Rate]] -> 0 | M19: =Table223[[#This Row],[Tonnes '#]]*Table223[[#This Row],[At mill/port Door Price]] -> 0 | AA19: Scragwood | AB19: 0.95
A20: 2025 | J20: =_xlfn.XLOOKUP(Table223[[#This Row],[Grade Breakdown]],AA:AA,AB:AB,0,0) -> 0 | K20: =Table223[[#This Row],[Tonnes '#]]*Table223[[#This Row],[Conversion Rate]] -> 0 | M20: =Table223[[#This Row],[Tonnes '#]]*Table223[[#This Row],[At mill/port Door Price]] -> 0 | AA20: CF+ | AB20: 1.03
A21: 2025 | J21: =_xlfn.XLOOKUP(Table223[[#This Row],[Grade Breakdown]],AA:AA,AB:AB,0,0) -> 0 | K21: =Table223[[#This Row],[Tonnes '#]]*Table223[[#This Row],[Conversion Rate]] -> 0 | M21: =Table223[[#This Row],[Tonnes '#]]*Table223[[#This Row],[At mill/port Door Price]] -> 0 | AA21: CF- | AB21: 0.99
A22: 2025 | J22: =_xlfn.XLOOKUP(Table223[[#This Row],[Grade Breakdown]],AA:AA,AB:AB,0,0) -> 0 | K22: =Table223[[#This Row],[Tonnes '#]]*Table223[[#This Row],[Conversion Rate]] -> 0 | M22: =Table223[[#This Row],[Tonnes '#]]*Table223[[#This Row],[At mill/port Door Price]] -> 0 | AA22: CM | AB22: 0.97
A23: 2025 | J23: =_xlfn.XLOOKUP(Table223[[#This Row],[Grade Breakdown]],AA:AA,AB:AB,0,0) -> 0 | K23: =Table223[[#This Row],[Tonnes '#]]*Table223[[#This Row],[Conversion Rate]] -> 0 | M23: =Table223[[#This Row],[Tonnes '#]]*Table223[[#This Row],[At mill/port Door Price]] -> 0 | AA23: Euc A | AB23: 0.95
A24: 2025 | J24: =_xlfn.XLOOKUP(Table223[[#This Row],[Grade Breakdown]],AA:AA,AB:AB,0,0) -> 0 | K24: =Table223[[#This Row],[Tonnes '#]]*Table223[[#This Row],[Conversion Rate]] -> 0 | M24: =Table223[[#This Row],[Tonnes '#]]*Table223[[#This Row],[At mill/port Door Price]] -> 0 | AA24: Euc K | AB24: 0.93
A25: 2025 | J25: =_xlfn.XLOOKUP(Table223[[#This Row],[Grade Breakdown]],AA:AA,AB:AB,0,0) -> 0 | K25: =Table223[[#This Row],[Tonnes '#]]*Table223[[#This Row],[Conversion Rate]] -> 0 | M25: =Table223[[#This Row],[Tonnes '#]]*Table223[[#This Row],[At mill/port Door Price]] -> 0
A26: 2025 | J26: =_xlfn.XLOOKUP(Table223[[#This Row],[Grade Breakdown]],AA:AA,AB:AB,0,0) -> 0 | K26: =Table223[[#This Row],[Tonnes '#]]*Table223[[#This Row],[Conversion Rate]] -> 0 | M26: =Table223[[#This Row],[Tonnes '#]]*Table223[[#This Row],[At mill/port Door Price]] -> 0
A27: 2025 | J27: =_xlfn.XLOOKUP(Table223[[#This Row],[Grade Breakdown]],AA:AA,AB:AB,0,0) -> 0 | K27: =Table223[[#This Row],[Tonnes '#]]*Table223[[#This Row],[Conversion Rate]] -> 0 | M27: =Table223[[#This Row],[Tonnes '#]]*Table223[[#This Row],[At mill/port Door Price]] -> 0
A28: 2025 | J28: =_xlfn.XLOOKUP(Table223[[#This Row],[Grade Breakdown]],AA:AA,AB:AB,0,0) -> 0 | K28: =Table223[[#This Row],[Tonnes '#]]*Table223[[#This Row],[Conversion Rate]] -> 0 | M28: =Table223[[#This Row],[Tonnes '#]]*Table223[[#This Row],[At mill/port Door Price]] -> 0
A29: 2025 | J29: =_xlfn.XLOOKUP(Table223[[#This Row],[Grade Breakdown]],AA:AA,AB:AB,0,0) -> 0 | K29: =Table223[[#This Row],[Tonnes '#]]*Table223[[#This Row],[Conversion Rate]] -> 0 | M29: =Table223[[#This Row],[Tonnes '#]]*Table223[[#This Row],[At mill/port Door Price]] -> 0
A30: 2025 | J30: =_xlfn.XLOOKUP(Table223[[#This Row],[Grade Breakdown]],AA:AA,AB:AB,0,0) -> 0 | K30: =Table223[[#This Row],[Tonnes '#]]*Table223[[#This Row],[Conversion Rate]] -> 0 | M30: =Table223[[#This Row],[Tonnes '#]]*Table223[[#This Row],[At mill/port Door Price]] -> 0
A31: 2025 | J31: =_xlfn.XLOOKUP(Table223[[#This Row],[Grade Breakdown]],AA:AA,AB:AB,0,0) -> 0 | K31: =Table223[[#This Row],[Tonnes '#]]*Table223[[#This Row],[Conversion Rate]] -> 0 | M31: =Table223[[#This Row],[Tonnes '#]]*Table223[[#This Row],[At mill/port Door Price]] -> 0
A32: 2025 | J32: =_xlfn.XLOOKUP(Table223[[#This Row],[Grade Breakdown]],AA:AA,AB:AB,0,0) -> 0 | K32: =Table223[[#This Row],[Tonnes '#]]*Table223[[#This Row],[Conversion Rate]] -> 0 | M32: =Table223[[#This Row],[Tonnes '#]]*Table223[[#This Row],[At mill/port Door Price]] -> 0
A33: 2025 | J33: =_xlfn.XLOOKUP(Table223[[#This Row],[Grade Breakdown]],AA:AA,AB:AB,0,0) -> 0 | K33: =Table223[[#This Row],[Tonnes '#]]*Table223[[#This Row],[Conversion Rate]] -> 0 | M33: =Table223[[#This Row],[Tonnes '#]]*Table223[[#This Row],[At mill/port Door Price]] -> 0
A34: 2025 | J34: =_xlfn.XLOOKUP(Table223[[#This Row],[Grade Breakdown]],AA:AA,AB:AB,0,0) -> 0 | K34: =Table223[[#This Row],[Tonnes '#]]*Table223[[#This Row],[Conversion Rate]] -> 0 | M34: =Table223[[#This Row],[Tonnes '#]]*Table223[[#This Row],[At mill/port Door Price]] -> 0
A35: 2025 | J35: =_xlfn.XLOOKUP(Table223[[#This Row],[Grade Breakdown]],AA:AA,AB:AB,0,0) -> 0 | K35: =Table223[[#This Row],[Tonnes '#]]*Table223[[#This Row],[Conversion Rate]] -> 0 | M35: =Table223[[#This Row],[Tonnes '#]]*Table223[[#This Row],[At mill/port Door Price]] -> 0
A36: 2025 | J36: =_xlfn.XLOOKUP(Table223[[#This Row],[Grade Breakdown]],AA:AA,AB:AB,0,0) -> 0 | K36: =Table223[[#This Row],[Tonnes '#]]*Table223[[#This Row],[Conversion Rate]] -> 0 | M36: =Table223[[#This Row],[Tonnes '#]]*Table223[[#This Row],[At mill/port Door Price]] -> 0
... A57: 2025 | J57: =_xlfn.XLOOKUP(Table223[[#This Row],[Grade Breakdown]],AA:AA,AB:AB,0,0) -> 0 | K57: =Table223[[#This Row],[Tonnes '#]]*Table223[[#This Row],[Conversion Rate]] -> 0 | M57: =Table223[[#This Row],[Tonnes '#]]*Table223[[#This Row],[At mill/port Door Price]] -> 0

Sheet Eastfork Budget
C1: 2025 | D1: Input
B2: Eastfork | H2: Estimated Tonnes (ha)
B3: PRODUCTION & RATE | G3: Total Monthly Working Days | I3: =SUM(J5:U5)+SUM(J8:U8)+SUM(J11:U11) -> 0 | J3: 45658 | K3: 45689 | L3: 45717 | M3: 45748 | N3: 45778 | O3: 45809 | P3: 45839 | Q3: 45870 | R3: 45901 | S3: 45931 | T3: 45962 | U3: 45992 | W3: Total
G4: Groundbase | H4: Daily production | I4: =IFERROR((J4*J5+K4*K5+L4*L5+M4*M5+N4*N5+O4*O5+P4*P5+Q4*Q5+R4*R5+S4*S5+T4*T5+U4*U5)/$W$16,0) -> 0
H5: Days worked
H6: Harvesting Rate
G7: Roadline | H7: Daily production | I7: =IFERROR((J7*J8+K7*K8+L7*L8+M7*M8+N7*N8+O7*O8+P7*P8+Q7*Q8+R7*R8+S7*S8+T7*T8+U7*U8)/$W$16,0) -> 0
H8: Days worked
H9: Harvesting Rate
G10: Hauler | H10: Daily production | I10: =IFERROR((J10*J11+K10*K11+L10*L11+M10*M11+N10*N11+O10*O11+P10*P11+Q10*Q11+R10*R11+S10*S11+T10*T11+U10*U11)/$W$16,0) -> 0
H11: Days worked
H12: Harvesting Rate
G13: Average | H13: Harvesting Rate | I13: =SUM(I4:I12) -> 0 | J13: =IFERROR((J4*J5*J6+J7*J8*J9+J10*J11*J12)/J16,0) -> 0 | K13: =IFERROR((K4*K5*K6+K7*K8*K9+K10*K11*K12)/K16,0) -> 0 | L13: =IFERROR((L4*L5*L6+L7*L8*L9+L10*L11*L12)/L16,0) -> 0 | M13: =IFERROR((M4*M5*M6+M7*M8*M9+M10*M11*M12)/M16,0) -> 0 | N13: =IFERROR((N4*N5*N6+N7*N8*N9+N10*N11*N12)/N16,0) -> 0 | O13: =IFERROR((O4*O5*O6+O7*O8*O9+O10*O11*O12)/O16,0) -> 0 | P13: =IFERROR((P4*P5*P6+P7*P8*P9+P10*P11*P12)/P16,0) -> 0 | Q13: =IFERROR((Q4*Q5*Q6+Q7*Q8*Q9+Q10*Q11*Q12)/Q16,0) -> 0 | ... U13: =IFERROR((U4*U5*U6+U7*U8*U9+U10*U11*U12)/U16,0) -> 0 | W13: =I3 -> 0 | X13: Monthly Working Days
G14: Average | H14: Daily production | J14: =J4+J7+J10 -> 0 | K14: =K4+K7+K10 -> 0 | L14: =L4+L7+L10 -> 0 | M14: =M4+M7+M10 -> 0 | N14: =N4+N7+N10 -> 0 | O14: =O4+O7+O10 -> 0 | P14: =P4+P7+P10 -> 0 | Q14: =Q4+Q7+Q10 -> 0 | ... U14: =U4+U7+U10 -> 0 | W14: =IF(W16=0,0,W16/W15) -> 0 | X14: =H2 -> Estimated Tonnes (ha)
G15: Total | H15: Hectare (ha) | J15: =IFERROR(J16/$I$2,0) -> 0 | K15: =IFERROR(K16/$I$2,0) -> 0 | L15: =IFERROR(L16/$I$2,0) -> 0 | M15: =IFERROR(M16/$I$2,0) -> 0 | N15: =IFERROR(N16/$I$2,0) -> 0 | O15: =IFERROR(O16/$I$2,0) -> 0 | P15: =IFERROR(P16/$I$2,0) -> 0 | Q15: =IFERROR(Q16/$I$2,0) -> 0 | ... U15: =IFERROR(U16/$I$2,0) -> 0 | W15: =SUM(J15:U15) -> 0 | X15: =H15 -> Hectare (ha)
G16: Total | H16: Tonnes Harvested | J16: =IFERROR((J4*J5+J7*J8+J10*J11),0) -> 0 | K16: =IFERROR((K4*K5+K7*K8+K10*K11),0) -> 0 | L16: =IFERROR((L4*L5+L7*L8+L10*L11),0) -> 0 | M16: =IFERROR((M4*M5+M7*M8+M10*M11),0) -> 0 | N16: =IFERROR((N4*N5+N7*N8+N10*N11),0) -> 0 | O16: =IFERROR((O4*O5+O7*O8+O10*O11),0) -> 0 | P16: =IFERROR((P4*P5+P7*P8+P10*P11),0) -> 0 | Q16: =IFERROR((Q4*Q5+Q7*Q8+Q10*Q11),0) -> 0 | ... U16: =IFERROR((U4*U5+U7*U8+U10*U11),0) -> 0 | W16: =SUM(J16:U16) -> 0 | X16: =H16 -> Tonnes Harvested
W17: =W16/W15 -> #DIV/0! | X17: Vol/ha
B18: REVENUE
B19: Grade | C19: Grade Mix % | D19: Conversion Rate | E19: Sale unit | F19: Sale unit/Vol | G19: Price/Unit | H19: TOTAL | J19: 45658 | K19: 45689 | L19: 45717 | M19: 45748 | N19: 45778 | O19: 45809 | P19: 45839 | Q19: 45870 | R19: 45901 | S19: 45931 | T19: 45962 | U19: 45992
B20: P35 | C20: 0.11412433 | D20: 1 | E20: Tonnes | F20: =IFERROR(H20/G20,0) -> 0 | H20: =SUM(J20:U20) -> 0 | J20: =J16*$C20*$D20*$G20 -> 0 | K20: =K16*$C$20*$D$20*$G$20 -> 0 | L20: =L16*$C$20*$D$20*$G$20 -> 0 | M20: =M16*$C$20*$D$20*$G$20 -> 0 | N20: =N16*$C$20*$D$20*$G$20 -> 0 | O20: =O16*$C$20*$D$20*$G$20 -> 0 | P20: =P16*$C$20*$D$20*$G$20 -> 0 | Q20: =Q16*$C$20*$D$20*$G$20 -> 0 | R20: =R16*$C$20*$D$20*$G$20 -> 0 | ... U20: =U16*$C$20*$D$20*$G$20 -> 0 | W20: =$W$17*C20 -> #DIV/0! | X20: =B20 -> P35
B21: S30 | C21: 0.07 | D21: 1 | E21: Tonnes | F21: =IFERROR(H21/G21,0) -> 0 | H21: =SUM(J21:U21) -> 0 | J21: =J16*$C$21*$D$21*$G$21 -> 0 | K21: =K16*$C$21*$D$21*$G$21 -> 0 | L21: =L16*$C$21*$D$21*$G$21 -> 0 | M21: =M16*$C$21*$D$21*$G$21 -> 0 | N21: =N16*$C$21*$D$21*$G$21 -> 0 | O21: =O16*$C$21*$D$21*$G$21 -> 0 | P21: =P16*$C$21*$D$21*$G$21 -> 0 | Q21: =Q16*$C$21*$D$21*$G$21 -> 0 | ... U21: =U16*$C$21*$D$21*$G$21 -> 0 | W21: =$W$17*C21 -> #DIV/0! | X21: =B21 -> S30
B22: S20 | C22: 0 | D22: 1 | E22: Tonnes | F22: =IFERROR(H22/G22,0) -> 0 | H22: =SUM(J22:U22) -> 0 | J22: =J16*$C$22*$D$22*$G$22 -> 0 | K22: =K16*$C$22*$D$22*$G$22 -> 0 | L22: =L16*$C$22*$D$22*$G$22 -> 0 | M22: =M16*$C$22*$D$22*$G$22 -> 0 | N22: =N16*$C$22*$D$22*$G$22 -> 0 | O22: =O16*$C$22*$D$22*$G$22 -> 0 | P22: =P16*$C$22*$D$22*$G$22 -> 0 | Q22: =Q16*$C$22*$D$22*$G$22 -> 0 | ... U22: =U16*$C$22*$D$22*$G$22 -> 0 | W22: =$W$17*C22 -> #DIV/0! | X22: =B22 -> S20
B23: Domestic Pulp | C23: 0.05 | D23: 1 | E23: Tonnes | F23: =IFERROR(H23/G23,0) -> 0 | H23: =SUM(J23:U23) -> 0 | J23: =J16*$C$23*$D$23*$G$23 -> 0 | K23: =K16*$C$23*$D$23*$G$23 -> 0 | L23: =L16*$C$23*$D$23*$G$23 -> 0 | M23: =M16*$C$23*$D$23*$G$23 -> 0 | N23: =N16*$C$23*$D$23*$G$23 -> 0 | O23: =O16*$C$23*$D$23*$G$23 -> 0 | P23: =P16*$C$23*$D$23*$G$23 -> 0 | Q23: =Q16*$C$23*$D$23*$G$23 -> 0 | ... U23: =U16*$C$23*$D$23*$G$23 -> 0 | W23: =$W$17*C23 -> #DIV/0! | X23: =B23 -> Domestic Pulp
B24: Eucalyptus | C24: 0 | D24: 1 | E24: Tonnes | F24: =IFERROR(H24/G24,0) -> 0 | H24: =SUM(J24:U24) -> 0 | J24: =J16*$C$24*$D$24*$G$24 -> 0 | K24: =K16*$C$24*$D$24*$G$24 -> 0 | L24: =L16*$C$24*$D$24*$G$24 -> 0 | M24: =M16*$C$24*$D$24*$G$24 -> 0 | N24: =N16*$C$24*$D$24*$G$24 -> 0 | O24: =O16*$C$24*$D$24*$G$24 -> 0 | P24: =P16*$C$24*$D$24*$G$24 -> 0 | Q24: =Q16*$C$24*$D$24*$G$24 -> 0 | ... U24: =U16*$C$24*$D$24*$G$24 -> 0 | W24: =$W$17*C24 -> #DIV/0! | X24: =B24 -> Eucalyptus
B25: FW | C25: 0 | D25: 1 | E25: Tonnes | F25: =IFERROR(H25/G25,0) -> 0 | H25: =SUM(J25:U25) -> 0 | J25: =J16*$C$25*$D$25*$G$25 -> 0 | K25: =K16*$C$25*$D$25*$G$25 -> 0 | L25: =L16*$C$25*$D$25*$G$25 -> 0 | M25: =M16*$C$25*$D$25*$G$25 -> 0 | N25: =N16*$C$25*$D$25*$G$25 -> 0 | O25: =O16*$C$25*$D$25*$G$25 -> 0 | P25: =P16*$C$25*$D$25*$G$25 -> 0 | Q25: =Q16*$C$25*$D$25*$G$25 -> 0 | ... U25: =U16*$C$25*$D$25*$G$25 -> 0 | W25: =$W$17*C25 -> #DIV/0! | X25: =B25 -> FW
B26: Euc Pulp | C26: 0 | D26: 1 | E26: Tonnes | F26: =IFERROR(H26/G26,0) -> 0 | H26: =SUM(J26:U26) -> 0 | J26: =J16*$C$26*$D$26*$G$26 -> 0 | K26: =K16*$C$26*$D$26*$G$26 -> 0 | L26: =L16*$C$26*$D$26*$G$26 -> 0 | M26: =M16*$C$26*$D$26*$G$26 -> 0 | N26: =N16*$C$26*$D$26*$G$26 -> 0 | O26: =O16*$C$26*$D$26*$G$26 -> 0 | P26: =P16*$C$26*$D$26*$G$26 -> 0 | Q26: =Q16*$C$26*$D$26*$G$26 -> 0 | ... U26: =U16*$C$26*$D$26*$G$26 -> 0 | W26: =$W$17*C26 -> #DIV/0! | X26: =B26 -> Euc Pulp
B27: Binwood | C27: 0 | D27: 1 | E27: Tonnes | F27: =IFERROR(H27/G27,0) -> 0 | H27: =SUM(J27:U27) -> 0 | J27: =J16*$C$27*$D$27*$G$27 -> 0 | K27: =K16*$C$27*$D$27*$G$27 -> 0 | L27: =L16*$C$27*$D$27*$G$27 -> 0 | M27: =M16*$C$27*$D$27*$G$27 -> 0 | N27: =N16*$C$27*$D$27*$G$27 -> 0 | O27: =O16*$C$27*$D$27*$G$27 -> 0 | P27: =P16*$C$27*$D$27*$G$27 -> 0 | Q27: =Q16*$C$27*$D$27*$G$27 -> 0 | ... U27: =U16*$C$27*$D$27*$G$27 -> 0 | W27: =$W$17*C27 -> #DIV/0! | X27: =B27 -> Binwood
B28: Spare Grade | C28: 0 | E28: Tonnes | F28: =IFERROR(H28/G28/D28,0) -> 0 | H28: =SUM(J28:U28) -> 0 | J28: =J16*$C$28*$D$28*$G$28 -> 0 | K28: =K16*$C$28*$D$28*$G$28 -> 0 | L28: =L16*$C$28*$D$28*$G$28 -> 0 | M28: =M16*$C$28*$D$28*$G$28 -> 0 | N28: =N16*$C$28*$D$28*$G$28 -> 0 | O28: =O16*$C$28*$D$28*$G$28 -> 0 | P28: =P16*$C$28*$D$28*$G$28 -> 0 | Q28: =Q16*$C$28*$D$28*$G$28 -> 0 | ... U28: =U16*$C$28*$D$28*$G$28 -> 0 | W28: =$W$17*C28 -> #DIV/0! | X28: =B28 -> Spare Grade
B29: P40 | C29: 0 | D29: 1 | E29: JAS | F29: =IFERROR(H29/G29/D29,0) -> 0 | H29: =SUM(J29:U29) -> 0 | J29: =J16*$C$29*$D$29*$G$29 -> 0 | K29: =K16*$C$29*$D$29*$G$29 -> 0 | L29: =L16*$C$29*$D$29*$G$29 -> 0 | M29: =M16*$C$29*$D$29*$G$29 -> 0 | N29: =N16*$C$29*$D$29*$G$29 -> 0 | O29: =O16*$C$29*$D$29*$G$29 -> 0 | P29: =P16*$C$29*$D$29*$G$29 -> 0 | Q29: =Q16*$C$29*$D$29*$G$29 -> 0 | ... U29: =U16*$C$29*$D$29*$G$29 -> 0 | W29: =$W$17*C29 -> #DIV/0! | X29: =B29 -> P40
B30: P30 | C30: 0.0019336678 | D30: 1.0288961 | E30: JAS | F30: =IFERROR(H30/G30/D30,0) -> 0 | H30: =SUM(J30:U30) -> 0 | J30: =J16*$C$30*$D$30*$G$30 -> 0 | K30: =K16*$C$30*$D$30*$G$30 -> 0 | L30: =L16*$C$30*$D$30*$G$30 -> 0 | M30: =M16*$C$30*$D$30*$G$30 -> 0 | N30: =N16*$C$30*$D$30*$G$30 -> 0 | O30: =O16*$C$30*$D$30*$G$30 -> 0 | P30: =P16*$C$30*$D$30*$G$30 -> 0 | Q30: =Q16*$C$30*$D$30*$G$30 -> 0 | ... U30: =U16*$C$30*$D$30*$G$30 -> 0 | W30: =$W$17*C30 -> #DIV/0! | X30: =B30 -> P30
B31: AO | C31: 0.15 | D31: 1.04 | E31: JAS | F31: =IFERROR(H31/G31/D31,0) -> 0 | H31: =SUM(J31:U31) -> 0 | J31: =J16*$C$31*$D$31*$G$31 -> 0 | K31: =K16*$C$31*$D$31*$G$31 -> 0 | L31: =L16*$C$31*$D$31*$G$31 -> 0 | M31: =M16*$C$31*$D$31*$G$31 -> 0 | N31: =N16*$C$31*$D$31*$G$31 -> 0 | O31: =O16*$C$31*$D$31*$G$31 -> 0 | P31: =P16*$C$31*$D$31*$G$31 -> 0 | Q31: =Q16*$C$31*$D$31*$G$31 -> 0 | ... U31: =U16*$C$31*$D$31*$G$31 -> 0 | W31: =$W$17*C31 -> #DIV/0! | X31: =B31 -> AO
B32: A | C32: 0.28 | D32: 1.01 | E32: JAS | F32: =IFERROR(H32/G32/D32,0) -> 0 | H32: =SUM(J32:U32) -> 0 | J32: =J16*$C$32*$D$32*$G$32 -> 0 | K32: =K16*$C$32*$D$32*$G$32 -> 0 | L32: =L16*$C$32*$D$32*$G$32 -> 0 | M32: =M16*$C$32*$D$32*$G$32 -> 0 | N32: =N16*$C$32*$D$32*$G$32 -> 0 | O32: =O16*$C$32*$D$32*$G$32 -> 0 | P32: =P16*$C$32*$D$32*$G$32 -> 0 | Q32: =Q16*$C$32*$D$32*$G$32 -> 0 | ... U32: =U16*$C$32*$D$32*$G$32 -> 0 | W32: =$W$17*C32 -> #DIV/0! | X32: =B32 -> A
B33: K | C33: 0.20870336 | D33: 0.96 | E33: JAS | F33: =IFERROR(H33/G33/D33,0) -> 0 | H33: =SUM(J33:U33) -> 0 | J33: =J16*$C$33*$D$33*$G$33 -> 0 | K33: =K16*$C$33*$D$33*$G$33 -> 0 | L33: =L16*$C$33*$D$33*$G$33 -> 0 | M33: =M16*$C$33*$D$33*$G$33 -> 0 | N33: =N16*$C$33*$D$33*$G$33 -> 0 | O33: =O16*$C$33*$D$33*$G$33 -> 0 | P33: =P16*$C$33*$D$33*$G$33 -> 0 | Q33: =Q16*$C$33*$D$33*$G$33 -> 0 | ... U33: =U16*$C$33*$D$33*$G$33 -> 0 | W33: =$W$17*C33 -> #DIV/0! | X33: =B33 -> K
B34: KI | C34: 0.025784396 | D34: 0.97 | E34: JAS | F34: =IFERROR(H34/G34/D34,0) -> 0 | H34: =SUM(J34:U34) -> 0 | J34: =J16*$C$34*$D$34*$G$34 -> 0 | K34: =K16*$C$34*$D$34*$G$34 -> 0 | L34: =L16*$C$34*$D$34*$G$34 -> 0 | M34: =M16*$C$34*$D$34*$G$34 -> 0 | N34: =N16*$C$34*$D$34*$G$34 -> 0 | O34: =O16*$C$34*$D$34*$G$34 -> 0 | P34: =P16*$C$34*$D$34*$G$34 -> 0 | Q34: =Q16*$C$34*$D$34*$G$34 -> 0 | ... U34: =U16*$C$34*$D$34*$G$34 -> 0 | W34: =$W$17*C34 -> #DIV/0! | X34: =B34 -> KI
B35: KIS | C35: 0.1017521 | D35: 0.92 | E35: JAS | F35: =IFERROR(H35/G35/D35,0) -> 0 | H35: =SUM(J35:U35) -> 0 | J35: =J16*$C$35*$D$35*$G$35 -> 0 | K35: =K16*$C$35*$D$35*$G$35 -> 0 | L35: =L16*$C$35*$D$35*$G$35 -> 0 | M35: =M16*$C$35*$D$35*$G$35 -> 0 | N35: =N16*$C$35*$D$35*$G$35 -> 0 | O35: =O16*$C$35*$D$35*$G$35 -> 0 | P35: =P16*$C$35*$D$35*$G$35 -> 0 | Q35: =Q16*$C$35*$D$35*$G$35 -> 0 | ... U35: =U16*$C$35*$D$35*$G$35 -> 0 | W35: =$W$17*C35 -> #DIV/0! | X35: =B35 -> KIS
B36: KI stub | E36: JAS | F36: =IFERROR(H36/G36/D36,0) -> 0 | H36: =SUM(J36:U36) -> 0 | J36: =J16*$C$36*$D$36*$G$36 -> 0 | K36: =K16*$C$36*$D$36*$G$36 -> 0 | L36: =L16*$C$36*$D$36*$G$36 -> 0 | M36: =M16*$C$36*$D$36*$G$36 -> 0 | N36: =N16*$C$36*$D$36*$G$36 -> 0 | O36: =O16*$C$36*$D$36*$G$36 -> 0 | P36: =P16*$C$36*$D$36*$G$36 -> 0 | Q36: =Q16*$C$36*$D$36*$G$36 -> 0 | ... U36: =U16*$C$36*$D$36*$G$36 -> 0 | W36: =$W$17*C36 -> #DIV/0! | X36: =B36 -> KI stub
B37: CF+ | E37: JAS | F37: =IFERROR(H37/G37/D37,0) -> 0 | H37: =SUM(J37:U37) -> 0 | J37: =J16*$C$37*$D$37*$G$37 -> 0 | K37: =K16*$C$37*$D$37*$G$37 -> 0 | L37: =L16*$C$37*$D$37*$G$37 -> 0 | M37: =M16*$C$37*$D$37*$G$37 -> 0 | N37: =N16*$C$37*$D$37*$G$37 -> 0 | O37: =O16*$C$37*$D$37*$G$37 -> 0 | P37: =P16*$C$37*$D$37*$G$37 -> 0 | Q37: =Q16*$C$37*$D$37*$G$37 -> 0 | ... U37: =U16*$C$37*$D$37*$G$37 -> 0 | W37: =$W$17*C37 -> #DIV/0! | X37: =B37 -> CF+
B38: CF- | E38: JAS | F38: =IFERROR(H38/G38/D38,0) -> 0 | H38: =SUM(J38:U38) -> 0 | J38: =J16*$C$38*$D$38*$G$38 -> 0 | K38: =K16*$C$38*$D$38*$G$38 -> 0 | L38: =L16*$C$38*$D$38*$G$38 -> 0 | M38: =M16*$C$38*$D$38*$G$38 -> 0 | N38: =N16*$C$38*$D$38*$G$38 -> 0 | O38: =O16*$C$38*$D$38*$G$38 -> 0 | P38: =P16*$C$38*$D$38*$G$38 -> 0 | Q38: =Q16*$C$38*$D$38*$G$38 -> 0 | ... U38: =U16*$C$38*$D$38*$G$38 -> 0 | W38: =$W$17*C38 -> #DIV/0! | X38: =B38 -> CF-
B39: CM | E39: JAS | F39: =IFERROR(H39/G39/D39,0) -> 0 | H39: =SUM(J39:U39) -> 0 | J39: =J16*$C$39*$D$39*$G$39 -> 0 | K39: =K16*$C$39*$D$39*$G$39 -> 0 | L39: =L16*$C$39*$D$39*$G$39 -> 0 | M39: =M16*$C$39*$D$39*$G$39 -> 0 | N39: =N16*$C$39*$D$39*$G$39 -> 0 | O39: =O16*$C$39*$D$39*$G$39 -> 0 | P39: =P16*$C$39*$D$39*$G$39 -> 0 | Q39: =Q16*$C$39*$D$39*$G$39 -> 0 | ... U39: =U16*$C$39*$D$39*$G$39 -> 0 | W39: =$W$17*C39 -> #DIV/0! | X39: =B39 -> CM
B40: Euc A | E40: JAS | F40: =IFERROR(H40/G40/D40,0) -> 0 | H40: =SUM(J40:U40) -> 0 | J40: =J16*$C$40*$D$40*$G$40 -> 0 | K40: =K16*$C$40*$D$40*$G$40 -> 0 | L40: =L16*$C$40*$D$40*$G$40 -> 0 | M40: =M16*$C$40*$D$40*$G$40 -> 0 | N40: =N16*$C$40*$D$40*$G$40 -> 0 | O40: =O16*$C$40*$D$40*$G$40 -> 0 | P40: =P16*$C$40*$D$40*$G$40 -> 0 | Q40: =Q16*$C$40*$D$40*$G$40 -> 0 | ... U40: =U16*$C$40*$D$40*$G$40 -> 0 | W40: =$W$17*C40 -> #DIV/0! | X40: =B40 -> Euc A
B41: Euc K | H41: =SUM(J41:U41) -> 0 | J41: =J16*$C$41*$D$41*$G$41 -> 0 | K41: =K16*$C$41*$D$41*$G$41 -> 0 | L41: =L16*$C$41*$D$41*$G$41 -> 0 | M41: =M16*$C$41*$D$41*$G$41 -> 0 | N41: =N16*$C$41*$D$41*$G$41 -> 0 | O41: =O16*$C$41*$D$41*$G$41 -> 0 | P41: =P16*$C$41*$D$41*$G$41 -> 0 | Q41: =Q16*$C$41*$D$41*$G$41 -> 0 | ... U41: =U16*$C$41*$D$41*$G$41 -> 0 | W41: =$W$17*C41 -> #DIV/0! | X41: =B41 -> Euc K
C42: =SUM(C20:C41) -> 1.0022978
B43: Export Sales | C43: =SUMIF(E20:E41,"JAS",C20:C41) -> 0.76817352 | H43: =SUM(J43:U43) -> 0 | J43: =SUM(J28:J41) -> 0 | K43: =SUM(K28:K41) -> 0 | L43: =SUM(L28:L41) -> 0 | M43: =SUM(M28:M41) -> 0 | N43: =SUM(N28:N41) -> 0 | O43: =SUM(O28:O41) -> 0 | P43: =SUM(P28:P41) -> 0 | Q43: =SUM(Q28:Q41) -> 0 | ... U43: =SUM(U28:U41) -> 0 | W43: =SUM(W20:W42) -> #DIV/0!
B44: Domestic Sales | C44: =SUMIF(E20:E41,"Tonnes",C20:C41) -> 0.23412433 | H44: =SUM(J44:U44) -> 0 | J44: =SUM(J20:J27) -> 0 | K44: =SUM(K20:K27) -> 0 | L44: =SUM(L20:L27) -> 0 | M44: =SUM(M20:M27) -> 0 | N44: =SUM(N20:N27) -> 0 | O44: =SUM(O20:O27) -> 0 | P44: =SUM(P20:P27) -> 0 | Q44: =SUM(Q20:Q27) -> 0 | ... U44: =SUM(U20:U27) -> 0
B46: TOTAL | G46: =H46/W16 -> #DIV/0! | H46: =SUM(H20:H41) -> 0 | J46: =SUM(J20:J41) -> 0 | K46: =SUM(K20:K41) -> 0 | L46: =SUM(L20:L41) -> 0 | M46: =SUM(M20:M41) -> 0 | N46: =SUM(N20:N41) -> 0 | O46: =SUM(O20:O41) -> 0 | P46: =SUM(P20:P41) -> 0 | Q46: =SUM(Q20:Q41) -> 0 | ... U46: =SUM(U20:U41) -> 0 | W46: =SUM(J46:U46) -> 0
B48: COSTS | C48: Op Code | D48: Activity
B49: Log and Load | C49: 300/01 | D49: Logging
H50: TOTAL | J50: 45658 | K50: 45689 | L50: 45717 | M50: 45748 | N50: 45778 | O50: 45809 | P50: 45839 | Q50: 45870 | R50: 45901 | S50: 45931 | T50: 45962 | U50: 45992
G51: =H51/W16 -> #DIV/0! | H51: =SUM(J51:U51) -> 0 | J51: =J16*J13 -> 0 | K51: =K16*K13 -> 0 | L51: =L16*L13 -> 0 | M51: =M16*M13 -> 0 | N51: =N16*N13 -> 0 | O51: =O16*O13 -> 0 | P51: =P16*P13 -> 0 | Q51: =Q16*Q13 -> 0 | ... U51: =U16*U13 -> 0 | W51: =SUM(J51:U51) -> 0
B54: Log Transport
B55: Grade | C55: Op Code | D55: Activity | E55: Destination | F55: Destination | G55: Cost/t | H55: TOTAL | J55: 45658 | K55: 45689 | L55: 45717 | M55: 45748 | N55: 45778 | O55: 45809 | P55: 45839 | Q55: 45870 | R55: 45901 | S55: 45931 | T55: 45962 | U55: 45992
B56: P35 | C56: 300/02 | D56: Transport | E56: Domestic | H56: =SUM(J56:U56) -> 0 | J56: =IF($C20>0,(J$16*$C20)*$G56,0) -> 0 | K56: =IF($C20>0,(K$16*$C20)*$G56,0) -> 0 | L56: =IF($C20>0,(L$16*$C20)*$G56,0) -> 0 | M56: =IF($C20>0,(M$16*$C20)*$G56,0) -> 0 | N56: =IF($C20>0,(N$16*$C20)*$G56,0) -> 0 | O56: =IF($C20>0,(O$16*$C20)*$G56,0) -> 0 | P56: =IF($C20>0,(P$16*$C20)*$G56,0) -> 0 | Q56: =IF($C20>0,(Q$16*$C20)*$G56,0) -> 0 | ... U56: =IF($C20>0,(U$16*$C20)*$G56,0) -> 0
B57: S30 | C57: 300/02 | D57: Transport | E57: Domestic | H57: =SUM(J57:U57) -> 0 | J57: =IF($C21>0,(J$16*$C21)*$G57,0) -> 0 | K57: =IF($C21>0,(K$16*$C21)*$G57,0) -> 0 | L57: =IF($C21>0,(L$16*$C21)*$G57,0) -> 0 | M57: =IF($C21>0,(M$16*$C21)*$G57,0) -> 0 | N57: =IF($C21>0,(N$16*$C21)*$G57,0) -> 0 | O57: =IF($C21>0,(O$16*$C21)*$G57,0) -> 0 | P57: =IF($C21>0,(P$16*$C21)*$G57,0) -> 0 | Q57: =IF($C21>0,(Q$16*$C21)*$G57,0) -> 0 | ... U57: =IF($C21>0,(U$16*$C21)*$G57,0) -> 0
B58: S20 | C58: 300/02 | D58: Transport | E58: Domestic | H58: =SUM(J58:U58) -> 0 | J58: =IF($C22>0,(J$16*$C22)*$G58,0) -> 0 | K58: =IF($C22>0,(K$16*$C22)*$G58,0) -> 0 | L58: =IF($C22>0,(L$16*$C22)*$G58,0) -> 0 | M58: =IF($C22>0,(M$16*$C22)*$G58,0) -> 0 | N58: =IF($C22>0,(N$16*$C22)*$G58,0) -> 0 | O58: =IF($C22>0,(O$16*$C22)*$G58,0) -> 0 | P58: =IF($C22>0,(P$16*$C22)*$G58,0) -> 0 | Q58: =IF($C22>0,(Q$16*$C22)*$G58,0) -> 0 | ... U58: =IF($C22>0,(U$16*$C22)*$G58,0) -> 0
B59: Domestic Pulp | C59: 300/02 | D59: Transport | E59: Domestic | H59: =SUM(J59:U59) -> 0 | J59: =IF($C23>0,(J$16*$C23)*$G59,0) -> 0 | K59: =IF($C23>0,(K$16*$C23)*$G59,0) -> 0 | L59: =IF($C23>0,(L$16*$C23)*$G59,0) -> 0 | M59: =IF($C23>0,(M$16*$C23)*$G59,0) -> 0 | N59: =IF($C23>0,(N$16*$C23)*$G59,0) -> 0 | O59: =IF($C23>0,(O$16*$C23)*$G59,0) -> 0 | P59: =IF($C23>0,(P$16*$C23)*$G59,0) -> 0 | Q59: =IF($C23>0,(Q$16*$C23)*$G59,0) -> 0 | ... U59: =IF($C23>0,(U$16*$C23)*$G59,0) -> 0
B60: Eucalyptus | C60: 300/02 | D60: Transport | E60: Domestic | H60: =SUM(J60:U60) -> 0 | J60: =IF($C24>0,(J$16*$C24)*$G60,0) -> 0 | K60: =IF($C24>0,(K$16*$C24)*$G60,0) -> 0 | L60: =IF($C24>0,(L$16*$C24)*$G60,0) -> 0 | M60: =IF($C24>0,(M$16*$C24)*$G60,0) -> 0 | N60: =IF($C24>0,(N$16*$C24)*$G60,0) -> 0 | O60: =IF($C24>0,(O$16*$C24)*$G60,0) -> 0 | P60: =IF($C24>0,(P$16*$C24)*$G60,0) -> 0 | Q60: =IF($C24>0,(Q$16*$C24)*$G60,0) -> 0 | ... U60: =IF($C24>0,(U$16*$C24)*$G60,0) -> 0
B61: FW | C61: 300/02 | D61: Transport | E61: Domestic | H61: =SUM(J61:U61) -> 0 | J61: =IF($C25>0,(J$16*$C25)*$G61,0) -> 0 | K61: =IF($C25>0,(K$16*$C25)*$G61,0) -> 0 | L61: =IF($C25>0,(L$16*$C25)*$G61,0) -> 0 | M61: =IF($C25>0,(M$16*$C25)*$G61,0) -> 0 | N61: =IF($C25>0,(N$16*$C25)*$G61,0) -> 0 | O61: =IF($C25>0,(O$16*$C25)*$G61,0) -> 0 | P61: =IF($C25>0,(P$16*$C25)*$G61,0) -> 0 | Q61: =IF($C25>0,(Q$16*$C25)*$G61,0) -> 0 | ... U61: =IF($C25>0,(U$16*$C25)*$G61,0) -> 0
B62: Euc Pulp | C62: 300/02 | D62: Transport | E62: Domestic | H62: =SUM(J62:U62) -> 0 | J62: =IF($C26>0,(J$16*$C26)*$G62,0) -> 0 | K62: =IF($C26>0,(K$16*$C26)*$G62,0) -> 0 | L62: =IF($C26>0,(L$16*$C26)*$G62,0) -> 0 | M62: =IF($C26>0,(M$16*$C26)*$G62,0) -> 0 | N62: =IF($C26>0,(N$16*$C26)*$G62,0) -> 0 | O62: =IF($C26>0,(O$16*$C26)*$G62,0) -> 0 | P62: =IF($C26>0,(P$16*$C26)*$G62,0) -> 0 | Q62: =IF($C26>0,(Q$16*$C26)*$G62,0) -> 0 | ... U62: =IF($C26>0,(U$16*$C26)*$G62,0) -> 0
B63: Binwood | C63: 300/02 | D63: Transport | E63: Domestic | H63: =SUM(J63:U63) -> 0 | J63: =IF($C27>0,(J$16*$C27)*$G63,0) -> 0 | K63: =IF($C27>0,(K$16*$C27)*$G63,0) -> 0 | L63: =IF($C27>0,(L$16*$C27)*$G63,0) -> 0 | M63: =IF($C27>0,(M$16*$C27)*$G63,0) -> 0 | N63: =IF($C27>0,(N$16*$C27)*$G63,0) -> 0 | O63: =IF($C27>0,(O$16*$C27)*$G63,0) -> 0 | P63: =IF($C27>0,(P$16*$C27)*$G63,0) -> 0 | Q63: =IF($C27>0,(Q$16*$C27)*$G63,0) -> 0 | ... U63: =IF($C27>0,(U$16*$C27)*$G63,0) -> 0
B64: P40 | C64: 300/02 | D64: Transport | E64: AWG | H64: =SUM(J64:U64) -> 0 | J64: =IF($C29>0,(J$16*$C29)*$G64,0) -> 0 | K64: =IF($C29>0,(K$16*$C29)*$G64,0) -> 0 | L64: =IF($C29>0,(L$16*$C29)*$G64,0) -> 0 | M64: =IF($C29>0,(M$16*$C29)*$G64,0) -> 0 | N64: =IF($C29>0,(N$16*$C29)*$G64,0) -> 0 | O64: =IF($C29>0,(O$16*$C29)*$G64,0) -> 0 | P64: =IF($C29>0,(P$16*$C29)*$G64,0) -> 0 | Q64: =IF($C29>0,(Q$16*$C29)*$G64,0) -> 0 | ... U64: =IF($C29>0,(U$16*$C29)*$G64,0) -> 0
B65: P30 | C65: 300/02 | D65: Transport | E65: AWG | H65: =SUM(J65:U65) -> 0 | J65: =IF($C30>0,(J$16*$C30)*$G65,0) -> 0 | K65: =IF($C30>0,(K$16*$C30)*$G65,0) -> 0 | L65: =IF($C30>0,(L$16*$C30)*$G65,0) -> 0 | M65: =IF($C30>0,(M$16*$C30)*$G65,0) -> 0 | N65: =IF($C30>0,(N$16*$C30)*$G65,0) -> 0 | O65: =IF($C30>0,(O$16*$C30)*$G65,0) -> 0 | P65: =IF($C30>0,(P$16*$C30)*$G65,0) -> 0 | Q65: =IF($C30>0,(Q$16*$C30)*$G65,0) -> 0 | ... U65: =IF($C30>0,(U$16*$C30)*$G65,0) -> 0
B66: AO | C66: 300/02 | D66: Transport | E66: AWG | H66: =SUM(J66:U66) -> 0 | J66: =IF($C31>0,(J$16*$C31)*$G66,0) -> 0 | K66: =IF($C31>0,(K$16*$C31)*$G66,0) -> 0 | L66: =IF($C31>0,(L$16*$C31)*$G66,0) -> 0 | M66: =IF($C31>0,(M$16*$C31)*$G66,0) -> 0 | N66: =IF($C31>0,(N$16*$C31)*$G66,0) -> 0 | O66: =IF($C31>0,(O$16*$C31)*$G66,0) -> 0 | P66: =IF($C31>0,(P$16*$C31)*$G66,0) -> 0 | Q66: =IF($C31>0,(Q$16*$C31)*$G66,0) -> 0 | ... U66: =IF($C31>0,(U$16*$C31)*$G66,0) -> 0
B67: A | C67: 300/02 | D67: Transport | E67: AWG | H67: =SUM(J67:U67) -> 0 | J67: =IF($C32>0,(J$16*$C32)*$G67,0) -> 0 | K67: =IF($C32>0,(K$16*$C32)*$G67,0) -> 0 | L67: =IF($C32>0,(L$16*$C32)*$G67,0) -> 0 | M67: =IF($C32>0,(M$16*$C32)*$G67,0) -> 0 | N67: =IF($C32>0,(N$16*$C32)*$G67,0) -> 0 | O67: =IF($C32>0,(O$16*$C32)*$G67,0) -> 0 | P67: =IF($C32>0,(P$16*$C32)*$G67,0) -> 0 | Q67: =IF($C32>0,(Q$16*$C32)*$G67,0) -> 0 | ... U67: =IF($C32>0,(U$16*$C32)*$G67,0) -> 0
B68: K | C68: 300/02 | D68: Transport | E68: AWG | H68: =SUM(J68:U68) -> 0 | J68: =IF($C33>0,(J$16*$C33)*$G68,0) -> 0 | K68: =IF($C33>0,(K$16*$C33)*$G68,0) -> 0 | L68: =IF($C33>0,(L$16*$C33)*$G68,0) -> 0 | M68: =IF($C33>0,(M$16*$C33)*$G68,0) -> 0 | N68: =IF($C33>0,(N$16*$C33)*$G68,0) -> 0 | O68: =IF($C33>0,(O$16*$C33)*$G68,0) -> 0 | P68: =IF($C33>0,(P$16*$C33)*$G68,0) -> 0 | Q68: =IF($C33>0,(Q$16*$C33)*$G68,0) -> 0 | ... U68: =IF($C33>0,(U$16*$C33)*$G68,0) -> 0
B69: KI | C69: 300/02 | D69: Transport | E69: AWG | H69: =SUM(J69:U69) -> 0 | J69: =IF($C34>0,(J$16*$C34)*$G69,0) -> 0 | K69: =IF($C34>0,(K$16*$C34)*$G69,0) -> 0 | L69: =IF($C34>0,(L$16*$C34)*$G69,0) -> 0 | M69: =IF($C34>0,(M$16*$C34)*$G69,0) -> 0 | N69: =IF($C34>0,(N$16*$C34)*$G69,0) -> 0 | O69: =IF($C34>0,(O$16*$C34)*$G69,0) -> 0 | P69: =IF($C34>0,(P$16*$C34)*$G69,0) -> 0 | Q69: =IF($C34>0,(Q$16*$C34)*$G69,0) -> 0 | ... U69: =IF($C34>0,(U$16*$C34)*$G69,0) -> 0
B70: KIS | C70: 300/02 | D70: Transport | E70: AWG | H70: =SUM(J70:U70) -> 0 | J70: =IF($C35>0,(J$16*$C35)*$G70,0) -> 0 | K70: =IF($C35>0,(K$16*$C35)*$G70,0) -> 0 | L70: =IF($C35>0,(L$16*$C35)*$G70,0) -> 0 | M70: =IF($C35>0,(M$16*$C35)*$G70,0) -> 0 | N70: =IF($C35>0,(N$16*$C35)*$G70,0) -> 0 | O70: =IF($C35>0,(O$16*$C35)*$G70,0) -> 0 | P70: =IF($C35>0,(P$16*$C35)*$G70,0) -> 0 | Q70: =IF($C35>0,(Q$16*$C35)*$G70,0) -> 0 | ... U70: =IF($C35>0,(U$16*$C35)*$G70,0) -> 0
B71: KI stub | C71: 300/02 | D71: Transport | E71: AWG | H71: =SUM(J71:U71) -> 0 | J71: =IF($C36>0,(J$16*$C36)*$G71,0) -> 0 | K71: =IF($C36>0,(K$16*$C36)*$G71,0) -> 0 | L71: =IF($C36>0,(L$16*$C36)*$G71,0) -> 0 | M71: =IF($C36>0,(M$16*$C36)*$G71,0) -> 0 | N71: =IF($C36>0,(N$16*$C36)*$G71,0) -> 0 | O71: =IF($C36>0,(O$16*$C36)*$G71,0) -> 0 | P71: =IF($C36>0,(P$16*$C36)*$G71,0) -> 0 | Q71: =IF($C36>0,(Q$16*$C36)*$G71,0) -> 0 | ... U71: =IF($C36>0,(U$16*$C36)*$G71,0) -> 0
B72: CF+ | C72: 300/02 | D72: Transport | E72: AWG | H72: =SUM(J72:U72) -> 0 | J72: =IF($C37>0,(J$16*$C37)*$G72,0) -> 0 | K72: =IF($C37>0,(K$16*$C37)*$G72,0) -> 0 | L72: =IF($C37>0,(L$16*$C37)*$G72,0) -> 0 | M72: =IF($C37>0,(M$16*$C37)*$G72,0) -> 0 | N72: =IF($C37>0,(N$16*$C37)*$G72,0) -> 0 | O72: =IF($C37>0,(O$16*$C37)*$G72,0) -> 0 | P72: =IF($C37>0,(P$16*$C37)*$G72,0) -> 0 | Q72: =IF($C37>0,(Q$16*$C37)*$G72,0) -> 0 | ... U72: =IF($C37>0,(U$16*$C37)*$G72,0) -> 0
B73: CF- | C73: 300/02 | D73: Transport | E73: AWG | H73: =SUM(J73:U73) -> 0 | J73: =IF($C38>0,(J$16*$C38)*$G73,0) -> 0 | K73: =IF($C38>0,(K$16*$C38)*$G73,0) -> 0 | L73: =IF($C38>0,(L$16*$C38)*$G73,0) -> 0 | M73: =IF($C38>0,(M$16*$C38)*$G73,0) -> 0 | N73: =IF($C38>0,(N$16*$C38)*$G73,0) -> 0 | O73: =IF($C38>0,(O$16*$C38)*$G73,0) -> 0 | P73: =IF($C38>0,(P$16*$C38)*$G73,0) -> 0 | Q73: =IF($C38>0,(Q$16*$C38)*$G73,0) -> 0 | ... U73: =IF($C38>0,(U$16*$C38)*$G73,0) -> 0
B74: CM | C74: 300/02 | D74: Transport | E74: AWG | H74: =SUM(J74:U74) -> 0 | J74: =IF($C39>0,(J$16*$C39)*$G74,0) -> 0 | K74: =IF($C39>0,(K$16*$C39)*$G74,0) -> 0 | L74: =IF($C39>0,(L$16*$C39)*$G74,0) -> 0 | M74: =IF($C39>0,(M$16*$C39)*$G74,0) -> 0 | N74: =IF($C39>0,(N$16*$C39)*$G74,0) -> 0 | O74: =IF($C39>0,(O$16*$C39)*$G74,0) -> 0 | P74: =IF($C39>0,(P$16*$C39)*$G74,0) -> 0 | Q74: =IF($C39>0,(Q$16*$C39)*$G74,0) -> 0 | ... U74: =IF($C39>0,(U$16*$C39)*$G74,0) -> 0
B75: Euc A | C75: 300/02 | D75: Transport | E75: AWG | H75: =SUM(J75:U75) -> 0 | J75: =IF($C40>0,(J$16*$C40)*$G75,0) -> 0 | K75: =IF($C40>0,(K$16*$C40)*$G75,0) -> 0 | L75: =IF($C40>0,(L$16*$C40)*$G75,0) -> 0 | M75: =IF($C40>0,(M$16*$C40)*$G75,0) -> 0 | N75: =IF($C40>0,(N$16*$C40)*$G75,0) -> 0 | O75: =IF($C40>0,(O$16*$C40)*$G75,0) -> 0 | P75: =IF($C40>0,(P$16*$C40)*$G75,0) -> 0 | Q75: =IF($C40>0,(Q$16*$C40)*$G75,0) -> 0 | ... U75: =IF($C40>0,(U$16*$C40)*$G75,0) -> 0
... B77: Spare grade | C77: 300/02 | D77: Transport | E77: AWG | H77: =SUM(J77:U77) -> 0 | J77: =IF($C42>0,(J$16*$C42)*$G77,0) -> 0 | K77: =IF($C42>0,(K$16*$C42)*$G77,0) -> 0 | L77: =IF($C42>0,(L$16*$C42)*$G77,0) -> 0 | M77: =IF($C42>0,(M$16*$C42)*$G77,0) -> 0 | N77: =IF($C42>0,(N$16*$C42)*$G77,0) -> 0 | O77: =IF($C42>0,(O$16*$C42)*$G77,0) -> 0 | P77: =IF($C42>0,(P$16*$C42)*$G77,0) -> 0 | Q77: =IF($C42>0,(Q$16*$C42)*$G77,0) -> 0 | ... U77: =IF($C42>0,(U$16*$C42)*$G77,0) -> 0
G78: =H78/W16 -> #DIV/0! | H78: =SUM(H56:H77) -> 0 | J78: =SUM(J56:J77) -> 0 | K78: =SUM(K56:K77) -> 0 | L78: =SUM(L56:L77) -> 0 | M78: =SUM(M56:M77) -> 0 | N78: =SUM(N56:N77) -> 0 | O78: =SUM(O56:O77) -> 0 | P78: =SUM(P56:P77) -> 0 | Q78: =SUM(Q56:Q77) -> 0 | ... U78: =SUM(U56:U77) -> 0 | W78: =SUM(J78:U78) -> 0
B80: Non-docket costs
B81: Operation | C81: Op Code | D81: Activity | E81: Resource | F81: Product | G81: Unit Rate | H81: TOTAL | J81: 45658 | K81: 45689 | L81: 45717 | M81: 45748 | N81: 45778 | O81: 45809 | P81: 45839 | Q81: 45870 | R81: 45901 | S81: 45931 | T81: 45962 | U81: 45992
B82: Tracking | C82: 300/04 | D82: Logging | H82: =SUM(J82:U82) -> 0
B83: Logging Machinery establishment/transportation | C83: 300/06 | D83: Logging | E83: 699 | F83: 3675 | H83: =SUM(J83:U83) -> 0
B84: Road control | C84: 300/16 | D84: Logging | E84: 699 | F84: 3691 | H84: =SUM(J84:U84) -> 0
B85: Powerline costs | C85: 300/17 | D85: Logging | E85: 699 | F85: 3677 | H85: =SUM(J85:U85) -> 0
B86: Fencing & gate construction | C86: 721 | D86: Logging | E86: 699 | F86: 3671 | H86: =SUM(J86:U86) -> 0
B87: Deadman | C87: 300/18 | D87: Logging | E87: 699 | F87: 3669 | H87: =SUM(J87:U87) -> 0
B88: Two-stage | C88: 300/19 | D88: Logging | E88: 699 | F88: 3665 | H88: =SUM(J88:U88) -> 0
B89: Harvest Planning | C89: 300/09 | D89: Logging | E89: 699 | F89: 3963 | H89: =SUM(J89:U89) -> 0
B90: Roading machinery establishment/transportation | C90: 300/07 | D90: Infrastructure | H90: =SUM(J90:U90) -> 0
B91: New Road Metalled or sealed | C91: 720 | D91: Infrastructure | H91: =SUM(J91:U91) -> 0 | J91: =J115 -> 0 | K91: =K115 -> 0 | L91: =L115 -> 0 | M91: =M115 -> 0 | N91: =N115 -> 0 | O91: =O115 -> 0 | P91: =P115 -> 0 | Q91: =Q115 -> 0 | ... U91: =U115 -> 0
B92: Upgrade Road metalled or sealed | C92: 720 | D92: Infrastructure | H92: =SUM(J92:U92) -> 0
B93: Other infrastructure | C93: 720 | D93: Infrastructure | H93: =SUM(J93:U93) -> 0
B94: Skid construction | C94: 300/05 | D94: Infrastructure | H94: =SUM(J94:U94) -> 0 | J94: =J119 -> 0 | K94: =K119 -> 0 | L94: =L119 -> 0 | M94: =M119 -> 0 | N94: =N119 -> 0 | O94: =O119 -> 0 | P94: =P119 -> 0 | Q94: =Q119 -> 0 | ... U94: =U119 -> 0
B95: Pad construction | C95: 300/05 | D95: Infrastructure | H95: =SUM(J95:U95) -> 0 | J95: =J120 -> 0 | K95: =K120 -> 0 | L95: =L120 -> 0 | M95: =M120 -> 0 | N95: =N120 -> 0 | O95: =O120 -> 0 | P95: =P120 -> 0 | Q95: =Q120 -> 0 | ... U95: =U120 -> 0
B96: Maintenance Forest Road | C96: 305 | D96: Maintenance | H96: =SUM(J96:U96) -> 0
B97: Maintenance Public Road | C97: 306 | D97: Maintenance | H97: =SUM(J97:U97) -> 0
B98: Skid/Pad maintenance | C98: 300/14 | D98: Post harvest costs | H98: =SUM(J98:U98) -> 0
B99: Post-harvest clean-up | C99: 300/10 | D99: Post harvest costs | H99: =SUM(J99:U99) -> 0
B100: Health and safety and Auditing | C100: 300/11 | D100: Indirect costs | H100: =SUM(J100:U100) -> 0
B101: Weighbridge | C101: 300/03 | D101: Indirect costs | G101: =H101/$W$16 -> #DIV/0! | H101: =SUM(J101:U101) -> 0
B102: Environmental monitoring/consents | C102: 330/04 | D102: Indirect costs | E102: 365 | H102: =SUM(J102:U102) -> 0
B103: Forest levy | C103: 300/08 | D103: Mgmt/Admin | E103: 338 | G103: 0.33 | H103: =SUM(J103:U103) -> 0 | J103: =$G$103*J16 -> 0 | K103: =$G$103*K16 -> 0 | L103: =$G$103*L16 -> 0 | M103: =$G$103*M16 -> 0 | N103: =$G$103*N16 -> 0 | O103: =$G$103*O16 -> 0 | P103: =$G$103*P16 -> 0 | Q103: =$G$103*Q16 -> 0 | ... U103: =$G$103*U16 -> 0
B104: Insurance Payment protection (domestic sales only) | C104: 351 | D104: Mgmt/Admin | E104: 324 | G104: 0.0016 | H104: =SUM(J104:U104) -> 0 | J104: =$G$104*J46/100 -> 0 | K104: =$G$104*K46/100 -> 0 | L104: =$G$104*L46/100 -> 0 | M104: =$G$104*M46/100 -> 0 | N104: =$G$104*N46/100 -> 0 | O104: =$G$104*O46/100 -> 0 | P104: =$G$104*P46/100 -> 0 | Q104: =$G$104*Q46/100 -> 0 | ... U104: =$G$104*U46/100 -> 0
B105: Harvest management fee | C105: 300/12 | D105: Mgmt/Admin | G105: 3.75 | H105: =SUM(J105:U105) -> 0 | J105: =$G$105*J16 -> 0 | K105: =$G$105*K16 -> 0 | L105: =$G$105*L16 -> 0 | M105: =$G$105*M16 -> 0 | N105: =$G$105*N16 -> 0 | O105: =$G$105*O16 -> 0 | P105: =$G$105*P16 -> 0 | Q105: =$G$105*Q16 -> 0 | ... U105: =$G$105*U16 -> 0
B107: Total non-docket costs | G107: =H107/B127 -> #DIV/0! | H107: =SUM(H82:H105) -> 0 | J107: =SUM(J82:J105) -> 0 | K107: =SUM(K82:K105) -> 0 | L107: =SUM(L82:L105) -> 0 | M107: =SUM(M82:M105) -> 0 | N107: =SUM(N82:N105) -> 0 | O107: =SUM(O82:O105) -> 0 | P107: =SUM(P82:P105) -> 0 | Q107: =SUM(Q82:Q105) -> 0 | ... U107: =SUM(U82:U105) -> 0
...

Sheet Eastfork Actual
C1: ='Eastfork Budget'!C1 -> 2025 | D1: Input
B2: ='Eastfork Budget'!B2 -> Eastfork | H2: Estimated Tonnes (ha)
B3: PRODUCTION & RATE | G3: Total Monthly Working Days | I3: =IF(NOT(ISBLANK(J5)), J5, IF(NOT(ISBLANK(J8)), J8, IF(NOT(ISBLANK(J11)), J11, 0)))+IF(NOT(ISBLANK(K5)), K5, IF(NOT(ISBLANK(K8)), K8, IF(NOT(ISBLANK(K11)), K11, 0)))+IF(NOT(ISBLANK(L5)), L5, IF(NOT(ISBLANK(L8)), L8, IF(NOT(ISBLANK(L11)), L11, 0)))+IF(NOT(ISBLANK(M5)), M5, IF(NOT(ISBLANK(M8)), M8, IF(NOT(ISBLANK(M11)), M11, 0)))+IF(NOT(ISBLANK(N5)), N5, IF(NOT(ISBLANK(N8)), N8, IF(NOT(ISBLANK(N11)), N11, 0)))+IF(NOT(ISBLANK(O5)), O5, IF(NOT(ISBLANK(O8)), O8, IF(NOT(ISBLANK(O11)), O11, 0)))+IF(NOT(ISBLANK(P5)), P5, IF(NOT(ISBLANK(P8)), P8, IF(NOT(ISBLANK(P11)), P11, 0)))+IF(NOT(ISBLANK(Q5)), Q5, IF(NOT(ISBLANK(Q8)), Q8, IF(NOT(ISBLANK(Q11)), Q11, 0)))+IF(NOT(ISBLANK(R5)), R5, IF(NOT(ISBLANK(R8)), R8, IF(NOT(ISBLANK(R11)), R11, 0)))+IF(NOT(ISBLANK(S5)), S5, IF(NOT(ISBLANK(S8)), S8, IF(NOT(ISBLANK(S11)), S11, 0)))+IF(NOT(ISBLANK(T5)), T5, IF(NOT(ISBLANK(T8)), T8, IF(NOT(ISBLANK(T11)), T11, 0)))+IF(NOT(ISBLANK(U5)), U5, IF(NOT(ISBLANK(U8)), U8, IF(NOT(ISBLANK(U11)), U11, 0))) -> 0 | J3: 45658 | K3: 45689 | L3: 45717 | M3: 45748 | N3: 45778 | O3: 45809 | P3: 45839 | Q3: 45870 | R3: 45901 | S3: 45931 | T3: 45962 | U3: 45992
G4: Roadline | H4: Total production | I4: =IFERROR(SUM(J4:U4)/$W$16,0) -> 0
H5: Days worked
H6: Harvesting Rate
G7: Groundbase | H7: Total production | I7: =IFERROR(SUM(J7:U7)/$W$16,0) -> 0
H8: Days worked
H9: Harvesting Rate
G10: Hauler | H10: Total production | I10: =IFERROR(SUM(J10:U10)/$W$16,0) -> 0
H11: Days worked
H12: Harvesting Rate
G13: Total | H13: Harvested Tonnes | I13: =SUM(I4:I12) -> 0 | J13: =J4+J7+J10 -> 0 | K13: =K4+K7+K10 -> 0 | L13: =L4+L7+L10 -> 0 | M13: =M4+M7+M10 -> 0 | N13: =N4+N7+N10 -> 0 | O13: =O4+O7+O10 -> 0 | P13: =P4+P7+P10 -> 0 | Q13: =Q4+Q7+Q10 -> 0 | ... U13: =U4+U7+U10 -> 0 | W13: =I3 -> 0 | X13: Monthly Working Days
H14: Variance Tones | J14: =J13-J16 -> 0 | K14: =K13-K16 -> 0 | L14: =L13-L16 -> 0 | M14: =M13-M16 -> 0 | N14: =N13-N16 -> 0 | O14: =O13-O16 -> 0 | P14: =P13-P16 -> 0 | Q14: =Q13-Q16 -> 0 | ... U14: =U13-U16 -> 0 | W14: =SUM(J14:U14) -> 0 | X14: =H14 -> Variance Tones
G15: Total | H15: Hectare (ha) | J15: =IFERROR(J13/$I$2,0) -> 0 | K15: =IFERROR(K13/$I$2,0) -> 0 | L15: =IFERROR(L13/$I$2,0) -> 0 | M15: =IFERROR(M13/$I$2,0) -> 0 | N15: =IFERROR(N13/$I$2,0) -> 0 | O15: =IFERROR(O13/$I$2,0) -> 0 | P15: =IFERROR(P13/$I$2,0) -> 0 | Q15: =IFERROR(Q13/$I$2,0) -> 0 | ... U15: =IFERROR(U13/$I$2,0) -> 0 | W15: =SUM(J15:U15) -> 0 | X15: =H15 -> Hectare (ha)
G16: Total | H16: Invoice Tonnes | J16: =Volume_1!D27 -> 0 | K16: =Volume_1!H27 -> 0 | L16: =Volume_1!L27 -> 0 | M16: =Volume_1!P27 -> 0 | N16: =Volume_1!T27 -> 0 | O16: =Volume_1!X27 -> 0 | P16: =Volume_1!AB27 -> 0 | Q16: =Volume_1!AF27 -> 0 | R16: =Volume_1!AJ27 -> 0 | S16: =Volume_1!AN27 -> 0 | T16: =Volume_1!AR27 -> 0 | U16: =Volume_1!AV27 -> 0 | W16: =SUM(J16:U16) -> 0 | X16: =H16 -> Invoice Tonnes
B18: REVENUE
B19: Grade | C19: Grade Mix % | D19: Conversion Rate | E19: Sale unit | F19: Sale unit/t | G19: Price/Unit | H19: TOTAL | J19: 45658 | K19: 45689 | L19: 45717 | M19: 45748 | N19: 45778 | O19: 45809 | P19: 45839 | Q19: 45870 | R19: 45901 | S19: 45931 | T19: 45962 | U19: 45992
A20: Domestic | B20: P35 | C20: =IFERROR(F20/$F$46,0) -> 0.08531746 | D20: =_xlfn.XLOOKUP(B20,'Log Sales Data'!AA:AA,'Log Sales Data'!AB:AB,0,0) -> 1.08 | E20: Tonnes | F20: =SUMIFS('Log Sales Data'!$I:$I,'Log Sales Data'!$C:$C,$B$2,'Log Sales Data'!$D:$D,$B20,'Log Sales Data'!$G:$G,$A20) -> 430 | G20: =IFERROR(H20/F20,"0") -> 195 | H20: =SUM(J20:U20) -> 83850 | J20: =SUMIFS('Log Sales Data'!$M:$M,'Log Sales Data'!$B:$B,J$19,'Log Sales Data'!$C:$C,$B$2,'Log Sales Data'!$D:$D,$B20,'Log Sales Data'!$G:$G,$A20) -> 83850 | K20: =SUMIFS('Log Sales Data'!$M:$M,'Log Sales Data'!$B:$B,K$19,'Log Sales Data'!$C:$C,$B$2,'Log Sales Data'!$D:$D,$B20,'Log Sales Data'!$G:$G,$A20) -> 0 | L20: =SUMIFS('Log Sales Data'!$M:$M,'Log Sales Data'!$B:$B,L$19,'Log Sales Data'!$C:$C,$B$2,'Log Sales Data'!$D:$D,$B20,'Log Sales Data'!$G:$G,$A20) -> 0 | M20: =SUMIFS('Log Sales Data'!$M:$M,'Log Sales Data'!$B:$B,M$19,'Log Sales Data'!$C:$C,$B$2,'Log Sales Data'!$D:$D,$B20,'Log Sales Data'!$G:$G,$A20) -> 0 | N20: =SUMIFS('Log Sales Data'!$M:$M,'Log Sales Data'!$B:$B,N$19,'Log Sales Data'!$C:$C,$B$2,'Log Sales Data'!$D:$D,$B20,'Log Sales Data'!$G:$G,$A20) -> 0 | O20: =SUMIFS('Log Sales Data'!$M:$M,'Log Sales Data'!$B:$B,O$19,'Log Sales Data'!$C:$C,$B$2,'Log Sales Data'!$D:$D,$B20,'Log Sales Data'!$G:$G,$A20) -> 0 | P20: =SUMIFS('Log Sales Data'!$M:$M,'Log Sales Data'!$B:$B,P$19,'Log Sales Data'!$C:$C,$B$2,'Log Sales Data'!$D:$D,$B20,'Log Sales Data'!$G:$G,$A20) -> 0 | Q20: =SUMIFS('Log Sales Data'!$M:$M,'Log Sales Data'!$B:$B,Q$19,'Log Sales Data'!$C:$C,$B$2,'Log Sales Data'!$D:$D,$B20,'Log Sales Data'!$G:$G,$A20) -> 0 | ... U20: =SUMIFS('Log Sales Data'!$M:$M,'Log Sales Data'!$B:$B,U$19,'Log Sales Data'!$C:$C,$B$2,'Log Sales Data'!$D:$D,$B20,'Log Sales Data'!$G:$G,$A20) -> 0
A21: Domestic | B21: S30 | C21: =IFERROR(F21/$F$46,0) -> 0.16468254 | D21: =_xlfn.XLOOKUP(B21,'Log Sales Data'!AA:AA,'Log Sales Data'!AB:AB,0,0) -> 1.03 | E21: Tonnes | F21: =SUMIFS('Log Sales Data'!$I:$I,'Log Sales Data'!$C:$C,$B$2,'Log Sales Data'!$D:$D,$B21,'Log Sales Data'!$G:$G,$A21) -> 830 | G21: =IFERROR(H21/F21,"0") -> 127 | H21: =SUM(J21:U21) -> 105410 | J21: =SUMIFS('Log Sales Data'!$M:$M,'Log Sales Data'!$B:$B,J$19,'Log Sales Data'!$C:$C,$B$2,'Log Sales Data'!$D:$D,$B21,'Log Sales Data'!$G:$G,$A21) -> 105410 | K21: =SUMIFS('Log Sales Data'!$M:$M,'Log Sales Data'!$B:$B,K$19,'Log Sales Data'!$C:$C,$B$2,'Log Sales Data'!$D:$D,$B21,'Log Sales Data'!$G:$G,$A21) -> 0 | L21: =SUMIFS('Log Sales Data'!$M:$M,'Log Sales Data'!$B:$B,L$19,'Log Sales Data'!$C:$C,$B$2,'Log Sales Data'!$D:$D,$B21,'Log Sales Data'!$G:$G,$A21) -> 0 | M21: =SUMIFS('Log Sales Data'!$M:$M,'Log Sales Data'!$B:$B,M$19,'Log Sales Data'!$C:$C,$B$2,'Log Sales Data'!$D:$D,$B21,'Log Sales Data'!$G:$G,$A21) -> 0 | N21: =SUMIFS('Log Sales Data'!$M:$M,'Log Sales Data'!$B:$B,N$19,'Log Sales Data'!$C:$C,$B$2,'Log Sales Data'!$D:$D,$B21,'Log Sales Data'!$G:$G,$A21) -> 0 | O21: =SUMIFS('Log Sales Data'!$M:$M,'Log Sales Data'!$B:$B,O$19,'Log Sales Data'!$C:$C,$B$2,'Log Sales Data'!$D:$D,$B21,'Log Sales Data'!$G:$G,$A21) -> 0 | P21: =SUMIFS('Log Sales Data'!$M:$M,'Log Sales Data'!$B:$B,P$19,'Log Sales Data'!$C:$C,$B$2,'Log Sales Data'!$D:$D,$B21,'Log Sales Data'!$G:$G,$A21) -> 0 | Q21: =SUMIFS('Log Sales Data'!$M:$M,'Log Sales Data'!$B:$B,Q$19,'Log Sales Data'!$C:$C,$B$2,'Log Sales Data'!$D:$D,$B21,'Log Sales Data'!$G:$G,$A21) -> 0 | ... U21: =SUMIFS('Log Sales Data'!$M:$M,'Log Sales Data'!$B:$B,U$19,'Log Sales Data'!$C:$C,$B$2,'Log Sales Data'!$D:$D,$B21,'Log Sales Data'!$G:$G,$A21) -> 0
A22: Domestic | B22: S20 | C22: =IFERROR(F22/$F$46,0) -> 0.24404762 | D22: =_xlfn.XLOOKUP(B22,'Log Sales Data'!AA:AA,'Log Sales Data'!AB:AB,0,0) -> 0.99 | E22: Tonnes | F22: =SUMIFS('Log Sales Data'!$I:$I,'Log Sales Data'!$C:$C,$B$2,'Log Sales Data'!$D:$D,$B22,'Log Sales Data'!$G:$G,$A22) -> 1230 | G22: =IFERROR(H22/F22,"0") -> 120 | H22: =SUM(J22:U22) -> 147600 | J22: =SUMIFS('Log Sales Data'!$M:$M,'Log Sales Data'!$B:$B,J$19,'Log Sales Data'!$C:$C,$B$2,'Log Sales Data'!$D:$D,$B22,'Log Sales Data'!$G:$G,$A22) -> 147600 | K22: =SUMIFS('Log Sales Data'!$M:$M,'Log Sales Data'!$B:$B,K$19,'Log Sales Data'!$C:$C,$B$2,'Log Sales Data'!$D:$D,$B22,'Log Sales Data'!$G:$G,$A22) -> 0 | L22: =SUMIFS('Log Sales Data'!$M:$M,'Log Sales Data'!$B:$B,L$19,'Log Sales Data'!$C:$C,$B$2,'Log Sales Data'!$D:$D,$B22,'Log Sales Data'!$G:$G,$A22) -> 0 | M22: =SUMIFS('Log Sales Data'!$M:$M,'Log Sales Data'!$B:$B,M$19,'Log Sales Data'!$C:$C,$B$2,'Log Sales Data'!$D:$D,$B22,'Log Sales Data'!$G:$G,$A22) -> 0 | N22: =SUMIFS('Log Sales Data'!$M:$M,'Log Sales Data'!$B:$B,N$19,'Log Sales Data'!$C:$C,$B$2,'Log Sales Data'!$D:$D,$B22,'Log Sales Data'!$G:$G,$A22) -> 0 | O22: =SUMIFS('Log Sales Data'!$M:$M,'Log Sales Data'!$B:$B,O$19,'Log Sales Data'!$C:$C,$B$2,'Log Sales Data'!$D:$D,$B22,'Log Sales Data'!$G:$G,$A22) -> 0 | P22: =SUMIFS('Log Sales Data'!$M:$M,'Log Sales Data'!$B:$B,P$19,'Log Sales Data'!$C:$C,$B$2,'Log Sales Data'!$D:$D,$B22,'Log Sales Data'!$G:$G,$A22) -> 0 | Q22: =SUMIFS('Log Sales Data'!$M:$M,'Log Sales Data'!$B:$B,Q$19,'Log Sales Data'!$C:$C,$B$2,'Log Sales Data'!$D:$D,$B22,'Log Sales Data'!$G:$G,$A22) -> 0 | ... U22: =SUMIFS('Log Sales Data'!$M:$M,'Log Sales Data'!$B:$B,U$19,'Log Sales Data'!$C:$C,$B$2,'Log Sales Data'!$D:$D,$B22,'Log Sales Data'!$G:$G,$A22) -> 0
A23: Domestic | B23: Domestic Pulp | C23: =IFERROR(F23/$F$46,0) -> 0 | D23: =_xlfn.XLOOKUP(B23,'Log Sales Data'!AA:AA,'Log Sales Data'!AB:AB,0,0) -> 0.88 | E23: Tonnes | F23: =SUMIFS('Log Sales Data'!$I:$I,'Log Sales Data'!$C:$C,$B$2,'Log Sales Data'!$D:$D,$B23,'Log Sales Data'!$G:$G,$A23) -> 0 | G23: =IFERROR(H23/F23,"0") -> 0 | H23: =SUM(J23:U23) -> 0 | J23: =SUMIFS('Log Sales Data'!$M:$M,'Log Sales Data'!$B:$B,J$19,'Log Sales Data'!$C:$C,$B$2,'Log Sales Data'!$D:$D,$B23,'Log Sales Data'!$G:$G,$A23) -> 0 | K23: =SUMIFS('Log Sales Data'!$M:$M,'Log Sales Data'!$B:$B,K$19,'Log Sales Data'!$C:$C,$B$2,'Log Sales Data'!$D:$D,$B23,'Log Sales Data'!$G:$G,$A23) -> 0 | L23: =SUMIFS('Log Sales Data'!$M:$M,'Log Sales Data'!$B:$B,L$19,'Log Sales Data'!$C:$C,$B$2,'Log Sales Data'!$D:$D,$B23,'Log Sales Data'!$G:$G,$A23) -> 0 | M23: =SUMIFS('Log Sales Data'!$M:$M,'Log Sales Data'!$B:$B,M$19,'Log Sales Data'!$C:$C,$B$2,'Log Sales Data'!$D:$D,$B23,'Log Sales Data'!$G:$G,$A23) -> 0 | N23: =SUMIFS('Log Sales Data'!$M:$M,'Log Sales Data'!$B:$B,N$19,'Log Sales Data'!$C:$C,$B$2,'Log Sales Data'!$D:$D,$B23,'Log Sales Data'!$G:$G,$A23) -> 0 | O23: =SUMIFS('Log Sales Data'!$M:$M,'Log Sales Data'!$B:$B,O$19,'Log Sales Data'!$C:$C,$B$2,'Log Sales Data'!$D:$D,$B23,'Log Sales Data'!$G:$G,$A23) -> 0 | P23: =SUMIFS('Log Sales Data'!$M:$M,'Log Sales Data'!$B:$B,P$19,'Log Sales Data'!$C:$C,$B$2,'Log Sales Data'!$D:$D,$B23,'Log Sales Data'!$G:$G,$A23) -> 0 | Q23: =SUMIFS('Log Sales Data'!$M:$M,'Log Sales Data'!$B:$B,Q$19,'Log Sales Data'!$C:$C,$B$2,'Log Sales Data'!$D:$D,$B23,'Log Sales Data'!$G:$G,$A23) -> 0 | ... U23: =SUMIFS('Log Sales Data'!$M:$M,'Log Sales Data'!$B:$B,U$19,'Log Sales Data'!$C:$C,$B$2,'Log Sales Data'!$D:$D,$B23,'Log Sales Data'!$G:$G,$A23) -> 0
A24: Domestic | B24: Eucalyptus | C24: =IFERROR(F24/$F$46,0) -> 0 | D24: =_xlfn.XLOOKUP(B24,'Log Sales Data'!AA:AA,'Log Sales Data'!AB:AB,0,0) -> 0.95 | E24: Tonnes | F24: =SUMIFS('Log Sales Data'!$I:$I,'Log Sales Data'!$C:$C,$B$2,'Log Sales Data'!$D:$D,$B24,'Log Sales Data'!$G:$G,$A24) -> 0 | G24: =IFERROR(H24/F24,"0") -> 0 | H24: =SUM(J24:U24) -> 0 | J24: =SUMIFS('Log Sales Data'!$M:$M,'Log Sales Data'!$B:$B,J$19,'Log Sales Data'!$C:$C,$B$2,'Log Sales Data'!$D:$D,$B24,'Log Sales Data'!$G:$G,$A24) -> 0 | K24: =SUMIFS('Log Sales Data'!$M:$M,'Log Sales Data'!$B:$B,K$19,'Log Sales Data'!$C:$C,$B$2,'Log Sales Data'!$D:$D,$B24,'Log Sales Data'!$G:$G,$A24) -> 0 | L24: =SUMIFS('Log Sales Data'!$M:$M,'Log Sales Data'!$B:$B,L$19,'Log Sales Data'!$C:$C,$B$2,'Log Sales Data'!$D:$D,$B24,'Log Sales Data'!$G:$G,$A24) -> 0 | M24: =SUMIFS('Log Sales Data'!$M:$M,'Log Sales Data'!$B:$B,M$19,'Log Sales Data'!$C:$C,$B$2,'Log Sales Data'!$D:$D,$B24,'Log Sales Data'!$G:$G,$A24) -> 0 | N24: =SUMIFS('Log Sales Data'!$M:$M,'Log Sales Data'!$B:$B,N$19,'Log Sales Data'!$C:$C,$B$2,'Log Sales Data'!$D:$D,$B24,'Log Sales Data'!$G:$G,$A24) -> 0 | O24: =SUMIFS('Log Sales Data'!$M:$M,'Log Sales Data'!$B:$B,O$19,'Log Sales Data'!$C:$C,$B$2,'Log Sales Data'!$D:$D,$B24,'Log Sales Data'!$G:$G,$A24) -> 0 | P24: =SUMIFS('Log Sales Data'!$M:$M,'Log Sales Data'!$B:$B,P$19,'Log Sales Data'!$C:$C,$B$2,'Log Sales Data'!$D:$D,$B24,'Log Sales Data'!$G:$G,$A24) -> 0 | Q24: =SUMIFS('Log Sales Data'!$M:$M,'Log Sales Data'!$B:$B,Q$19,'Log Sales Data'!$C:$C,$B$2,'Log Sales Data'!$D:$D,$B24,'Log Sales Data'!$G:$G,$A24) -> 0 | ... U24: =SUMIFS('Log Sales Data'!$M:$M,'Log Sales Data'!$B:$B,U$19,'Log Sales Data'!$C:$C,$B$2,'Log Sales Data'!$D:$D,$B24,'Log Sales Data'!$G:$G,$A24) -> 0
A25: Domestic | B25: FW | C25: =IFERROR(F25/$F$46,0) -> 0 | D25: =_xlfn.XLOOKUP(B25,'Log Sales Data'!AA:AA,'Log Sales Data'!AB:AB,0,0) -> 0.95 | E25: Tonnes | F25: =SUMIFS('Log Sales Data'!$I:$I,'Log Sales Data'!$C:$C,$B$2,'Log Sales Data'!$D:$D,$B25,'Log Sales Data'!$G:$G,$A25) -> 0 | G25: =IFERROR(H25/F25,"0") -> 0 | H25: =SUM(J25:U25) -> 0 | J25: =SUMIFS('Log Sales Data'!$M:$M,'Log Sales Data'!$B:$B,J$19,'Log Sales Data'!$C:$C,$B$2,'Log Sales Data'!$D:$D,$B25,'Log Sales Data'!$G:$G,$A25) -> 0 | K25: =SUMIFS('Log Sales Data'!$M:$M,'Log Sales Data'!$B:$B,K$19,'Log Sales Data'!$C:$C,$B$2,'Log Sales Data'!$D:$D,$B25,'Log Sales Data'!$G:$G,$A25) -> 0 | L25: =SUMIFS('Log Sales Data'!$M:$M,'Log Sales Data'!$B:$B,L$19,'Log Sales Data'!$C:$C,$B$2,'Log Sales Data'!$D:$D,$B25,'Log Sales Data'!$G:$G,$A25) -> 0 | M25: =SUMIFS('Log Sales Data'!$M:$M,'Log Sales Data'!$B:$B,M$19,'Log Sales Data'!$C:$C,$B$2,'Log Sales Data'!$D:$D,$B25,'Log Sales Data'!$G:$G,$A25) -> 0 | N25: =SUMIFS('Log Sales Data'!$M:$M,'Log Sales Data'!$B:$B,N$19,'Log Sales Data'!$C:$C,$B$2,'Log Sales Data'!$D:$D,$B25,'Log Sales Data'!$G:$G,$A25) -> 0 | O25: =SUMIFS('Log Sales Data'!$M:$M,'Log Sales Data'!$B:$B,O$19,'Log Sales Data'!$C:$C,$B$2,'Log Sales Data'!$D:$D,$B25,'Log Sales Data'!$G:$G,$A25) -> 0 | P25: =SUMIFS('Log Sales Data'!$M:$M,'Log Sales Data'!$B:$B,P$19,'Log Sales Data'!$C:$C,$B$2,'Log Sales Data'!$D:$D,$B25,'Log Sales Data'!$G:$G,$A25) -> 0 | Q25: =SUMIFS('Log Sales Data'!$M:$M,'Log Sales Data'!$B:$B,Q$19,'Log Sales Data'!$C:$C,$B$2,'Log Sales Data'!$D:$D,$B25,'Log Sales Data'!$G:$G,$A25) -> 0 | ... U25: =SUMIFS('Log Sales Data'!$M:$M,'Log Sales Data'!$B:$B,U$19,'Log Sales Data'!$C:$C,$B$2,'Log Sales Data'!$D:$D,$B25,'Log Sales Data'!$G:$G,$A25) -> 0
A26: Domestic | B26: Euc Pulp | C26: =IFERROR(F26/$F$46,0) -> 0 | D26: =_xlfn.XLOOKUP(B26,'Log Sales Data'!AA:AA,'Log Sales Data'!AB:AB,0,0) -> 0.88 | E26: Tonnes | F26: =SUMIFS('Log Sales Data'!$I:$I,'Log Sales Data'!$C:$C,$B$2,'Log Sales Data'!$D:$D,$B26,'Log Sales Data'!$G:$G,$A26) -> 0 | G26: =IFERROR(H26/F26,"0") -> 0 | H26: =SUM(J26:U26) -> 0 | J26: =SUMIFS('Log Sales Data'!$M:$M,'Log Sales Data'!$B:$B,J$19,'Log Sales Data'!$C:$C,$B$2,'Log Sales Data'!$D:$D,$B26,'Log Sales Data'!$G:$G,$A26) -> 0 | K26: =SUMIFS('Log Sales Data'!$M:$M,'Log Sales Data'!$B:$B,K$19,'Log Sales Data'!$C:$C,$B$2,'Log Sales Data'!$D:$D,$B26,'Log Sales Data'!$G:$G,$A26) -> 0 | L26: =SUMIFS('Log Sales Data'!$M:$M,'Log Sales Data'!$B:$B,L$19,'Log Sales Data'!$C:$C,$B$2,'Log Sales Data'!$D:$D,$B26,'Log Sales Data'!$G:$G,$A26) -> 0 | M26: =SUMIFS('Log Sales Data'!$M:$M,'Log Sales Data'!$B:$B,M$19,'Log Sales Data'!$C:$C,$B$2,'Log Sales Data'!$D:$D,$B26,'Log Sales Data'!$G:$G,$A26) -> 0 | N26: =SUMIFS('Log Sales Data'!$M:$M,'Log Sales Data'!$B:$B,N$19,'Log Sales Data'!$C:$C,$B$2,'Log Sales Data'!$D:$D,$B26,'Log Sales Data'!$G:$G,$A26) -> 0 | O26: =SUMIFS('Log Sales Data'!$M:$M,'Log Sales Data'!$B:$B,O$19,'Log Sales Data'!$C:$C,$B$2,'Log Sales Data'!$D:$D,$B26,'Log Sales Data'!$G:$G,$A26) -> 0 | P26: =SUMIFS('Log Sales Data'!$M:$M,'Log Sales Data'!$B:$B,P$19,'Log Sales Data'!$C:$C,$B$2,'Log Sales Data'!$D:$D,$B26,'Log Sales Data'!$G:$G,$A26) -> 0 | Q26: =SUMIFS('Log Sales Data'!$M:$M,'Log Sales Data'!$B:$B,Q$19,'Log Sales Data'!$C:$C,$B$2,'Log Sales Data'!$D:$D,$B26,'Log Sales Data'!$G:$G,$A26) -> 0 | ... U26: =SUMIFS('Log Sales Data'!$M:$M,'Log Sales Data'!$B:$B,U$19,'Log Sales Data'!$C:$C,$B$2,'Log Sales Data'!$D:$D,$B26,'Log Sales Data'!$G:$G,$A26) -> 0
A27: Domestic | B27: Binwood | C27: =IFERROR(F27/$F$46,0) -> 0 | D27: =_xlfn.XLOOKUP(B27,'Log Sales Data'!AA:AA,'Log Sales Data'!AB:AB,0,0) -> 0.88 | E27: Tonnes | F27: =SUMIFS('Log Sales Data'!$I:$I,'Log Sales Data'!$C:$C,$B$2,'Log Sales Data'!$D:$D,$B27,'Log Sales Data'!$G:$G,$A27) -> 0 | G27: =IFERROR(H27/F27,"0") -> 0 | H27: =SUM(J27:U27) -> 0 | J27: =SUMIFS('Log Sales Data'!$M:$M,'Log Sales Data'!$B:$B,J$19,'Log Sales Data'!$C:$C,$B$2,'Log Sales Data'!$D:$D,$B27,'Log Sales Data'!$G:$G,$A27) -> 0 | K27: =SUMIFS('Log Sales Data'!$M:$M,'Log Sales Data'!$B:$B,K$19,'Log Sales Data'!$C:$C,$B$2,'Log Sales Data'!$D:$D,$B27,'Log Sales Data'!$G:$G,$A27) -> 0 | L27: =SUMIFS('Log Sales Data'!$M:$M,'Log Sales Data'!$B:$B,L$19,'Log Sales Data'!$C:$C,$B$2,'Log Sales Data'!$D:$D,$B27,'Log Sales Data'!$G:$G,$A27) -> 0 | M27: =SUMIFS('Log Sales Data'!$M:$M,'Log Sales Data'!$B:$B,M$19,'Log Sales Data'!$C:$C,$B$2,'Log Sales Data'!$D:$D,$B27,'Log Sales Data'!$G:$G,$A27) -> 0 | N27: =SUMIFS('Log Sales Data'!$M:$M,'Log Sales Data'!$B:$B,N$19,'Log Sales Data'!$C:$C,$B$2,'Log Sales Data'!$D:$D,$B27,'Log Sales Data'!$G:$G,$A27) -> 0 | O27: =SUMIFS('Log Sales Data'!$M:$M,'Log Sales Data'!$B:$B,O$19,'Log Sales Data'!$C:$C,$B$2,'Log Sales Data'!$D:$D,$B27,'Log Sales Data'!$G:$G,$A27) -> 0 | P27: =SUMIFS('Log Sales Data'!$M:$M,'Log Sales Data'!$B:$B,P$19,'Log Sales Data'!$C:$C,$B$2,'Log Sales Data'!$D:$D,$B27,'Log Sales Data'!$G:$G,$A27) -> 0 | Q27: =SUMIFS('Log Sales Data'!$M:$M,'Log Sales Data'!$B:$B,Q$19,'Log Sales Data'!$C:$C,$B$2,'Log Sales Data'!$D:$D,$B27,'Log Sales Data'!$G:$G,$A27) -> 0 | ... U27: =SUMIFS('Log Sales Data'!$M:$M,'Log Sales Data'!$B:$B,U$19,'Log Sales Data'!$C:$C,$B$2,'Log Sales Data'!$D:$D,$B27,'Log Sales Data'!$G:$G,$A27) -> 0
A28: Domestic | B28: Spare Grade | E28: Tonnes | H28: =SUM(J28:U28) -> 0 | J28: =SUMIFS('Log Sales Data'!$M:$M,'Log Sales Data'!$B:$B,J$19,'Log Sales Data'!$C:$C,$B$2,'Log Sales Data'!$D:$D,$B28,'Log Sales Data'!$G:$G,$A28) -> 0 | K28: =SUMIFS('Log Sales Data'!$M:$M,'Log Sales Data'!$B:$B,K$19,'Log Sales Data'!$C:$C,$B$2,'Log Sales Data'!$D:$D,$B28,'Log Sales Data'!$G:$G,$A28) -> 0 | L28: =SUMIFS('Log Sales Data'!$M:$M,'Log Sales Data'!$B:$B,L$19,'Log Sales Data'!$C:$C,$B$2,'Log Sales Data'!$D:$D,$B28,'Log Sales Data'!$G:$G,$A28) -> 0 | M28: =SUMIFS('Log Sales Data'!$M:$M,'Log Sales Data'!$B:$B,M$19,'Log Sales Data'!$C:$C,$B$2,'Log Sales Data'!$D:$D,$B28,'Log Sales Data'!$G:$G,$A28) -> 0 | N28: =SUMIFS('Log Sales Data'!$M:$M,'Log Sales Data'!$B:$B,N$19,'Log Sales Data'!$C:$C,$B$2,'Log Sales Data'!$D:$D,$B28,'Log Sales Data'!$G:$G,$A28) -> 0 | O28: =SUMIFS('Log Sales Data'!$M:$M,'Log Sales Data'!$B:$B,O$19,'Log Sales Data'!$C:$C,$B$2,'Log Sales Data'!$D:$D,$B28,'Log Sales Data'!$G:$G,$A28) -> 0 | P28: =SUMIFS('Log Sales Data'!$M:$M,'Log Sales Data'!$B:$B,P$19,'Log Sales Data'!$C:$C,$B$2,'Log Sales Data'!$D:$D,$B28,'Log Sales Data'!$G:$G,$A28) -> 0 | Q28: =SUMIFS('Log Sales Data'!$M:$M,'Log Sales Data'!$B:$B,Q$19,'Log Sales Data'!$C:$C,$B$2,'Log Sales Data'!$D:$D,$B28,'Log Sales Data'!$G:$G,$A28) -> 0 | ... U28: =SUMIFS('Log Sales Data'!$M:$M,'Log Sales Data'!$B:$B,U$19,'Log Sales Data'!$C:$C,$B$2,'Log Sales Data'!$D:$D,$B28,'Log Sales Data'!$G:$G,$A28) -> 0
A29: Export | B29: P40 | C29: =IFERROR(F29/$F$46,0) -> 0.089285714 | D29: =_xlfn.XLOOKUP(B29,'Log Sales Data'!AA:AA,'Log Sales Data'!AB:AB,0,0) -> 1.09 | E29: Tonnes | F29: =SUMIFS('Log Sales Data'!$I:$I,'Log Sales Data'!$C:$C,$B$2,'Log Sales Data'!$D:$D,$B29,'Log Sales Data'!$G:$G,$A29) -> 450 | G29: =IFERROR(H29/F29,"0") -> 195 | H29: =SUM(J29:U29) -> 87750 | J29: =SUMIFS('Log Sales Data'!$M:$M,'Log Sales Data'!$B:$B,J$19,'Log Sales Data'!$C:$C,$B$2,'Log Sales Data'!$D:$D,$B29,'Log Sales Data'!$G:$G,$A29) -> 87750 | K29: =SUMIFS('Log Sales Data'!$M:$M,'Log Sales Data'!$B:$B,K$19,'Log Sales Data'!$C:$C,$B$2,'Log Sales Data'!$D:$D,$B29,'Log Sales Data'!$G:$G,$A29) -> 0 | L29: =SUMIFS('Log Sales Data'!$M:$M,'Log Sales Data'!$B:$B,L$19,'Log Sales Data'!$C:$C,$B$2,'Log Sales Data'!$D:$D,$B29,'Log Sales Data'!$G:$G,$A29) -> 0 | M29: =SUMIFS('Log Sales Data'!$M:$M,'Log Sales Data'!$B:$B,M$19,'Log Sales Data'!$C:$C,$B$2,'Log Sales Data'!$D:$D,$B29,'Log Sales Data'!$G:$G,$A29) -> 0 | N29: =SUMIFS('Log Sales Data'!$M:$M,'Log Sales Data'!$B:$B,N$19,'Log Sales Data'!$C:$C,$B$2,'Log Sales Data'!$D:$D,$B29,'Log Sales Data'!$G:$G,$A29) -> 0 | O29: =SUMIFS('Log Sales Data'!$M:$M,'Log Sales Data'!$B:$B,O$19,'Log Sales Data'!$C:$C,$B$2,'Log Sales Data'!$D:$D,$B29,'Log Sales Data'!$G:$G,$A29) -> 0 | P29: =SUMIFS('Log Sales Data'!$M:$M,'Log Sales Data'!$B:$B,P$19,'Log Sales Data'!$C:$C,$B$2,'Log Sales Data'!$D:$D,$B29,'Log Sales Data'!$G:$G,$A29) -> 0 | Q29: =SUMIFS('Log Sales Data'!$M:$M,'Log Sales Data'!$B:$B,Q$19,'Log Sales Data'!$C:$C,$B$2,'Log Sales Data'!$D:$D,$B29,'Log Sales Data'!$G:$G,$A29) -> 0 | ... U29: =SUMIFS('Log Sales Data'!$M:$M,'Log Sales Data'!$B:$B,U$19,'Log Sales Data'!$C:$C,$B$2,'Log Sales Data'!$D:$D,$B29,'Log Sales Data'!$G:$G,$A29) -> 0
A30: Export | B30: P30 | C30: =IFERROR(F30/$F$46,0) -> 0 | D30: =_xlfn.XLOOKUP(B30,'Log Sales Data'!AA:AA,'Log Sales Data'!AB:AB,0,0) -> 1.07 | E30: Tonnes | F30: =SUMIFS('Log Sales Data'!$I:$I,'Log Sales Data'!$C:$C,$B$2,'Log Sales Data'!$D:$D,$B30,'Log Sales Data'!$G:$G,$A30) -> 0 | G30: =IFERROR(H30/F30,"0") -> 0 | H30: =SUM(J30:U30) -> 0 | J30: =SUMIFS('Log Sales Data'!$M:$M,'Log Sales Data'!$B:$B,J$19,'Log Sales Data'!$C:$C,$B$2,'Log Sales Data'!$D:$D,$B30,'Log Sales Data'!$G:$G,$A30) -> 0 | K30: =SUMIFS('Log Sales Data'!$M:$M,'Log Sales Data'!$B:$B,K$19,'Log Sales Data'!$C:$C,$B$2,'Log Sales Data'!$D:$D,$B30,'Log Sales Data'!$G:$G,$A30) -> 0 | L30: =SUMIFS('Log Sales Data'!$M:$M,'Log Sales Data'!$B:$B,L$19,'Log Sales Data'!$C:$C,$B$2,'Log Sales Data'!$D:$D,$B30,'Log Sales Data'!$G:$G,$A30) -> 0 | M30: =SUMIFS('Log Sales Data'!$M:$M,'Log Sales Data'!$B:$B,M$19,'Log Sales Data'!$C:$C,$B$2,'Log Sales Data'!$D:$D,$B30,'Log Sales Data'!$G:$G,$A30) -> 0 | N30: =SUMIFS('Log Sales Data'!$M:$M,'Log Sales Data'!$B:$B,N$19,'Log Sales Data'!$C:$C,$B$2,'Log Sales Data'!$D:$D,$B30,'Log Sales Data'!$G:$G,$A30) -> 0 | O30: =SUMIFS('Log Sales Data'!$M:$M,'Log Sales Data'!$B:$B,O$19,'Log Sales Data'!$C:$C,$B$2,'Log Sales Data'!$D:$D,$B30,'Log Sales Data'!$G:$G,$A30) -> 0 | P30: =SUMIFS('Log Sales Data'!$M:$M,'Log Sales Data'!$B:$B,P$19,'Log Sales Data'!$C:$C,$B$2,'Log Sales Data'!$D:$D,$B30,'Log Sales Data'!$G:$G,$A30) -> 0 | Q30: =SUMIFS('Log Sales Data'!$M:$M,'Log Sales Data'!$B:$B,Q$19,'Log Sales Data'!$C:$C,$B$2,'Log Sales Data'!$D:$D,$B30,'Log Sales Data'!$G:$G,$A30) -> 0 | ... U30: =SUMIFS('Log Sales Data'!$M:$M,'Log Sales Data'!$B:$B,U$19,'Log Sales Data'!$C:$C,$B$2,'Log Sales Data'!$D:$D,$B30,'Log Sales Data'!$G:$G,$A30) -> 0
A31: Export | B31: AO | C31: =IFERROR(F31/$F$46,0) -> 0 | D31: =_xlfn.XLOOKUP(B31,'Log Sales Data'!AA:AA,'Log Sales Data'!AB:AB,0,0) -> 1.03 | E31: Tonnes | F31: =SUMIFS('Log Sales Data'!$I:$I,'Log Sales Data'!$C:$C,$B$2,'Log Sales Data'!$D:$D,$B31,'Log Sales Data'!$G:$G,$A31) -> 0 | G31: =IFERROR(H31/F31,"0") -> 0 | H31: =SUM(J31:U31) -> 0 | J31: =SUMIFS('Log Sales Data'!$M:$M,'Log Sales Data'!$B:$B,J$19,'Log Sales Data'!$C:$C,$B$2,'Log Sales Data'!$D:$D,$B31,'Log Sales Data'!$G:$G,$A31) -> 0 | K31: =SUMIFS('Log Sales Data'!$M:$M,'Log Sales Data'!$B:$B,K$19,'Log Sales Data'!$C:$C,$B$2,'Log Sales Data'!$D:$D,$B31,'Log Sales Data'!$G:$G,$A31) -> 0 | L31: =SUMIFS('Log Sales Data'!$M:$M,'Log Sales Data'!$B:$B,L$19,'Log Sales Data'!$C:$C,$B$2,'Log Sales Data'!$D:$D,$B31,'Log Sales Data'!$G:$G,$A31) -> 0 | M31: =SUMIFS('Log Sales Data'!$M:$M,'Log Sales Data'!$B:$B,M$19,'Log Sales Data'!$C:$C,$B$2,'Log Sales Data'!$D:$D,$B31,'Log Sales Data'!$G:$G,$A31) -> 0 | N31: =SUMIFS('Log Sales Data'!$M:$M,'Log Sales Data'!$B:$B,N$19,'Log Sales Data'!$C:$C,$B$2,'Log Sales Data'!$D:$D,$B31,'Log Sales Data'!$G:$G,$A31) -> 0 | O31: =SUMIFS('Log Sales Data'!$M:$M,'Log Sales Data'!$B:$B,O$19,'Log Sales Data'!$C:$C,$B$2,'Log Sales Data'!$D:$D,$B31,'Log Sales Data'!$G:$G,$A31) -> 0 | P31: =SUMIFS('Log Sales Data'!$M:$M,'Log Sales Data'!$B:$B,P$19,'Log Sales Data'!$C:$C,$B$2,'Log Sales Data'!$D:$D,$B31,'Log Sales Data'!$G:$G,$A31) -> 0 | Q31: =SUMIFS('Log Sales Data'!$M:$M,'Log Sales Data'!$B:$B,Q$19,'Log Sales Data'!$C:$C,$B$2,'Log Sales Data'!$D:$D,$B31,'Log Sales Data'!$G:$G,$A31) -> 0 | ... U31: =SUMIFS('Log Sales Data'!$M:$M,'Log Sales Data'!$B:$B,U$19,'Log Sales Data'!$C:$C,$B$2,'Log Sales Data'!$D:$D,$B31,'Log Sales Data'!$G:$G,$A31) -> 0
A32: Export | B32: A | C32: =IFERROR(F32/$F$46,0) -> 0.16865079 | D32: =_xlfn.XLOOKUP(B32,'Log Sales Data'!AA:AA,'Log Sales Data'!AB:AB,0,0) -> 1.03 | E32: Tonnes | F32: =SUMIFS('Log Sales Data'!$I:$I,'Log Sales Data'!$C:$C,$B$2,'Log Sales Data'!$D:$D,$B32,'Log Sales Data'!$G:$G,$A32) -> 850 | G32: =IFERROR(H32/F32,"0") -> 127 | H32: =SUM(J32:U32) -> 107950 | J32: =SUMIFS('Log Sales Data'!$M:$M,'Log Sales Data'!$B:$B,J$19,'Log Sales Data'!$C:$C,$B$2,'Log Sales Data'!$D:$D,$B32,'Log Sales Data'!$G:$G,$A32) -> 107950 | K32: =SUMIFS('Log Sales Data'!$M:$M,'Log Sales Data'!$B:$B,K$19,'Log Sales Data'!$C:$C,$B$2,'Log Sales Data'!$D:$D,$B32,'Log Sales Data'!$G:$G,$A32) -> 0 | L32: =SUMIFS('Log Sales Data'!$M:$M,'Log Sales Data'!$B:$B,L$19,'Log Sales Data'!$C:$C,$B$2,'Log Sales Data'!$D:$D,$B32,'Log Sales Data'!$G:$G,$A32) -> 0 | M32: =SUMIFS('Log Sales Data'!$M:$M,'Log Sales Data'!$B:$B,M$19,'Log Sales Data'!$C:$C,$B$2,'Log Sales Data'!$D:$D,$B32,'Log Sales Data'!$G:$G,$A32) -> 0 | N32: =SUMIFS('Log Sales Data'!$M:$M,'Log Sales Data'!$B:$B,N$19,'Log Sales Data'!$C:$C,$B$2,'Log Sales Data'!$D:$D,$B32,'Log Sales Data'!$G:$G,$A32) -> 0 | O32: =SUMIFS('Log Sales Data'!$M:$M,'Log Sales Data'!$B:$B,O$19,'Log Sales Data'!$C:$C,$B$2,'Log Sales Data'!$D:$D,$B32,'Log Sales Data'!$G:$G,$A32) -> 0 | P32: =SUMIFS('Log Sales Data'!$M:$M,'Log Sales Data'!$B:$B,P$19,'Log Sales Data'!$C:$C,$B$2,'Log Sales Data'!$D:$D,$B32,'Log Sales Data'!$G:$G,$A32) -> 0 | Q32: =SUMIFS('Log Sales Data'!$M:$M,'Log Sales Data'!$B:$B,Q$19,'Log Sales Data'!$C:$C,$B$2,'Log Sales Data'!$D:$D,$B32,'Log Sales Data'!$G:$G,$A32) -> 0 | ... U32: =SUMIFS('Log Sales Data'!$M:$M,'Log Sales Data'!$B:$B,U$19,'Log Sales Data'!$C:$C,$B$2,'Log Sales Data'!$D:$D,$B32,'Log Sales Data'!$G:$G,$A32) -> 0
A33: Export | B33: K | C33: =IFERROR(F33/$F$46,0) -> 0.24801587 | D33: =_xlfn.XLOOKUP(B33,'Log Sales Data'!AA:AA,'Log Sales Data'!AB:AB,0,0) -> 0.99 | E33: Tonnes | F33: =SUMIFS('Log Sales Data'!$I:$I,'Log Sales Data'!$C:$C,$B$2,'Log Sales Data'!$D:$D,$B33,'Log Sales Data'!$G:$G,$A33) -> 1250 | G33: =IFERROR(H33/F33,"0") -> 120 | H33: =SUM(J33:U33) -> 150000 | J33: =SUMIFS('Log Sales Data'!$M:$M,'Log Sales Data'!$B:$B,J$19,'Log Sales Data'!$C:$C,$B$2,'Log Sales Data'!$D:$D,$B33,'Log Sales Data'!$G:$G,$A33) -> 150000 | K33: =SUMIFS('Log Sales Data'!$M:$M,'Log Sales Data'!$B:$B,K$19,'Log Sales Data'!$C:$C,$B$2,'Log Sales Data'!$D:$D,$B33,'Log Sales Data'!$G:$G,$A33) -> 0 | L33: =SUMIFS('Log Sales Data'!$M:$M,'Log Sales Data'!$B:$B,L$19,'Log Sales Data'!$C:$C,$B$2,'Log Sales Data'!$D:$D,$B33,'Log Sales Data'!$G:$G,$A33) -> 0 | M33: =SUMIFS('Log Sales Data'!$M:$M,'Log Sales Data'!$B:$B,M$19,'Log Sales Data'!$C:$C,$B$2,'Log Sales Data'!$D:$D,$B33,'Log Sales Data'!$G:$G,$A33) -> 0 | N33: =SUMIFS('Log Sales Data'!$M:$M,'Log Sales Data'!$B:$B,N$19,'Log Sales Data'!$C:$C,$B$2,'Log Sales Data'!$D:$D,$B33,'Log Sales Data'!$G:$G,$A33) -> 0 | O33: =SUMIFS('Log Sales Data'!$M:$M,'Log Sales Data'!$B:$B,O$19,'Log Sales Data'!$C:$C,$B$2,'Log Sales Data'!$D:$D,$B33,'Log Sales Data'!$G:$G,$A33) -> 0 | P33: =SUMIFS('Log Sales Data'!$M:$M,'Log Sales Data'!$B:$B,P$19,'Log Sales Data'!$C:$C,$B$2,'Log Sales Data'!$D:$D,$B33,'Log Sales Data'!$G:$G,$A33) -> 0 | Q33: =SUMIFS('Log Sales Data'!$M:$M,'Log Sales Data'!$B:$B,Q$19,'Log Sales Data'!$C:$C,$B$2,'Log Sales Data'!$D:$D,$B33,'Log Sales Data'!$G:$G,$A33) -> 0 | ... U33: =SUMIFS('Log Sales Data'!$M:$M,'Log Sales Data'!$B:$B,U$19,'Log Sales Data'!$C:$C,$B$2,'Log Sales Data'!$D:$D,$B33,'Log Sales Data'!$G:$G,$A33) -> 0
A34: Export | B34: KI | C34: =IFERROR(F34/$F$46,0) -> 0 | D34: =_xlfn.XLOOKUP(B34,'Log Sales Data'!AA:AA,'Log Sales Data'!AB:AB,0,0) -> 0.97 | E34: Tonnes | F34: =SUMIFS('Log Sales Data'!$I:$I,'Log Sales Data'!$C:$C,$B$2,'Log Sales Data'!$D:$D,$B34,'Log Sales Data'!$G:$G,$A34) -> 0 | G34: =IFERROR(H34/F34,"0") -> 0 | H34: =SUM(J34:U34) -> 0 | J34: =SUMIFS('Log Sales Data'!$M:$M,'Log Sales Data'!$B:$B,J$19,'Log Sales Data'!$C:$C,$B$2,'Log Sales Data'!$D:$D,$B34,'Log Sales Data'!$G:$G,$A34) -> 0 | K34: =SUMIFS('Log Sales Data'!$M:$M,'Log Sales Data'!$B:$B,K$19,'Log Sales Data'!$C:$C,$B$2,'Log Sales Data'!$D:$D,$B34,'Log Sales Data'!$G:$G,$A34) -> 0 | L34: =SUMIFS('Log Sales Data'!$M:$M,'Log Sales Data'!$B:$B,L$19,'Log Sales Data'!$C:$C,$B$2,'Log Sales Data'!$D:$D,$B34,'Log Sales Data'!$G:$G,$A34) -> 0 | M34: =SUMIFS('Log Sales Data'!$M:$M,'Log Sales Data'!$B:$B,M$19,'Log Sales Data'!$C:$C,$B$2,'Log Sales Data'!$D:$D,$B34,'Log Sales Data'!$G:$G,$A34) -> 0 | N34: =SUMIFS('Log Sales Data'!$M:$M,'Log Sales Data'!$B:$B,N$19,'Log Sales Data'!$C:$C,$B$2,'Log Sales Data'!$D:$D,$B34,'Log Sales Data'!$G:$G,$A34) -> 0 | O34: =SUMIFS('Log Sales Data'!$M:$M,'Log Sales Data'!$B:$B,O$19,'Log Sales Data'!$C:$C,$B$2,'Log Sales Data'!$D:$D,$B34,'Log Sales Data'!$G:$G,$A34) -> 0 | P34: =SUMIFS('Log Sales Data'!$M:$M,'Log Sales Data'!$B:$B,P$19,'Log Sales Data'!$C:$C,$B$2,'Log Sales Data'!$D:$D,$B34,'Log Sales Data'!$G:$G,$A34) -> 0 | Q34: =SUMIFS('Log Sales Data'!$M:$M,'Log Sales Data'!$B:$B,Q$19,'Log Sales Data'!$C:$C,$B$2,'Log Sales Data'!$D:$D,$B34,'Log Sales Data'!$G:$G,$A34) -> 0 | ... U34: =SUMIFS('Log Sales Data'!$M:$M,'Log Sales Data'!$B:$B,U$19,'Log Sales Data'!$C:$C,$B$2,'Log Sales Data'!$D:$D,$B34,'Log Sales Data'!$G:$G,$A34) -> 0
A35: Export | B35: KIS | C35: =IFERROR(F35/$F$46,0) -> 0 | D35: =_xlfn.XLOOKUP(B35,'Log Sales Data'!AA:AA,'Log Sales Data'!AB:AB,0,0) -> 0.88 | E35: Tonnes | F35: =SUMIFS('Log Sales Data'!$I:$I,'Log Sales Data'!$C:$C,$B$2,'Log Sales Data'!$D:$D,$B35,'Log Sales Data'!$G:$G,$A35) -> 0 | G35: =IFERROR(H35/F35,"0") -> 0 | H35: =SUM(J35:U35) -> 0 | J35: =SUMIFS('Log Sales Data'!$M:$M,'Log Sales Data'!$B:$B,J$19,'Log Sales Data'!$C:$C,$B$2,'Log Sales Data'!$D:$D,$B35,'Log Sales Data'!$G:$G,$A35) -> 0 | K35: =SUMIFS('Log Sales Data'!$M:$M,'Log Sales Data'!$B:$B,K$19,'Log Sales Data'!$C:$C,$B$2,'Log Sales Data'!$D:$D,$B35,'Log Sales Data'!$G:$G,$A35) -> 0 | L35: =SUMIFS('Log Sales Data'!$M:$M,'Log Sales Data'!$B:$B,L$19,'Log Sales Data'!$C:$C,$B$2,'Log Sales Data'!$D:$D,$B35,'Log Sales Data'!$G:$G,$A35) -> 0 | M35: =SUMIFS('Log Sales Data'!$M:$M,'Log Sales Data'!$B:$B,M$19,'Log Sales Data'!$C:$C,$B$2,'Log Sales Data'!$D:$D,$B35,'Log Sales Data'!$G:$G,$A35) -> 0 | N35: =SUMIFS('Log Sales Data'!$M:$M,'Log Sales Data'!$B:$B,N$19,'Log Sales Data'!$C:$C,$B$2,'Log Sales Data'!$D:$D,$B35,'Log Sales Data'!$G:$G,$A35) -> 0 | O35: =SUMIFS('Log Sales Data'!$M:$M,'Log Sales Data'!$B:$B,O$19,'Log Sales Data'!$C:$C,$B$2,'Log Sales Data'!$D:$D,$B35,'Log Sales Data'!$G:$G,$A35) -> 0 | P35: =SUMIFS('Log Sales Data'!$M:$M,'Log Sales Data'!$B:$B,P$19,'Log Sales Data'!$C:$C,$B$2,'Log Sales Data'!$D:$D,$B35,'Log Sales Data'!$G:$G,$A35) -> 0 | Q35: =SUMIFS('Log Sales Data'!$M:$M,'Log Sales Data'!$B:$B,Q$19,'Log Sales Data'!$C:$C,$B$2,'Log Sales Data'!$D:$D,$B35,'Log Sales Data'!$G:$G,$A35) -> 0 | ... U35: =SUMIFS('Log Sales Data'!$M:$M,'Log Sales Data'!$B:$B,U$19,'Log Sales Data'!$C:$C,$B$2,'Log Sales Data'!$D:$D,$B35,'Log Sales Data'!$G:$G,$A35) -> 0
A36: Export | B36: KI stub | C36: =IFERROR(F36/$F$46,0) -> 0 | D36: =_xlfn.XLOOKUP(B36,'Log Sales Data'!AA:AA,'Log Sales Data'!AB:AB,0,0) -> 0.97 | E36: Tonnes | F36: =SUMIFS('Log Sales Data'!$I:$I,'Log Sales Data'!$C:$C,$B$2,'Log Sales Data'!$D:$D,$B36,'Log Sales Data'!$G:$G,$A36) -> 0 | G36: =IFERROR(H36/F36,"0") -> 0 | H36: =SUM(J36:U36) -> 0 | J36: =SUMIFS('Log Sales Data'!$M:$M,'Log Sales Data'!$B:$B,J$19,'Log Sales Data'!$C:$C,$B$2,'Log Sales Data'!$D:$D,$B36,'Log Sales Data'!$G:$G,$A36) -> 0 | K36: =SUMIFS('Log Sales Data'!$M:$M,'Log Sales Data'!$B:$B,K$19,'Log Sales Data'!$C:$C,$B$2,'Log Sales Data'!$D:$D,$B36,'Log Sales Data'!$G:$G,$A36) -> 0 | L36: =SUMIFS('Log Sales Data'!$M:$M,'Log Sales Data'!$B:$B,L$19,'Log Sales Data'!$C:$C,$B$2,'Log Sales Data'!$D:$D,$B36,'Log Sales Data'!$G:$G,$A36) -> 0 | M36: =SUMIFS('Log Sales Data'!$M:$M,'Log Sales Data'!$B:$B,M$19,'Log Sales Data'!$C:$C,$B$2,'Log Sales Data'!$D:$D,$B36,'Log Sales Data'!$G:$G,$A36) -> 0 | N36: =SUMIFS('Log Sales Data'!$M:$M,'Log Sales Data'!$B:$B,N$19,'Log Sales Data'!$C:$C,$B$2,'Log Sales Data'!$D:$D,$B36,'Log Sales Data'!$G:$G,$A36) -> 0 | O36: =SUMIFS('Log Sales Data'!$M:$M,'Log Sales Data'!$B:$B,O$19,'Log Sales Data'!$C:$C,$B$2,'Log Sales Data'!$D:$D,$B36,'Log Sales Data'!$G:$G,$A36) -> 0 | P36: =SUMIFS('Log Sales Data'!$M:$M,'Log Sales Data'!$B:$B,P$19,'Log Sales Data'!$C:$C,$B$2,'Log Sales Data'!$D:$D,$B36,'Log Sales Data'!$G:$G,$A36) -> 0 | Q36: =SUMIFS('Log Sales Data'!$M:$M,'Log Sales Data'!$B:$B,Q$19,'Log Sales Data'!$C:$C,$B$2,'Log Sales Data'!$D:$D,$B36,'Log Sales Data'!$G:$G,$A36) -> 0 | ... U36: =SUMIFS('Log Sales Data'!$M:$M,'Log Sales Data'!$B:$B,U$19,'Log Sales Data'!$C:$C,$B$2,'Log Sales Data'!$D:$D,$B36,'Log Sales Data'!$G:$G,$A36) -> 0
A37: Export | B37: CF+ | C37: =IFERROR(F37/$F$46,0) -> 0 | D37: =_xlfn.XLOOKUP(B37,'Log Sales Data'!AA:AA,'Log Sales Data'!AB:AB,0,0) -> 1.03 | E37: Tonnes | F37: =SUMIFS('Log Sales Data'!$I:$I,'Log Sales Data'!$C:$C,$B$2,'Log Sales Data'!$D:$D,$B37,'Log Sales Data'!$G:$G,$A37) -> 0 | G37: =IFERROR(H37/F37,"0") -> 0 | H37: =SUM(J37:U37) -> 0 | J37: =SUMIFS('Log Sales Data'!$M:$M,'Log Sales Data'!$B:$B,J$19,'Log Sales Data'!$C:$C,$B$2,'Log Sales Data'!$D:$D,$B37,'Log Sales Data'!$G:$G,$A37) -> 0 | K37: =SUMIFS('Log Sales Data'!$M:$M,'Log Sales Data'!$B:$B,K$19,'Log Sales Data'!$C:$C,$B$2,'Log Sales Data'!$D:$D,$B37,'Log Sales Data'!$G:$G,$A37) -> 0 | L37: =SUMIFS('Log Sales Data'!$M:$M,'Log Sales Data'!$B:$B,L$19,'Log Sales Data'!$C:$C,$B$2,'Log Sales Data'!$D:$D,$B37,'Log Sales Data'!$G:$G,$A37) -> 0 | M37: =SUMIFS('Log Sales Data'!$M:$M,'Log Sales Data'!$B:$B,M$19,'Log Sales Data'!$C:$C,$B$2,'Log Sales Data'!$D:$D,$B37,'Log Sales Data'!$G:$G,$A37) -> 0 | N37: =SUMIFS('Log Sales Data'!$M:$M,'Log Sales Data'!$B:$B,N$19,'Log Sales Data'!$C:$C,$B$2,'Log Sales Data'!$D:$D,$B37,'Log Sales Data'!$G:$G,$A37) -> 0 | O37: =SUMIFS('Log Sales Data'!$M:$M,'Log Sales Data'!$B:$B,O$19,'Log Sales Data'!$C:$C,$B$2,'Log Sales Data'!$D:$D,$B37,'Log Sales Data'!$G:$G,$A37) -> 0 | P37: =SUMIFS('Log Sales Data'!$M:$M,'Log Sales Data'!$B:$B,P$19,'Log Sales Data'!$C:$C,$B$2,'Log Sales Data'!$D:$D,$B37,'Log Sales Data'!$G:$G,$A37) -> 0 | Q37: =SUMIFS('Log Sales Data'!$M:$M,'Log Sales Data'!$B:$B,Q$19,'Log Sales Data'!$C:$C,$B$2,'Log Sales Data'!$D:$D,$B37,'Log Sales Data'!$G:$G,$A37) -> 0 | ... U37: =SUMIFS('Log Sales Data'!$M:$M,'Log Sales Data'!$B:$B,U$19,'Log Sales Data'!$C:$C,$B$2,'Log Sales Data'!$D:$D,$B37,'Log Sales Data'!$G:$G,$A37) -> 0
A38: Export | B38: CF- | C38: =IFERROR(F38/$F$46,0) -> 0 | D38: =_xlfn.XLOOKUP(B38,'Log Sales Data'!AA:AA,'Log Sales Data'!AB:AB,0,0) -> 0.99 | E38: Tonnes | F38: =SUMIFS('Log Sales Data'!$I:$I,'Log Sales Data'!$C:$C,$B$2,'Log Sales Data'!$D:$D,$B38,'Log Sales Data'!$G:$G,$A38) -> 0 | G38: =IFERROR(H38/F38,"0") -> 0 | H38: =SUM(J38:U38) -> 0 | J38: =SUMIFS('Log Sales Data'!$M:$M,'Log Sales Data'!$B:$B,J$19,'Log Sales Data'!$C:$C,$B$2,'Log Sales Data'!$D:$D,$B38,'Log Sales Data'!$G:$G,$A38) -> 0 | K38: =SUMIFS('Log Sales Data'!$M:$M,'Log Sales Data'!$B:$B,K$19,'Log Sales Data'!$C:$C,$B$2,'Log Sales Data'!$D:$D,$B38,'Log Sales Data'!$G:$G,$A38) -> 0 | L38: =SUMIFS('Log Sales Data'!$M:$M,'Log Sales Data'!$B:$B,L$19,'Log Sales Data'!$C:$C,$B$2,'Log Sales Data'!$D:$D,$B38,'Log Sales Data'!$G:$G,$A38) -> 0 | M38: =SUMIFS('Log Sales Data'!$M:$M,'Log Sales Data'!$B:$B,M$19,'Log Sales Data'!$C:$C,$B$2,'Log Sales Data'!$D:$D,$B38,'Log Sales Data'!$G:$G,$A38) -> 0 | N38: =SUMIFS('Log Sales Data'!$M:$M,'Log Sales Data'!$B:$B,N$19,'Log Sales Data'!$C:$C,$B$2,'Log Sales Data'!$D:$D,$B38,'Log Sales Data'!$G:$G,$A38) -> 0 | O38: =SUMIFS('Log Sales Data'!$M:$M,'Log Sales Data'!$B:$B,O$19,'Log Sales Data'!$C:$C,$B$2,'Log Sales Data'!$D:$D,$B38,'Log Sales Data'!$G:$G,$A38) -> 0 | P38: =SUMIFS('Log Sales Data'!$M:$M,'Log Sales Data'!$B:$B,P$19,'Log Sales Data'!$C:$C,$B$2,'Log Sales Data'!$D:$D,$B38,'Log Sales Data'!$G:$G,$A38) -> 0 | Q38: =SUMIFS('Log Sales Data'!$M:$M,'Log Sales Data'!$B:$B,Q$19,'Log Sales Data'!$C:$C,$B$2,'Log Sales Data'!$D:$D,$B38,'Log Sales Data'!$G:$G,$A38) -> 0 | ... U38: =SUMIFS('Log Sales Data'!$M:$M,'Log Sales Data'!$B:$B,U$19,'Log Sales Data'!$C:$C,$B$2,'Log Sales Data'!$D:$D,$B38,'Log Sales Data'!$G:$G,$A38) -> 0
A39: Export | B39: CM | C39: =IFERROR(F39/$F$46,0) -> 0 | D39: =_xlfn.XLOOKUP(B39,'Log Sales Data'!AA:AA,'Log Sales Data'!AB:AB,0,0) -> 0.97 | E39: Tonnes | F39: =SUMIFS('Log Sales Data'!$I:$I,'Log Sales Data'!$C:$C,$B$2,'Log Sales Data'!$D:$D,$B39,'Log Sales Data'!$G:$G,$A39) -> 0 | G39: =IFERROR(H39/F39,"0") -> 0 | H39: =SUM(J39:U39) -> 0 | J39: =SUMIFS('Log Sales Data'!$M:$M,'Log Sales Data'!$B:$B,J$19,'Log Sales Data'!$C:$C,$B$2,'Log Sales Data'!$D:$D,$B39,'Log Sales Data'!$G:$G,$A39) -> 0 | K39: =SUMIFS('Log Sales Data'!$M:$M,'Log Sales Data'!$B:$B,K$19,'Log Sales Data'!$C:$C,$B$2,'Log Sales Data'!$D:$D,$B39,'Log Sales Data'!$G:$G,$A39) -> 0 | L39: =SUMIFS('Log Sales Data'!$M:$M,'Log Sales Data'!$B:$B,L$19,'Log Sales Data'!$C:$C,$B$2,'Log Sales Data'!$D:$D,$B39,'Log Sales Data'!$G:$G,$A39) -> 0 | M39: =SUMIFS('Log Sales Data'!$M:$M,'Log Sales Data'!$B:$B,M$19,'Log Sales Data'!$C:$C,$B$2,'Log Sales Data'!$D:$D,$B39,'Log Sales Data'!$G:$G,$A39) -> 0 | N39: =SUMIFS('Log Sales Data'!$M:$M,'Log Sales Data'!$B:$B,N$19,'Log Sales Data'!$C:$C,$B$2,'Log Sales Data'!$D:$D,$B39,'Log Sales Data'!$G:$G,$A39) -> 0 | O39: =SUMIFS('Log Sales Data'!$M:$M,'Log Sales Data'!$B:$B,O$19,'Log Sales Data'!$C:$C,$B$2,'Log Sales Data'!$D:$D,$B39,'Log Sales Data'!$G:$G,$A39) -> 0 | P39: =SUMIFS('Log Sales Data'!$M:$M,'Log Sales Data'!$B:$B,P$19,'Log Sales Data'!$C:$C,$B$2,'Log Sales Data'!$D:$D,$B39,'Log Sales Data'!$G:$G,$A39) -> 0 | Q39: =SUMIFS('Log Sales Data'!$M:$M,'Log Sales Data'!$B:$B,Q$19,'Log Sales Data'!$C:$C,$B$2,'Log Sales Data'!$D:$D,$B39,'Log Sales Data'!$G:$G,$A39) -> 0 | ... U39: =SUMIFS('Log Sales Data'!$M:$M,'Log Sales Data'!$B:$B,U$19,'Log Sales Data'!$C:$C,$B$2,'Log Sales Data'!$D:$D,$B39,'Log Sales Data'!$G:$G,$A39) -> 0
A40: Export | B40: Euc A | C40: =IFERROR(F40/$F$46,0) -> 0 | D40: =_xlfn.XLOOKUP(B40,'Log Sales Data'!AA:AA,'Log Sales Data'!AB:AB,0,0) -> 0.95 | E40: Tonnes | F40: =SUMIFS('Log Sales Data'!$I:$I,'Log Sales Data'!$C:$C,$B$2,'Log Sales Data'!$D:$D,$B40,'Log Sales Data'!$G:$G,$A40) -> 0 | G40: =IFERROR(H40/F40,"0") -> 0 | H40: =SUM(J40:U40) -> 0 | J40: =SUMIFS('Log Sales Data'!$M:$M,'Log Sales Data'!$B:$B,J$19,'Log Sales Data'!$C:$C,$B$2,'Log Sales Data'!$D:$D,$B40,'Log Sales Data'!$G:$G,$A40) -> 0 | K40: =SUMIFS('Log Sales Data'!$M:$M,'Log Sales Data'!$B:$B,K$19,'Log Sales Data'!$C:$C,$B$2,'Log Sales Data'!$D:$D,$B40,'Log Sales Data'!$G:$G,$A40) -> 0 | L40: =SUMIFS('Log Sales Data'!$M:$M,'Log Sales Data'!$B:$B,L$19,'Log Sales Data'!$C:$C,$B$2,'Log Sales Data'!$D:$D,$B40,'Log Sales Data'!$G:$G,$A40) -> 0 | M40: =SUMIFS('Log Sales Data'!$M:$M,'Log Sales Data'!$B:$B,M$19,'Log Sales Data'!$C:$C,$B$2,'Log Sales Data'!$D:$D,$B40,'Log Sales Data'!$G:$G,$A40) -> 0 | N40: =SUMIFS('Log Sales Data'!$M:$M,'Log Sales Data'!$B:$B,N$19,'Log Sales Data'!$C:$C,$B$2,'Log Sales Data'!$D:$D,$B40,'Log Sales Data'!$G:$G,$A40) -> 0 | O40: =SUMIFS('Log Sales Data'!$M:$M,'Log Sales Data'!$B:$B,O$19,'Log Sales Data'!$C:$C,$B$2,'Log Sales Data'!$D:$D,$B40,'Log Sales Data'!$G:$G,$A40) -> 0 | P40: =SUMIFS('Log Sales Data'!$M:$M,'Log Sales Data'!$B:$B,P$19,'Log Sales Data'!$C:$C,$B$2,'Log Sales Data'!$D:$D,$B40,'Log Sales Data'!$G:$G,$A40) -> 0 | Q40: =SUMIFS('Log Sales Data'!$M:$M,'Log Sales Data'!$B:$B,Q$19,'Log Sales Data'!$C:$C,$B$2,'Log Sales Data'!$D:$D,$B40,'Log Sales Data'!$G:$G,$A40) -> 0 | ... U40: =SUMIFS('Log Sales Data'!$M:$M,'Log Sales Data'!$B:$B,U$19,'Log Sales Data'!$C:$C,$B$2,'Log Sales Data'!$D:$D,$B40,'Log Sales Data'!$G:$G,$A40) -> 0
A41: Export | B41: Euc K | C41: =IFERROR(F41/$F$46,0) -> 0 | D41: =_xlfn.XLOOKUP(B41,'Log Sales Data'!AA:AA,'Log Sales Data'!AB:AB,0,0) -> 0.93 | E41: Tonnes | F41: =SUMIFS('Log Sales Data'!$I:$I,'Log Sales Data'!$C:$C,$B$2,'Log Sales Data'!$D:$D,$B41,'Log Sales Data'!$G:$G,$A41) -> 0 | G41: =IFERROR(H41/F41,"0") -> 0 | H41: =SUM(J41:U41) -> 0 | J41: =SUMIFS('Log Sales Data'!$M:$M,'Log Sales Data'!$B:$B,J$19,'Log Sales Data'!$C:$C,$B$2,'Log Sales Data'!$D:$D,$B41,'Log Sales Data'!$G:$G,$A41) -> 0 | K41: =SUMIFS('Log Sales Data'!$M:$M,'Log Sales Data'!$B:$B,K$19,'Log Sales Data'!$C:$C,$B$2,'Log Sales Data'!$D:$D,$B41,'Log Sales Data'!$G:$G,$A41) -> 0 | L41: =SUMIFS('Log Sales Data'!$M:$M,'Log Sales Data'!$B:$B,L$19,'Log Sales Data'!$C:$C,$B$2,'Log Sales Data'!$D:$D,$B41,'Log Sales Data'!$G:$G,$A41) -> 0 | M41: =SUMIFS('Log Sales Data'!$M:$M,'Log Sales Data'!$B:$B,M$19,'Log Sales Data'!$C:$C,$B$2,'Log Sales Data'!$D:$D,$B41,'Log Sales Data'!$G:$G,$A41) -> 0 | N41: =SUMIFS('Log Sales Data'!$M:$M,'Log Sales Data'!$B:$B,N$19,'Log Sales Data'!$C:$C,$B$2,'Log Sales Data'!$D:$D,$B41,'Log Sales Data'!$G:$G,$A41) -> 0 | O41: =SUMIFS('Log Sales Data'!$M:$M,'Log Sales Data'!$B:$B,O$19,'Log Sales Data'!$C:$C,$B$2,'Log Sales Data'!$D:$D,$B41,'Log Sales Data'!$G:$G,$A41) -> 0 | P41: =SUMIFS('Log Sales Data'!$M:$M,'Log Sales Data'!$B:$B,P$19,'Log Sales Data'!$C:$C,$B$2,'Log Sales Data'!$D:$D,$B41,'Log Sales Data'!$G:$G,$A41) -> 0 | Q41: =SUMIFS('Log Sales Data'!$M:$M,'Log Sales Data'!$B:$B,Q$19,'Log Sales Data'!$C:$C,$B$2,'Log Sales Data'!$D:$D,$B41,'Log Sales Data'!$G:$G,$A41) -> 0 | ... U41: =SUMIFS('Log Sales Data'!$M:$M,'Log Sales Data'!$B:$B,U$19,'Log Sales Data'!$C:$C,$B$2,'Log Sales Data'!$D:$D,$B41,'Log Sales Data'!$G:$G,$A41) -> 0
C42: =SUM(C20:C41) -> 1
B43: Export Sales | C43: =SUMIF(A20:A43,"Export",C20:C43) -> 0.50595238 | H43: =SUM(J43:U43) -> 345700 | J43: =SUM(J28:J41) -> 345700 | K43: =SUM(K28:K41) -> 0 | L43: =SUM(L28:L41) -> 0 | M43: =SUM(M28:M41) -> 0 | N43: =SUM(N28:N41) -> 0 | O43: =SUM(O28:O41) -> 0 | P43: =SUM(P28:P41) -> 0 | Q43: =SUM(Q28:Q41) -> 0 | ... U43: =SUM(U28:U41) -> 0
B44: Domestic Sales | C44: =SUMIF(A20:A43,"Domestic",C20:C43) -> 0.49404762 | H44: =SUM(J44:U44) -> 336860 | J44: =SUM(J20:J27) -> 336860 | K44: =SUM(K20:K27) -> 0 | L44: =SUM(L20:L27) -> 0 | M44: =SUM(M20:M27) -> 0 | N44: =SUM(N20:N27) -> 0 | O44: =SUM(O20:O27) -> 0 | P44: =SUM(P20:P27) -> 0 | Q44: =SUM(Q20:Q27) -> 0 | ... U44: =SUM(U20:U27) -> 0
F45: Tonnes | G45: JAS
B46: TOTAL | E46: GRAND TOTAL | F46: =SUM(F20:F41) -> 5040 | G46: =SUMIF('Log Sales Data'!C:C,B2,'Log Sales Data'!K:K) -> 5140.5 | H46: =SUM(H20:H41) -> 682560 | J46: =SUM(J20:J41) -> 682560 | K46: =SUM(K20:K41) -> 0 | L46: =SUM(L20:L41) -> 0 | M46: =SUM(M20:M41) -> 0 | N46: =SUM(N20:N41) -> 0 | O46: =SUM(O20:O41) -> 0 | P46: =SUM(P20:P41) -> 0 | Q46: =SUM(Q20:Q41) -> 0 | ... U46: =SUM(U20:U41) -> 0 | W46: =SUM(J46:U46) -> 682560
B48: COSTS | C48: Op Code | D48: Activity
B49: Log and Load | C49: 300/01 | D49: Logging
H50: TOTAL | J50: 45658 | K50: 45689 | L50: 45717 | M50: 45748 | N50: 45778 | O50: 45809 | P50: 45839 | Q50: 45870 | R50: 45901 | S50: 45931 | T50: 45962 | U50: 45992
G51: =H51/W16 -> #DIV/0! | H51: =SUM(J51:U51) -> 0 | W51: =SUM(J51:U51) -> 0
B54: Log Transport
B55: Grade | C55: Op Code | D55: Activity | E55: Destination | F55: Destination | G55: Cost/t | H55: TOTAL | J55: 45658 | K55: 45689 | L55: 45717 | M55: 45748 | N55: 45778 | O55: 45809 | P55: 45839 | Q55: 45870 | R55: 45901 | S55: 45931 | T55: 45962 | U55: 45992
B56: P35 | C56: 300/02 | D56: Transport | E56: Domestic | H56: =SUM(J56:U56) -> 0
B57: S30 | C57: 300/02 | D57: Transport | E57: Domestic | H57: 0
B58: S20 | C58: 300/02 | D58: Transport | E58: Domestic | H58: =SUM(J58:U58) -> 0
B59: Domestic Pulp | C59: 300/02 | D59: Transport | E59: Domestic | H59: =SUM(J59:U59) -> 0
B60: Eucalyptus | C60: 300/02 | D60: Transport | E60: Domestic | H60: =SUM(J60:U60) -> 0
B61: FW | C61: 300/02 | D61: Transport | E61: Domestic | H61: =SUM(J61:U61) -> 0
B62: Euc Pulp | C62: 300/02 | D62: Transport | E62: Domestic | H62: =SUM(J62:U62) -> 0
B63: Binwood | C63: 300/02 | D63: Transport | E63: Domestic | H63: =SUM(J63:U63) -> 0
B64: P40 | C64: 300/02 | D64: Transport | E64: AWG | H64: =SUM(J64:U64) -> 0
B65: P30 | C65: 300/02 | D65: Transport | E65: AWG | H65: =SUM(J65:U65) -> 0
B66: AO | C66: 300/02 | D66: Transport | E66: AWG | H66: =SUM(J66:U66) -> 0
B67: A | C67: 300/02 | D67: Transport | E67: AWG | H67: =SUM(J67:U67) -> 0
B68: K | C68: 300/02 | D68: Transport | E68: AWG | H68: =SUM(J68:U68) -> 0
B69: KI | C69: 300/02 | D69: Transport | E69: AWG | H69: =SUM(J69:U69) -> 0
... B74: CM | C74: 300/02 | D74: Transport | E74: AWG | H74: =SUM(J74:U74) -> 0
B75: Euc A | C75: 300/02 | D75: Transport | H75: =SUM(J75:U75) -> 0
B76: Euc K | C76: 300/02 | D76: Transport | H76: =SUM(J76:U76) -> 0
B77: Spare grade | C77: 300/02 | D77: Transport | H77: =SUM(J77:U77) -> 0
G78: =H78/W16 -> #DIV/0! | H78: =SUM(H56:H77) -> 0 | W78: =SUM(J78:U78) -> 0
B80: Non-docket costs
B81: Operation | C81: Op Code | D81: Activity | E81: Resource | F81: Product | G81: Destination | H81: TOTAL | J81: 45658 | K81: 45689 | L81: 45717 | M81: 45748 | N81: 45778 | O81: 45809 | P81: 45839 | Q81: 45870 | R81: 45901 | S81: 45931 | T81: 45962 | U81: 45992
B82: Tracking | C82: 300/04 | D82: Logging | H82: =SUM(J82:U82) -> 0
B83: Logging Machinery establishment/transportation | C83: 300/06 | D83: Logging | E83: 699 | F83: 3675 | H83: =SUM(J83:U83) -> 0
B84: Road control | C84: 300/16 | D84: Logging | E84: 699 | F84: 3691 | H84: =SUM(J84:U84) -> 0
B85: Powerline costs | C85: 300/17 | D85: Logging | E85: 699 | F85: 3677 | H85: =SUM(J85:U85) -> 0
B86: Fencing & gate construction | C86: 721 | D86: Logging | E86: 699 | F86: 3671 | H86: =SUM(J86:U86) -> 0
B87: Deadman | C87: 300/18 | D87: Logging | E87: 699 | F87: 3669 | H87: =SUM(J87:U87) -> 0
B88: Two-stage | C88: 300/19 | D88: Logging | E88: 699 | F88: 3665 | H88: =SUM(J88:U88) -> 0
B89: Harvest Planning | C89: 300/09 | D89: Logging | E89: 699 | F89: 3963 | H89: =SUM(J89:U89) -> 0
B90: Roading machinery establishment/transportation | C90: 300/07 | D90: Infrastructure | H90: =SUM(J90:U90) -> 0
B91: New Road Metalled or sealed | C91: 720 | D91: Infrastructure | H91: =SUM(J91:U91) -> 0 | J91: =J115 -> 0 | K91: =K115 -> 0 | L91: =L115 -> 0 | M91: =M115 -> 0 | N91: =N115 -> 0 | O91: =O115 -> 0 | P91: =P115 -> 0 | Q91: =Q115 -> 0 | ... U91: =U115 -> 0
B92: Upgrade Road metalled or sealed | C92: 720 | D92: Infrastructure | H92: =SUM(J92:U92) -> 0
B93: Other infrastructure | C93: 720 | D93: Infrastructure | H93: =SUM(J93:U93) -> 0
B94: Skid construction | C94: 300/05 | D94: Infrastructure | H94: =SUM(J94:U94) -> 0 | J94: =J119 -> 0 | K94: =K119 -> 0 | L94: =L119 -> 0 | M94: =M119 -> 0 | N94: =N119 -> 0 | O94: =O119 -> 0 | P94: =P119 -> 0 | Q94: =Q119 -> 0 | ... U94: =U119 -> 0
B95: Pad construction | C95: 300/05 | D95: Infrastructure | H95: =SUM(J95:U95) -> 0 | J95: =J120 -> 0 | K95: =K120 -> 0 | L95: =L120 -> 0 | M95: =M120 -> 0 | N95: =N120 -> 0 | O95: =O120 -> 0 | P95: =P120 -> 0 | Q95: =Q120 -> 0 | ... U95: =U120 -> 0
B96: Maintenance Forest Road | C96: 305 | D96: Maintenance | H96: =SUM(J96:U96) -> 0
B97: Maintenance Public Road | C97: 306 | D97: Maintenance | H97: =SUM(J97:U97) -> 0
B98: Skid/Pad maintenance | C98: 300/14 | D98: Post harvest costs | H98: =SUM(J98:U98) -> 0
B99: Post-harvest clean-up | C99: 300/10 | D99: Post harvest costs | H99: =SUM(J99:U99) -> 0
B100: Health and safety and Auditing | C100: 300/11 | D100: Indirect costs | H100: =SUM(J100:U100) -> 0
B101: Weighbridge | C101: 300/03 | D101: Indirect costs | G101: =H101/$W$16 -> #DIV/0! | H101: =SUM(J101:U101) -> 0
B102: Environmental monitoring/consents | C102: 330/04 | D102: Indirect costs | E102: 365 | H102: =SUM(J102:U102) -> 0
B103: Forest levy | C103: 300/08 | D103: Mgmt/Admin | E103: 338 | G103: 0.33 | H103: =SUM(J103:U103) -> 0 | J103: =$G$103*J16 -> 0 | K103: =$G$103*K16 -> 0 | L103: =$G$103*L16 -> 0 | M103: =$G$103*M16 -> 0 | N103: =$G$103*N16 -> 0 | O103: =$G$103*O16 -> 0 | P103: =$G$103*P16 -> 0 | Q103: =$G$103*Q16 -> 0 | ... U103: =$G$103*U16 -> 0
B104: Insurance Payment protection (domestic sales only) | C104: 351 | D104: Mgmt/Admin | E104: 324 | G104: 0.0016 | H104: =SUM(J104:U104) -> 10.92096 | J104: =$G$104*J46/100 -> 10.92096 | K104: =$G$104*K46/100 -> 0 | L104: =$G$104*L46/100 -> 0 | M104: =$G$104*M46/100 -> 0 | N104: =$G$104*N46/100 -> 0 | O104: =$G$104*O46/100 -> 0 | P104: =$G$104*P46/100 -> 0 | Q104: =$G$104*Q46/100 -> 0 | ... U104: =$G$104*U46/100 -> 0
B105: Harvest management fee | C105: 300/12 | D105: Mgmt/Admin | G105: 3.75 | H105: =SUM(J105:U105) -> 0 | J105: =$G$105*J16 -> 0 | K105: =$G$105*K16 -> 0 | L105: =$G$105*L16 -> 0 | M105: =$G$105*M16 -> 0 | N105: =$G$105*N16 -> 0 | O105: =$G$105*O16 -> 0 | P105: =$G$105*P16 -> 0 | Q105: =$G$105*Q16 -> 0 | ... U105: =$G$105*U16 -> 0
B107: Total non-docket costs | G107: =H107/B127 -> #DIV/0! | H107: =SUM(H82:H105) -> 10.92096 | J107: =SUM(J82:J105) -> 10.92096 | K107: =SUM(K82:K105) -> 0 | L107: =SUM(L82:L105) -> 0 | M107: =SUM(M82:M105) -> 0 | N107: =SUM(N82:N105) -> 0 | O107: =SUM(O82:O105) -> 0 | P107: =SUM(P82:P105) -> 0 | Q107: =SUM(Q82:Q105) -> 0 | ... U107: =SUM(U82:U105) -> 0
B109: Total Costs | H109: =H51+H78+H107 -> 10.92096 | J109: =J51+J78+J107 -> 10.92096 | K109: =K51+K78+K107 -> 0 | L109: =L51+L78+L107 -> 0 | M109: =M51+M78+M107 -> 0 | N109: =N51+N78+N107 -> 0 | O109: =O51+O78+O107 -> 0 | P109: =P51+P78+P107 -> 0 | Q109: =Q51+Q78+Q107 -> 0 | ... U109: =U51+U78+U107 -> 0 | W109: =SUM(J109:U109) -> 10.92096
B111: Net Harvest Total | H111: =H46-H109 -> 682549.08 | J111: =J46-J109 -> 682549.08 | K111: =K46-K109 -> 0 | L111: =L46-L109 -> 0 | M111: =M46-M109 -> 0 | N111: =N46-N109 -> 0 | O111: =O46-O109 -> 0 | P111: =P46-P109 -> 0 | Q111: =Q46-Q109 -> 0 | ... U111: =U46-U109 -> 0 | W111: =SUM(J111:U111) -> 682549.08
B113: Engineering | C113: Op Code | D113: Activity | E113: Unit | F113: Vol | G113: Unit Rate | J113: Metres constructed or number of skids/pads
...

Sheet Waipuna Budget
C1: 2025 | D1: Input
B2: Waipuna | H2: Estimated Tonnes (ha)
B3: PRODUCTION & RATE | G3: Total Monthly Working Days | I3: =IF(NOT(ISBLANK(J5)), J5, IF(NOT(ISBLANK(J8)), J8, IF(NOT(ISBLANK(J11)), J11, 0)))+IF(NOT(ISBLANK(K5)), K5, IF(NOT(ISBLANK(K8)), K8, IF(NOT(ISBLANK(K11)), K11, 0)))+IF(NOT(ISBLANK(L5)), L5, IF(NOT(ISBLANK(L8)), L8, IF(NOT(ISBLANK(L11)), L11, 0)))+IF(NOT(ISBLANK(M5)), M5, IF(NOT(ISBLANK(M8)), M8, IF(NOT(ISBLANK(M11)), M11, 0)))+IF(NOT(ISBLANK(N5)), N5, IF(NOT(ISBLANK(N8)), N8, IF(NOT(ISBLANK(N11)), N11, 0)))+IF(NOT(ISBLANK(O5)), O5, IF(NOT(ISBLANK(O8)), O8, IF(NOT(ISBLANK(O11)), O11, 0)))+IF(NOT(ISBLANK(P5)), P5, IF(NOT(ISBLANK(P8)), P8, IF(NOT(ISBLANK(P11)), P11, 0)))+IF(NOT(ISBLANK(Q5)), Q5, IF(NOT(ISBLANK(Q8)), Q8, IF(NOT(ISBLANK(Q11)), Q11, 0)))+IF(NOT(ISBLANK(R5)), R5, IF(NOT(ISBLANK(R8)), R8, IF(NOT(ISBLANK(R11)), R11, 0)))+IF(NOT(ISBLANK(S5)), S5, IF(NOT(ISBLANK(S8)), S8, IF(NOT(ISBLANK(S11)), S11, 0)))+IF(NOT(ISBLANK(T5)), T5, IF(NOT(ISBLANK(T8)), T8, IF(NOT(ISBLANK(T11)), T11, 0)))+IF(NOT(ISBLANK(U5)), U5, IF(NOT(ISBLANK(U8)), U8, IF(NOT(ISBLANK(U11)), U11, 0))) -> 0 | J3: 45658 | K3: 45689 | L3: 45717 | M3: 45748 | N3: 45778 | O3: 45809 | P3: 45839 | Q3: 45870 | R3: 45901 | S3: 45931 | T3: 45962 | U3: 45992 | W3: Total
G4: Groundbase | H4: Daily production | I4: =IFERROR((J4*J5+K4*K5+L4*L5+M4*M5+N4*N5+O4*O5+P4*P5+Q4*Q5+R4*R5+S4*S5+T4*T5+U4*U5)/$W$16,0) -> 0
H5: Days worked
H6: Harvesting Rate
G7: Roadline | H7: Daily production | I7: =IFERROR((J7*J8+K7*K8+L7*L8+M7*M8+N7*N8+O7*O8+P7*P8+Q7*Q8+R7*R8+S7*S8+T7*T8+U7*U8)/$W$16,0) -> 0
H8: Days worked
H9: Harvesting Rate
G10: Hauler | H10: Daily production | I10: =IFERROR((J10*J11+K10*K11+L10*L11+M10*M11+N10*N11+O10*O11+P10*P11+Q10*Q11+R10*R11+S10*S11+T10*T11+U10*U11)/$W$16,0) -> 0
H11: Days worked
H12: Harvesting Rate
G13: Average | H13: Harvesting Rate | I13: =SUM(I4:I12) -> 0 | J13: =IFERROR((J4*J5*J6+J7*J8*J9+J10*J11*J12)/J16,0) -> 0 | K13: =IFERROR((K4*K5*K6+K7*K8*K9+K10*K11*K12)/K16,0) -> 0 | L13: =IFERROR((L4*L5*L6+L7*L8*L9+L10*L11*L12)/L16,0) -> 0 | M13: =IFERROR((M4*M5*M6+M7*M8*M9+M10*M11*M12)/M16,0) -> 0 | N13: =IFERROR((N4*N5*N6+N7*N8*N9+N10*N11*N12)/N16,0) -> 0 | O13: =IFERROR((O4*O5*O6+O7*O8*O9+O10*O11*O12)/O16,0) -> 0 | P13: =IFERROR((P4*P5*P6+P7*P8*P9+P10*P11*P12)/P16,0) -> 0 | Q13: =IFERROR((Q4*Q5*Q6+Q7*Q8*Q9+Q10*Q11*Q12)/Q16,0) -> 0 | ... U13: =IFERROR((U4*U5*U6+U7*U8*U9+U10*U11*U12)/U16,0) -> 0 | W13: =I3 -> 0 | X13: Monthly Working Days
G14: Average | H14: Daily production | J14: =J4+J7+J10 -> 0 | K14: =K4+K7+K10 -> 0 | L14: =L4+L7+L10 -> 0 | M14: =M4+M7+M10 -> 0 | N14: =N4+N7+N10 -> 0 | O14: =O4+O7+O10 -> 0 | P14: =P4+P7+P10 -> 0 | Q14: =Q4+Q7+Q10 -> 0 | ... U14: =U4+U7+U10 -> 0 | W14: =IF(W16=0,0,W16/W15) -> 0 | X14: =H2 -> Estimated Tonnes (ha)
G15: Total | H15: Hectare (ha) | J15: =IFERROR(J16/$I$2,0) -> 0 | K15: =IFERROR(K16/$I$2,0) -> 0 | L15: =IFERROR(L16/$I$2,0) -> 0 | M15: =IFERROR(M16/$I$2,0) -> 0 | N15: =IFERROR(N16/$I$2,0) -> 0 | O15: =IFERROR(O16/$I$2,0) -> 0 | P15: =IFERROR(P16/$I$2,0) -> 0 | Q15: =IFERROR(Q16/$I$2,0) -> 0 | ... U15: =IFERROR(U16/$I$2,0) -> 0 | W15: =SUM(J15:U15) -> 0 | X15: =H15 -> Hectare (ha)
G16: Total | H16: Tonnes Harvested | J16: =IFERROR((J4*J5+J7*J8+J10*J11),0) -> 0 | K16: =IFERROR((K4*K5+K7*K8+K10*K11),0) -> 0 | L16: =IFERROR((L4*L5+L7*L8+L10*L11),0) -> 0 | M16: =IFERROR((M4*M5+M7*M8+M10*M11),0) -> 0 | N16: =IFERROR((N4*N5+N7*N8+N10*N11),0) -> 0 | O16: =IFERROR((O4*O5+O7*O8+O10*O11),0) -> 0 | P16: =IFERROR((P4*P5+P7*P8+P10*P11),0) -> 0 | Q16: =IFERROR((Q4*Q5+Q7*Q8+Q10*Q11),0) -> 0 | ... U16: =IFERROR((U4*U5+U7*U8+U10*U11),0) -> 0 | W16: =SUM(J16:U16) -> 0 | X16: =H16 -> Tonnes Harvested
W17: =W16/W15 -> #DIV/0! | X17: Vol/ha
B18: REVENUE
B19: Grade | C19: Grade Mix % | D19: Conversion Rate | E19: Sale unit | F19: Sale unit/Vol | G19: Price/Unit | H19: TOTAL | J19: 45658 | K19: 45689 | L19: 45717 | M19: 45748 | N19: 45778 | O19: 45809 | P19: 45839 | Q19: 45870 | R19: 45901 | S19: 45931 | T19: 45962 | U19: 45992
B20: P35 | C20: 0.11412433 | D20: 1 | E20: Tonnes | F20: =IFERROR(H20/G20,0) -> 0 | H20: =SUM(J20:U20) -> 0 | J20: =J16*$C20*$D20*$G20 -> 0 | K20: =K16*$C$20*$D$20*$G$20 -> 0 | L20: =L16*$C$20*$D$20*$G$20 -> 0 | M20: =M16*$C$20*$D$20*$G$20 -> 0 | N20: =N16*$C$20*$D$20*$G$20 -> 0 | O20: =O16*$C$20*$D$20*$G$20 -> 0 | P20: =P16*$C$20*$D$20*$G$20 -> 0 | Q20: =Q16*$C$20*$D$20*$G$20 -> 0 | R20: =R16*$C$20*$D$20*$G$20 -> 0 | ... U20: =U16*$C$20*$D$20*$G$20 -> 0 | W20: =$W$17*C20 -> #DIV/0! | X20: =B20 -> P35
B21: S30 | C21: 0.07 | D21: 1 | E21: Tonnes | F21: =IFERROR(H21/G21,0) -> 0 | H21: =SUM(J21:U21) -> 0 | J21: =J16*$C$21*$D$21*$G$21 -> 0 | K21: =K16*$C$21*$D$21*$G$21 -> 0 | L21: =L16*$C$21*$D$21*$G$21 -> 0 | M21: =M16*$C$21*$D$21*$G$21 -> 0 | N21: =N16*$C$21*$D$21*$G$21 -> 0 | O21: =O16*$C$21*$D$21*$G$21 -> 0 | P21: =P16*$C$21*$D$21*$G$21 -> 0 | Q21: =Q16*$C$21*$D$21*$G$21 -> 0 | ... U21: =U16*$C$21*$D$21*$G$21 -> 0 | W21: =$W$17*C21 -> #DIV/0! | X21: =B21 -> S30
B22: S20 | C22: 0 | D22: 1 | E22: Tonnes | F22: =IFERROR(H22/G22,0) -> 0 | H22: =SUM(J22:U22) -> 0 | J22: =J16*$C$22*$D$22*$G$22 -> 0 | K22: =K16*$C$22*$D$22*$G$22 -> 0 | L22: =L16*$C$22*$D$22*$G$22 -> 0 | M22: =M16*$C$22*$D$22*$G$22 -> 0 | N22: =N16*$C$22*$D$22*$G$22 -> 0 | O22: =O16*$C$22*$D$22*$G$22 -> 0 | P22: =P16*$C$22*$D$22*$G$22 -> 0 | Q22: =Q16*$C$22*$D$22*$G$22 -> 0 | ... U22: =U16*$C$22*$D$22*$G$22 -> 0 | W22: =$W$17*C22 -> #DIV/0! | X22: =B22 -> S20
B23: Domestic Pulp | C23: 0.05 | D23: 1 | E23: Tonnes | F23: =IFERROR(H23/G23,0) -> 0 | H23: =SUM(J23:U23) -> 0 | J23: =J16*$C$23*$D$23*$G$23 -> 0 | K23: =K16*$C$23*$D$23*$G$23 -> 0 | L23: =L16*$C$23*$D$23*$G$23 -> 0 | M23: =M16*$C$23*$D$23*$G$23 -> 0 | N23: =N16*$C$23*$D$23*$G$23 -> 0 | O23: =O16*$C$23*$D$23*$G$23 -> 0 | P23: =P16*$C$23*$D$23*$G$23 -> 0 | Q23: =Q16*$C$23*$D$23*$G$23 -> 0 | ... U23: =U16*$C$23*$D$23*$G$23 -> 0 | W23: =$W$17*C23 -> #DIV/0! | X23: =B23 -> Domestic Pulp
B24: Eucalyptus | C24: 0 | D24: 1 | E24: Tonnes | F24: =IFERROR(H24/G24,0) -> 0 | H24: =SUM(J24:U24) -> 0 | J24: =J16*$C$24*$D$24*$G$24 -> 0 | K24: =K16*$C$24*$D$24*$G$24 -> 0 | L24: =L16*$C$24*$D$24*$G$24 -> 0 | M24: =M16*$C$24*$D$24*$G$24 -> 0 | N24: =N16*$C$24*$D$24*$G$24 -> 0 | O24: =O16*$C$24*$D$24*$G$24 -> 0 | P24: =P16*$C$24*$D$24*$G$24 -> 0 | Q24: =Q16*$C$24*$D$24*$G$24 -> 0 | ... U24: =U16*$C$24*$D$24*$G$24 -> 0 | W24: =$W$17*C24 -> #DIV/0! | X24: =B24 -> Eucalyptus
B25: FW | C25: 0 | D25: 1 | E25: Tonnes | F25: =IFERROR(H25/G25,0) -> 0 | H25: =SUM(J25:U25) -> 0 | J25: =J16*$C$25*$D$25*$G$25 -> 0 | K25: =K16*$C$25*$D$25*$G$25 -> 0 | L25: =L16*$C$25*$D$25*$G$25 -> 0 | M25: =M16*$C$25*$D$25*$G$25 -> 0 | N25: =N16*$C$25*$D$25*$G$25 -> 0 | O25: =O16*$C$25*$D$25*$G$25 -> 0 | P25: =P16*$C$25*$D$25*$G$25 -> 0 | Q25: =Q16*$C$25*$D$25*$G$25 -> 0 | ... U25: =U16*$C$25*$D$25*$G$25 -> 0 | W25: =$W$17*C25 -> #DIV/0! | X25: =B25 -> FW
B26: Euc Pulp | C26: 0 | D26: 1 | E26: Tonnes | F26: =IFERROR(H26/G26,0) -> 0 | H26: =SUM(J26:U26) -> 0 | J26: =J16*$C$26*$D$26*$G$26 -> 0 | K26: =K16*$C$26*$D$26*$G$26 -> 0 | L26: =L16*$C$26*$D$26*$G$26 -> 0 | M26: =M16*$C$26*$D$26*$G$26 -> 0 | N26: =N16*$C$26*$D$26*$G$26 -> 0 | O26: =O16*$C$26*$D$26*$G$26 -> 0 | P26: =P16*$C$26*$D$26*$G$26 -> 0 | Q26: =Q16*$C$26*$D$26*$G$26 -> 0 | ... U26: =U16*$C$26*$D$26*$G$26 -> 0 | W26: =$W$17*C26 -> #DIV/0! | X26: =B26 -> Euc Pulp
B27: Binwood | C27: 0 | D27: 1 | E27: Tonnes | F27: =IFERROR(H27/G27,0) -> 0 | H27: =SUM(J27:U27) -> 0 | J27: =J16*$C$27*$D$27*$G$27 -> 0 | K27: =K16*$C$27*$D$27*$G$27 -> 0 | L27: =L16*$C$27*$D$27*$G$27 -> 0 | M27: =M16*$C$27*$D$27*$G$27 -> 0 | N27: =N16*$C$27*$D$27*$G$27 -> 0 | O27: =O16*$C$27*$D$27*$G$27 -> 0 | P27: =P16*$C$27*$D$27*$G$27 -> 0 | Q27: =Q16*$C$27*$D$27*$G$27 -> 0 | ... U27: =U16*$C$27*$D$27*$G$27 -> 0 | W27: =$W$17*C27 -> #DIV/0! | X27: =B27 -> Binwood
B28: Spare Grade | C28: 0 | E28: Tonnes | F28: =IFERROR(H28/G28/D28,0) -> 0 | H28: =SUM(J28:U28) -> 0 | J28: =J16*$C$28*$D$28*$G$28 -> 0 | K28: =K16*$C$28*$D$28*$G$28 -> 0 | L28: =L16*$C$28*$D$28*$G$28 -> 0 | M28: =M16*$C$28*$D$28*$G$28 -> 0 | N28: =N16*$C$28*$D$28*$G$28 -> 0 | O28: =O16*$C$28*$D$28*$G$28 -> 0 | P28: =P16*$C$28*$D$28*$G$28 -> 0 | Q28: =Q16*$C$28*$D$28*$G$28 -> 0 | ... U28: =U16*$C$28*$D$28*$G$28 -> 0 | W28: =$W$17*C28 -> #DIV/0! | X28: =B28 -> Spare Grade
B29: P40 | C29: 0 | D29: 1 | E29: JAS | F29: =IFERROR(H29/G29/D29,0) -> 0 | H29: =SUM(J29:U29) -> 0 | J29: =J16*$C$29*$D$29*$G$29 -> 0 | K29: =K16*$C$29*$D$29*$G$29 -> 0 | L29: =L16*$C$29*$D$29*$G$29 -> 0 | M29: =M16*$C$29*$D$29*$G$29 -> 0 | N29: =N16*$C$29*$D$29*$G$29 -> 0 | O29: =O16*$C$29*$D$29*$G$29 -> 0 | P29: =P16*$C$29*$D$29*$G$29 -> 0 | Q29: =Q16*$C$29*$D$29*$G$29 -> 0 | ... U29: =U16*$C$29*$D$29*$G$29 -> 0 | W29: =$W$17*C29 -> #DIV/0! | X29: =B29 -> P40
B30: P30 | C30: 0.0019336678 | D30: 1.0288961 | E30: JAS | F30: =IFERROR(H30/G30/D30,0) -> 0 | H30: =SUM(J30:U30) -> 0 | J30: =J16*$C$30*$D$30*$G$30 -> 0 | K30: =K16*$C$30*$D$30*$G$30 -> 0 | L30: =L16*$C$30*$D$30*$G$30 -> 0 | M30: =M16*$C$30*$D$30*$G$30 -> 0 | N30: =N16*$C$30*$D$30*$G$30 -> 0 | O30: =O16*$C$30*$D$30*$G$30 -> 0 | P30: =P16*$C$30*$D$30*$G$30 -> 0 | Q30: =Q16*$C$30*$D$30*$G$30 -> 0 | ... U30: =U16*$C$30*$D$30*$G$30 -> 0 | W30: =$W$17*C30 -> #DIV/0! | X30: =B30 -> P30
B31: AO | C31: 0.15 | D31: 1.04 | E31: JAS | F31: =IFERROR(H31/G31/D31,0) -> 0 | H31: =SUM(J31:U31) -> 0 | J31: =J16*$C$31*$D$31*$G$31 -> 0 | K31: =K16*$C$31*$D$31*$G$31 -> 0 | L31: =L16*$C$31*$D$31*$G$31 -> 0 | M31: =M16*$C$31*$D$31*$G$31 -> 0 | N31: =N16*$C$31*$D$31*$G$31 -> 0 | O31: =O16*$C$31*$D$31*$G$31 -> 0 | P31: =P16*$C$31*$D$31*$G$31 -> 0 | Q31: =Q16*$C$31*$D$31*$G$31 -> 0 | ... U31: =U16*$C$31*$D$31*$G$31 -> 0 | W31: =$W$17*C31 -> #DIV/0! | X31: =B31 -> AO
B32: A | C32: 0.28 | D32: 1.01 | E32: JAS | F32: =IFERROR(H32/G32/D32,0) -> 0 | H32: =SUM(J32:U32) -> 0 | J32: =J16*$C$32*$D$32*$G$32 -> 0 | K32: =K16*$C$32*$D$32*$G$32 -> 0 | L32: =L16*$C$32*$D$32*$G$32 -> 0 | M32: =M16*$C$32*$D$32*$G$32 -> 0 | N32: =N16*$C$32*$D$32*$G$32 -> 0 | O32: =O16*$C$32*$D$32*$G$32 -> 0 | P32: =P16*$C$32*$D$32*$G$32 -> 0 | Q32: =Q16*$C$32*$D$32*$G$32 -> 0 | ... U32: =U16*$C$32*$D$32*$G$32 -> 0 | W32: =$W$17*C32 -> #DIV/0! | X32: =B32 -> A
B33: K | C33: 0.20870336 | D33: 0.96 | E33: JAS | F33: =IFERROR(H33/G33/D33,0) -> 0 | H33: =SUM(J33:U33) -> 0 | J33: =J16*$C$33*$D$33*$G$33 -> 0 | K33: =K16*$C$33*$D$33*$G$33 -> 0 | L33: =L16*$C$33*$D$33*$G$33 -> 0 | M33: =M16*$C$33*$D$33*$G$33 -> 0 | N33: =N16*$C$33*$D$33*$G$33 -> 0 | O33: =O16*$C$33*$D$33*$G$33 -> 0 | P33: =P16*$C$33*$D$33*$G$33 -> 0 | Q33: =Q16*$C$33*$D$33*$G$33 -> 0 | ... U33: =U16*$C$33*$D$33*$G$33 -> 0 | W33: =$W$17*C33 -> #DIV/0! | X33: =B33 -> K
B34: KI | C34: 0.025784396 | D34: 0.97 | E34: JAS | F34: =IFERROR(H34/G34/D34,0) -> 0 | H34: =SUM(J34:U34) -> 0 | J34: =J16*$C$34*$D$34*$G$34 -> 0 | K34: =K16*$C$34*$D$34*$G$34 -> 0 | L34: =L16*$C$34*$D$34*$G$34 -> 0 | M34: =M16*$C$34*$D$34*$G$34 -> 0 | N34: =N16*$C$34*$D$34*$G$34 -> 0 | O34: =O16*$C$34*$D$34*$G$34 -> 0 | P34: =P16*$C$34*$D$34*$G$34 -> 0 | Q34: =Q16*$C$34*$D$34*$G$34 -> 0 | ... U34: =U16*$C$34*$D$34*$G$34 -> 0 | W34: =$W$17*C34 -> #DIV/0! | X34: =B34 -> KI
B35: KIS | C35: 0.1017521 | D35: 0.92 | E35: JAS | F35: =IFERROR(H35/G35/D35,0) -> 0 | H35: =SUM(J35:U35) -> 0 | J35: =J16*$C$35*$D$35*$G$35 -> 0 | K35: =K16*$C$35*$D$35*$G$35 -> 0 | L35: =L16*$C$35*$D$35*$G$35 -> 0 | M35: =M16*$C$35*$D$35*$G$35 -> 0 | N35: =N16*$C$35*$D$35*$G$35 -> 0 | O35: =O16*$C$35*$D$35*$G$35 -> 0 | P35: =P16*$C$35*$D$35*$G$35 -> 0 | Q35: =Q16*$C$35*$D$35*$G$35 -> 0 | ... U35: =U16*$C$35*$D$35*$G$35 -> 0 | W35: =$W$17*C35 -> #DIV/0! | X35: =B35 -> KIS
B36: KI stub | E36: JAS | F36: =IFERROR(H36/G36/D36,0) -> 0 | H36: =SUM(J36:U36) -> 0 | J36: =J16*$C$36*$D$36*$G$36 -> 0 | K36: =K16*$C$36*$D$36*$G$36 -> 0 | L36: =L16*$C$36*$D$36*$G$36 -> 0 | M36: =M16*$C$36*$D$36*$G$36 -> 0 | N36: =N16*$C$36*$D$36*$G$36 -> 0 | O36: =O16*$C$36*$D$36*$G$36 -> 0 | P36: =P16*$C$36*$D$36*$G$36 -> 0 | Q36: =Q16*$C$36*$D$36*$G$36 -> 0 | ... U36: =U16*$C$36*$D$36*$G$36 -> 0 | W36: =$W$17*C36 -> #DIV/0! | X36: =B36 -> KI stub
B37: CF+ | E37: JAS | F37: =IFERROR(H37/G37/D37,0) -> 0 | H37: =SUM(J37:U37) -> 0 | J37: =J16*$C$37*$D$37*$G$37 -> 0 | K37: =K16*$C$37*$D$37*$G$37 -> 0 | L37: =L16*$C$37*$D$37*$G$37 -> 0 | M37: =M16*$C$37*$D$37*$G$37 -> 0 | N37: =N16*$C$37*$D$37*$G$37 -> 0 | O37: =O16*$C$37*$D$37*$G$37 -> 0 | P37: =P16*$C$37*$D$37*$G$37 -> 0 | Q37: =Q16*$C$37*$D$37*$G$37 -> 0 | ... U37: =U16*$C$37*$D$37*$G$37 -> 0 | W37: =$W$17*C37 -> #DIV/0! | X37: =B37 -> CF+
B38: CF- | E38: JAS | F38: =IFERROR(H38/G38/D38,0) -> 0 | H38: =SUM(J38:U38) -> 0 | J38: =J16*$C$38*$D$38*$G$38 -> 0 | K38: =K16*$C$38*$D$38*$G$38 -> 0 | L38: =L16*$C$38*$D$38*$G$38 -> 0 | M38: =M16*$C$38*$D$38*$G$38 -> 0 | N38: =N16*$C$38*$D$38*$G$38 -> 0 | O38: =O16*$C$38*$D$38*$G$38 -> 0 | P38: =P16*$C$38*$D$38*$G$38 -> 0 | Q38: =Q16*$C$38*$D$38*$G$38 -> 0 | ... U38: =U16*$C$38*$D$38*$G$38 -> 0 | W38: =$W$17*C38 -> #DIV/0! | X38: =B38 -> CF-
B39: CM | E39: JAS | F39: =IFERROR(H39/G39/D39,0) -> 0 | H39: =SUM(J39:U39) -> 0 | J39: =J16*$C$39*$D$39*$G$39 -> 0 | K39: =K16*$C$39*$D$39*$G$39 -> 0 | L39: =L16*$C$39*$D$39*$G$39 -> 0 | M39: =M16*$C$39*$D$39*$G$39 -> 0 | N39: =N16*$C$39*$D$39*$G$39 -> 0 | O39: =O16*$C$39*$D$39*$G$39 -> 0 | P39: =P16*$C$39*$D$39*$G$39 -> 0 | Q39: =Q16*$C$39*$D$39*$G$39 -> 0 | ... U39: =U16*$C$39*$D$39*$G$39 -> 0 | W39: =$W$17*C39 -> #DIV/0! | X39: =B39 -> CM
B40: Euc A | E40: JAS | F40: =IFERROR(H40/G40/D40,0) -> 0 | H40: =SUM(J40:U40) -> 0 | J40: =J16*$C$40*$D$40*$G$40 -> 0 | K40: =K16*$C$40*$D$40*$G$40 -> 0 | L40: =L16*$C$40*$D$40*$G$40 -> 0 | M40: =M16*$C$40*$D$40*$G$40 -> 0 | N40: =N16*$C$40*$D$40*$G$40 -> 0 | O40: =O16*$C$40*$D$40*$G$40 -> 0 | P40: =P16*$C$40*$D$40*$G$40 -> 0 | Q40: =Q16*$C$40*$D$40*$G$40 -> 0 | ... U40: =U16*$C$40*$D$40*$G$40 -> 0 | W40: =$W$17*C40 -> #DIV/0! | X40: =B40 -> Euc A
B41: Euc K | H41: =SUM(J41:U41) -> 0 | J41: =J16*$C$41*$D$41*$G$41 -> 0 | K41: =K16*$C$41*$D$41*$G$41 -> 0 | L41: =L16*$C$41*$D$41*$G$41 -> 0 | M41: =M16*$C$41*$D$41*$G$41 -> 0 | N41: =N16*$C$41*$D$41*$G$41 -> 0 | O41: =O16*$C$41*$D$41*$G$41 -> 0 | P41: =P16*$C$41*$D$41*$G$41 -> 0 | Q41: =Q16*$C$41*$D$41*$G$41 -> 0 | ... U41: =U16*$C$41*$D$41*$G$41 -> 0 | W41: =$W$17*C41 -> #DIV/0! | X41: =B41 -> Euc K
C42: =SUM(C20:C41) -> 1.0022978
B43: Export Sales | C43: =SUMIF(E20:E41,"JAS",C20:C41) -> 0.76817352 | H43: =SUM(J43:U43) -> 0 | J43: =SUM(J28:J41) -> 0 | K43: =SUM(K28:K41) -> 0 | L43: =SUM(L28:L41) -> 0 | M43: =SUM(M28:M41) -> 0 | N43: =SUM(N28:N41) -> 0 | O43: =SUM(O28:O41) -> 0 | P43: =SUM(P28:P41) -> 0 | Q43: =SUM(Q28:Q41) -> 0 | ... U43: =SUM(U28:U41) -> 0 | W43: =SUM(W20:W42) -> #DIV/0!
B44: Domestic Sales | C44: =SUMIF(E20:E41,"Tonnes",C20:C41) -> 0.23412433 | H44: =SUM(J44:U44) -> 0 | J44: =SUM(J20:J27) -> 0 | K44: =SUM(K20:K27) -> 0 | L44: =SUM(L20:L27) -> 0 | M44: =SUM(M20:M27) -> 0 | N44: =SUM(N20:N27) -> 0 | O44: =SUM(O20:O27) -> 0 | P44: =SUM(P20:P27) -> 0 | Q44: =SUM(Q20:Q27) -> 0 | ... U44: =SUM(U20:U27) -> 0
B46: TOTAL | G46: =H46/W16 -> #DIV/0! | H46: =SUM(H20:H41) -> 0 | J46: =SUM(J20:J41) -> 0 | K46: =SUM(K20:K41) -> 0 | L46: =SUM(L20:L41) -> 0 | M46: =SUM(M20:M41) -> 0 | N46: =SUM(N20:N41) -> 0 | O46: =SUM(O20:O41) -> 0 | P46: =SUM(P20:P41) -> 0 | Q46: =SUM(Q20:Q41) -> 0 | ... U46: =SUM(U20:U41) -> 0 | W46: =SUM(J46:U46) -> 0
B48: COSTS | C48: Op Code | D48: Activity
B49: Log and Load | C49: 300/01 | D49: Logging
H50: TOTAL | J50: 45658 | K50: 45689 | L50: 45717 | M50: 45748 | N50: 45778 | O50: 45809 | P50: 45839 | Q50: 45870 | R50: 45901 | S50: 45931 | T50: 45962 | U50: 45992
G51: =H51/W16 -> #DIV/0! | H51: =SUM(J51:U51) -> 0 | J51: =J16*J13 -> 0 | K51: =K16*K13 -> 0 | L51: =L16*L13 -> 0 | M51: =M16*M13 -> 0 | N51: =N16*N13 -> 0 | O51: =O16*O13 -> 0 | P51: =P16*P13 -> 0 | Q51: =Q16*Q13 -> 0 | ... U51: =U16*U13 -> 0 | W51: =SUM(J51:U51) -> 0
B54: Log Transport
B55: Grade | C55: Op Code | D55: Activity | E55: Destination | F55: Destination | G55: Cost/t | H55: TOTAL | J55: 45658 | K55: 45689 | L55: 45717 | M55: 45748 | N55: 45778 | O55: 45809 | P55: 45839 | Q55: 45870 | R55: 45901 | S55: 45931 | T55: 45962 | U55: 45992
B56: P35 | C56: 300/02 | D56: Transport | E56: Domestic | H56: =SUM(J56:U56) -> 0 | J56: =IF($C20>0,(J$16*$C20)*$G56,0) -> 0 | K56: =IF($C20>0,(K$16*$C20)*$G56,0) -> 0 | L56: =IF($C20>0,(L$16*$C20)*$G56,0) -> 0 | M56: =IF($C20>0,(M$16*$C20)*$G56,0) -> 0 | N56: =IF($C20>0,(N$16*$C20)*$G56,0) -> 0 | O56: =IF($C20>0,(O$16*$C20)*$G56,0) -> 0 | P56: =IF($C20>0,(P$16*$C20)*$G56,0) -> 0 | Q56: =IF($C20>0,(Q$16*$C20)*$G56,0) -> 0 | ... U56: =IF($C20>0,(U$16*$C20)*$G56,0) -> 0
B57: S30 | C57: 300/02 | D57: Transport | E57: Domestic | H57: =SUM(J57:U57) -> 0 | J57: =IF($C21>0,(J$16*$C21)*$G57,0) -> 0 | K57: =IF($C21>0,(K$16*$C21)*$G57,0) -> 0 | L57: =IF($C21>0,(L$16*$C21)*$G57,0) -> 0 | M57: =IF($C21>0,(M$16*$C21)*$G57,0) -> 0 | N57: =IF($C21>0,(N$16*$C21)*$G57,0) -> 0 | O57: =IF($C21>0,(O$16*$C21)*$G57,0) -> 0 | P57: =IF($C21>0,(P$16*$C21)*$G57,0) -> 0 | Q57: =IF($C21>0,(Q$16*$C21)*$G57,0) -> 0 | ... U57: =IF($C21>0,(U$16*$C21)*$G57,0) -> 0
B58: S20 | C58: 300/02 | D58: Transport | E58: Domestic | H58: =SUM(J58:U58) -> 0 | J58: =IF($C22>0,(J$16*$C22)*$G58,0) -> 0 | K58: =IF($C22>0,(K$16*$C22)*$G58,0) -> 0 | L58: =IF($C22>0,(L$16*$C22)*$G58,0) -> 0 | M58: =IF($C22>0,(M$16*$C22)*$G58,0) -> 0 | N58: =IF($C22>0,(N$16*$C22)*$G58,0) -> 0 | O58: =IF($C22>0,(O$16*$C22)*$G58,0) -> 0 | P58: =IF($C22>0,(P$16*$C22)*$G58,0) -> 0 | Q58: =IF($C22>0,(Q$16*$C22)*$G58,0) -> 0 | ... U58: =IF($C22>0,(U$16*$C22)*$G58,0) -> 0
B59: Domestic Pulp | C59: 300/02 | D59: Transport | E59: Domestic | H59: =SUM(J59:U59) -> 0 | J59: =IF($C23>0,(J$16*$C23)*$G59,0) -> 0 | K59: =IF($C23>0,(K$16*$C23)*$G59,0) -> 0 | L59: =IF($C23>0,(L$16*$C23)*$G59,0) -> 0 | M59: =IF($C23>0,(M$16*$C23)*$G59,0) -> 0 | N59: =IF($C23>0,(N$16*$C23)*$G59,0) -> 0 | O59: =IF($C23>0,(O$16*$C23)*$G59,0) -> 0 | P59: =IF($C23>0,(P$16*$C23)*$G59,0) -> 0 | Q59: =IF($C23>0,(Q$16*$C23)*$G59,0) -> 0 | ... U59: =IF($C23>0,(U$16*$C23)*$G59,0) -> 0
B60: Eucalyptus | C60: 300/02 | D60: Transport | E60: Domestic | H60: =SUM(J60:U60) -> 0 | J60: =IF($C24>0,(J$16*$C24)*$G60,0) -> 0 | K60: =IF($C24>0,(K$16*$C24)*$G60,0) -> 0 | L60: =IF($C24>0,(L$16*$C24)*$G60,0) -> 0 | M60: =IF($C24>0,(M$16*$C24)*$G60,0) -> 0 | N60: =IF($C24>0,(N$16*$C24)*$G60,0) -> 0 | O60: =IF($C24>0,(O$16*$C24)*$G60,0) -> 0 | P60: =IF($C24>0,(P$16*$C24)*$G60,0) -> 0 | Q60: =IF($C24>0,(Q$16*$C24)*$G60,0) -> 0 | ... U60: =IF($C24>0,(U$16*$C24)*$G60,0) -> 0
B61: FW | C61: 300/02 | D61: Transport | E61: Domestic | H61: =SUM(J61:U61) -> 0 | J61: =IF($C25>0,(J$16*$C25)*$G61,0) -> 0 | K61: =IF($C25>0,(K$16*$C25)*$G61,0) -> 0 | L61: =IF($C25>0,(L$16*$C25)*$G61,0) -> 0 | M61: =IF($C25>0,(M$16*$C25)*$G61,0) -> 0 | N61: =IF($C25>0,(N$16*$C25)*$G61,0) -> 0 | O61: =IF($C25>0,(O$16*$C25)*$G61,0) -> 0 | P61: =IF($C25>0,(P$16*$C25)*$G61,0) -> 0 | Q61: =IF($C25>0,(Q$16*$C25)*$G61,0) -> 0 | ... U61: =IF($C25>0,(U$16*$C25)*$G61,0) -> 0
B62: Euc Pulp | C62: 300/02 | D62: Transport | E62: Domestic | H62: =SUM(J62:U62) -> 0 | J62: =IF($C26>0,(J$16*$C26)*$G62,0) -> 0 | K62: =IF($C26>0,(K$16*$C26)*$G62,0) -> 0 | L62: =IF($C26>0,(L$16*$C26)*$G62,0) -> 0 | M62: =IF($C26>0,(M$16*$C26)*$G62,0) -> 0 | N62: =IF($C26>0,(N$16*$C26)*$G62,0) -> 0 | O62: =IF($C26>0,(O$16*$C26)*$G62,0) -> 0 | P62: =IF($C26>0,(P$16*$C26)*$G62,0) -> 0 | Q62: =IF($C26>0,(Q$16*$C26)*$G62,0) -> 0 | ... U62: =IF($C26>0,(U$16*$C26)*$G62,0) -> 0
B63: Binwood | C63: 300/02 | D63: Transport | E63: Domestic | H63: =SUM(J63:U63) -> 0 | J63: =IF($C27>0,(J$16*$C27)*$G63,0) -> 0 | K63: =IF($C27>0,(K$16*$C27)*$G63,0) -> 0 | L63: =IF($C27>0,(L$16*$C27)*$G63,0) -> 0 | M63: =IF($C27>0,(M$16*$C27)*$G63,0) -> 0 | N63: =IF($C27>0,(N$16*$C27)*$G63,0) -> 0 | O63: =IF($C27>0,(O$16*$C27)*$G63,0) -> 0 | P63: =IF($C27>0,(P$16*$C27)*$G63,0) -> 0 | Q63: =IF($C27>0,(Q$16*$C27)*$G63,0) -> 0 | ... U63: =IF($C27>0,(U$16*$C27)*$G63,0) -> 0
B64: P40 | C64: 300/02 | D64: Transport | E64: AWG | H64: =SUM(J64:U64) -> 0 | J64: =IF($C28>0,(J$16*$C28)*$G64,0) -> 0 | K64: =IF($C28>0,(K$16*$C28)*$G64,0) -> 0 | L64: =IF($C28>0,(L$16*$C28)*$G64,0) -> 0 | M64: =IF($C28>0,(M$16*$C28)*$G64,0) -> 0 | N64: =IF($C28>0,(N$16*$C28)*$G64,0) -> 0 | O64: =IF($C28>0,(O$16*$C28)*$G64,0) -> 0 | P64: =IF($C28>0,(P$16*$C28)*$G64,0) -> 0 | Q64: =IF($C28>0,(Q$16*$C28)*$G64,0) -> 0 | ... U64: =IF($C28>0,(U$16*$C28)*$G64,0) -> 0
B65: P30 | C65: 300/02 | D65: Transport | E65: AWG | H65: =SUM(J65:U65) -> 0 | J65: =IF($C29>0,(J$16*$C29)*$G65,0) -> 0 | K65: =IF($C29>0,(K$16*$C29)*$G65,0) -> 0 | L65: =IF($C29>0,(L$16*$C29)*$G65,0) -> 0 | M65: =IF($C29>0,(M$16*$C29)*$G65,0) -> 0 | N65: =IF($C29>0,(N$16*$C29)*$G65,0) -> 0 | O65: =IF($C29>0,(O$16*$C29)*$G65,0) -> 0 | P65: =IF($C29>0,(P$16*$C29)*$G65,0) -> 0 | Q65: =IF($C29>0,(Q$16*$C29)*$G65,0) -> 0 | ... U65: =IF($C29>0,(U$16*$C29)*$G65,0) -> 0
B66: AO | C66: 300/02 | D66: Transport | E66: AWG | H66: =SUM(J66:U66) -> 0 | J66: =IF($C30>0,(J$16*$C30)*$G66,0) -> 0 | K66: =IF($C30>0,(K$16*$C30)*$G66,0) -> 0 | L66: =IF($C30>0,(L$16*$C30)*$G66,0) -> 0 | M66: =IF($C30>0,(M$16*$C30)*$G66,0) -> 0 | N66: =IF($C30>0,(N$16*$C30)*$G66,0) -> 0 | O66: =IF($C30>0,(O$16*$C30)*$G66,0) -> 0 | P66: =IF($C30>0,(P$16*$C30)*$G66,0) -> 0 | Q66: =IF($C30>0,(Q$16*$C30)*$G66,0) -> 0 | ... U66: =IF($C30>0,(U$16*$C30)*$G66,0) -> 0
B67: A | C67: 300/02 | D67: Transport | E67: AWG | H67: =SUM(J67:U67) -> 0 | J67: =IF($C31>0,(J$16*$C31)*$G67,0) -> 0 | K67: =IF($C31>0,(K$16*$C31)*$G67,0) -> 0 | L67: =IF($C31>0,(L$16*$C31)*$G67,0) -> 0 | M67: =IF($C31>0,(M$16*$C31)*$G67,0) -> 0 | N67: =IF($C31>0,(N$16*$C31)*$G67,0) -> 0 | O67: =IF($C31>0,(O$16*$C31)*$G67,0) -> 0 | P67: =IF($C31>0,(P$16*$C31)*$G67,0) -> 0 | Q67: =IF($C31>0,(Q$16*$C31)*$G67,0) -> 0 | ... U67: =IF($C31>0,(U$16*$C31)*$G67,0) -> 0
... B77: Spare grade | C77: 300/02 | D77: Transport | E77: AWG | H77: =SUM(J77:U77) -> 0 | J77: =IF($C41>0,(J$16*$C41)*$G77,0) -> 0 | K77: =IF($C41>0,(K$16*$C41)*$G77,0) -> 0 | L77: =IF($C41>0,(L$16*$C41)*$G77,0) -> 0 | M77: =IF($C41>0,(M$16*$C41)*$G77,0) -> 0 | N77: =IF($C41>0,(N$16*$C41)*$G77,0) -> 0 | O77: =IF($C41>0,(O$16*$C41)*$G77,0) -> 0 | P77: =IF($C41>0,(P$16*$C41)*$G77,0) -> 0 | Q77: =IF($C41>0,(Q$16*$C41)*$G77,0) -> 0 | ... U77: =IF($C41>0,(U$16*$C41)*$G77,0) -> 0
G78: =H78/W16 -> #DIV/0! | H78: =SUM(H56:H77) -> 0 | J78: =SUM(J56:J77) -> 0 | K78: =SUM(K56:K77) -> 0 | L78: =SUM(L56:L77) -> 0 | M78: =SUM(M56:M77) -> 0 | N78: =SUM(N56:N77) -> 0 | O78: =SUM(O56:O77) -> 0 | P78: =SUM(P56:P77) -> 0 | Q78: =SUM(Q56:Q77) -> 0 | ... U78: =SUM(U56:U77) -> 0 | W78: =SUM(J78:U78) -> 0
B80: Non-docket costs
B81: Operation | C81: Op Code | D81: Activity | E81: Resource | F81: Product | G81: Unit Rate | H81: TOTAL | J81: 45658 | K81: 45689 | L81: 45717 | M81: 45748 | N81: 45778 | O81: 45809 | P81: 45839 | Q81: 45870 | R81: 45901 | S81: 45931 | T81: 45962 | U81: 45992
B82: Tracking | C82: 300/04 | D82: Logging | H82: =SUM(J82:U82) -> 0
B83: Logging Machinery establishment/transportation | C83: 300/06 | D83: Logging | E83: 699 | F83: 3675 | H83: =SUM(J83:U83) -> 0
B84: Road control | C84: 300/16 | D84: Logging | E84: 699 | F84: 3691 | H84: =SUM(J84:U84) -> 0
B85: Powerline costs | C85: 300/17 | D85: Logging | E85: 699 | F85: 3677 | H85: =SUM(J85:U85) -> 0
B86: Fencing & gate construction | C86: 721 | D86: Logging | E86: 699 | F86: 3671 | H86: =SUM(J86:U86) -> 0
B87: Deadman | C87: 300/18 | D87: Logging | E87: 699 | F87: 3669 | H87: =SUM(J87:U87) -> 0
B88: Two-stage | C88: 300/19 | D88: Logging | E88: 699 | F88: 3665 | H88: =SUM(J88:U88) -> 0
B89: Harvest Planning | C89: 300/09 | D89: Logging | E89: 699 | F89: 3963 | H89: =SUM(J89:U89) -> 0
B90: Roading machinery establishment/transportation | C90: 300/07 | D90: Infrastructure | H90: =SUM(J90:U90) -> 0
B91: New Road Metalled or sealed | C91: 720 | D91: Infrastructure | H91: =SUM(J91:U91) -> 0 | J91: =J115 -> 0 | K91: =K115 -> 0 | L91: =L115 -> 0 | M91: =M115 -> 0 | N91: =N115 -> 0 | O91: =O115 -> 0 | P91: =P115 -> 0 | Q91: =Q115 -> 0 | ... U91: =U115 -> 0
B92: Upgrade Road metalled or sealed | C92: 720 | D92: Infrastructure | H92: =SUM(J92:U92) -> 0 | J92: =J114 -> 0 | K92: =K114 -> 0 | L92: =L114 -> 0 | M92: =M114 -> 0 | N92: =N114 -> 0 | O92: =O114 -> 0 | P92: =P114 -> 0 | Q92: =Q114 -> 0 | ... U92: =U114 -> 0
B93: Other infrastructure | C93: 720 | D93: Infrastructure | H93: =SUM(J93:U93) -> 0
B94: Skid construction | C94: 300/05 | D94: Infrastructure | H94: =SUM(J94:U94) -> 0 | J94: =J119 -> 0 | K94: =K119 -> 0 | L94: =L119 -> 0 | M94: =M119 -> 0 | N94: =N119 -> 0 | O94: =O119 -> 0 | P94: =P119 -> 0 | Q94: =Q119 -> 0 | ... U94: =U119 -> 0
B95: Pad construction | C95: 300/05 | D95: Infrastructure | H95: =SUM(J95:U95) -> 0 | J95: =J120 -> 0 | K95: =K120 -> 0 | L95: =L120 -> 0 | M95: =M120 -> 0 | N95: =N120 -> 0 | O95: =O120 -> 0 | P95: =P120 -> 0 | Q95: =Q120 -> 0 | ... U95: =U120 -> 0
B96: Maintenance Forest Road | C96: 305 | D96: Maintenance | H96: =SUM(J96:U96) -> 0
B97: Maintenance Public Road | C97: 306 | D97: Maintenance | H97: =SUM(J97:U97) -> 0
B98: Skid/Pad maintenance | C98: 300/14 | D98: Post harvest costs | H98: =SUM(J98:U98) -> 0
B99: Post-harvest clean-up | C99: 300/10 | D99: Post harvest costs | H99: =SUM(J99:U99) -> 0
B100: Health and safety and Auditing | C100: 300/11 | D100: Indirect costs | H100: =SUM(J100:U100) -> 0
B101: Weighbridge | C101: 300/03 | D101: Indirect costs | G101: =IFERROR(H101/$W$16,0) -> 0 | H101: =SUM(J101:U101) -> 0
B102: Environmental monitoring/consents | C102: 330/04 | D102: Indirect costs | E102: 365 | H102: =SUM(J102:U102) -> 0
B103: Forest levy | C103: 300/08 | D103: Mgmt/Admin | E103: 338 | G103: 0.33 | H103: =SUM(J103:U103) -> 0 | J103: =$G$103*J16 -> 0 | K103: =$G$103*K16 -> 0 | L103: =$G$103*L16 -> 0 | M103: =$G$103*M16 -> 0 | N103: =$G$103*N16 -> 0 | O103: =$G$103*O16 -> 0 | P103: =$G$103*P16 -> 0 | Q103: =$G$103*Q16 -> 0 | ... U103: =$G$103*U16 -> 0
B104: Insurance Payment protection (domestic sales only) | C104: 351 | D104: Mgmt/Admin | E104: 324 | G104: 0.0016 | H104: =SUM(J104:U104) -> 0 | J104: =$G$104*J46/100 -> 0 | K104: =$G$104*K46/100 -> 0 | L104: =$G$104*L46/100 -> 0 | M104: =$G$104*M46/100 -> 0 | N104: =$G$104*N46/100 -> 0 | O104: =$G$104*O46/100 -> 0 | P104: =$G$104*P46/100 -> 0 | Q104: =$G$104*Q46/100 -> 0 | ... U104: =$G$104*U46/100 -> 0
B105: Harvest management fee | C105: 300/12 | D105: Mgmt/Admin | G105: 4.5 | H105: =SUM(J105:U105) -> 0 | J105: =$G$105*J16 -> 0 | K105: =$G$105*K16 -> 0 | L105: =$G$105*L16 -> 0 | M105: =$G$105*M16 -> 0 | N105: =$G$105*N16 -> 0 | O105: =$G$105*O16 -> 0 | P105: =$G$105*P16 -> 0 | Q105: =$G$105*Q16 -> 0 | ... U105: =$G$105*U16 -> 0
B107: Total non-docket costs | G107: =IFERROR(H107/B127,0) -> 0 | H107: =SUM(H82:H105) -> 0 | J107: =SUM(J82:J105) -> 0 | K107: =SUM(K82:K105) -> 0 | L107: =SUM(L82:L105) -> 0 | M107: =SUM(M82:M105) -> 0 | N107: =SUM(N82:N105) -> 0 | O107: =SUM(O82:O105) -> 0 | P107: =SUM(P82:P105) -> 0 | Q107: =SUM(Q82:Q105) -> 0 | ... U107: =SUM(U82:U105) -> 0
B109: Total Costs | H109: =H51+H78+H107 -> 0 | J109: =J51+J78+J107 -> 0 | K109: =K51+K78+K107 -> 0 | L109: =L51+L78+L107 -> 0 | M109: =M51+M78+M107 -> 0 | N109: =N51+N78+N107 -> 0 | O109: =O51+O78+O107 -> 0 | P109: =P51+P78+P107 -> 0 | Q109: =Q51+Q78+Q107 -> 0 | ... U109: =U51+U78+U107 -> 0 | W109: =SUM(J109:U109) -> 0
B111: Net Harvest Total | H111: =H46-H109 -> 0 | J111: =J46-J109 -> 0 | K111: =K46-K109 -> 0 | L111: =L46-L109 -> 0 | M111: =M46-M109 -> 0 | N111: =N46-N109 -> 0 | O111: =O46-O109 -> 0 | P111: =P46-P109 -> 0 | Q111: =Q46-Q109 -> 0 | ... U111: =U46-U109 -> 0 | W111: =SUM(J111:U111) -> 0
B113: Engineering | C113: Op Code | D113: Activity | E113: Unit | F113: Vol | G113: Unit Rate | J113: Metres constructed or number of skids/pads
B114: Existing road upgrade-Substantially metalled or sealed | C114: 720 | D114: Infrastructure | E114: cost/m | G114: =IFERROR(H114/F114,0) -> 0 | H114: =SUM(J114:U114) -> 0
B115: New road construction-Substantially metalled or sealed | C115: 720 | D115: Infrastructure | E115: cost/m | G115: =IFERROR(H115/F115,0) -> 0 | H115: =SUM(J115:U115) -> 0
B116: Existing road upgrade-Partially metalled or sealed | C116: 720 | D116: Infrastructure | E116: cost/m | G116: =IFERROR(H116/F116,0) -> 0 | H116: =SUM(J116:U116) -> 0
B117: New road construction-Partially metalled or sealed | C117: 720 | D117: Infrastructure | E117: cost/m | G117: =IFERROR(H117/F117,0) -> 0 | H117: =SUM(J117:U117) -> 0
B118: Other infrastructure | C118: 720 | D118: Infrastructure | E118: cost/unit | G118: =IFERROR(H118/F118,0) -> 0 | H118: =SUM(J118:U118) -> 0
...

Sheet Waipuna Actual
C1: ='Waipuna Budget'!C1 -> 2025 | D1: Input
B2: ='Waipuna Budget'!B2 -> Waipuna | H2: Estimated Tonnes (ha)
B3: PRODUCTION & RATE | G3: Total Monthly Working Days | I3: =IF(NOT(ISBLANK(J5)), J5, IF(NOT(ISBLANK(J8)), J8, IF(NOT(ISBLANK(J11)), J11, 0)))+IF(NOT(ISBLANK(K5)), K5, IF(NOT(ISBLANK(K8)), K8, IF(NOT(ISBLANK(K11)), K11, 0)))+IF(NOT(ISBLANK(L5)), L5, IF(NOT(ISBLANK(L8)), L8, IF(NOT(ISBLANK(L11)), L11, 0)))+IF(NOT(ISBLANK(M5)), M5, IF(NOT(ISBLANK(M8)), M8, IF(NOT(ISBLANK(M11)), M11, 0)))+IF(NOT(ISBLANK(N5)), N5, IF(NOT(ISBLANK(N8)), N8, IF(NOT(ISBLANK(N11)), N11, 0)))+IF(NOT(ISBLANK(O5)), O5, IF(NOT(ISBLANK(O8)), O8, IF(NOT(ISBLANK(O11)), O11, 0)))+IF(NOT(ISBLANK(P5)), P5, IF(NOT(ISBLANK(P8)), P8, IF(NOT(ISBLANK(P11)), P11, 0)))+IF(NOT(ISBLANK(Q5)), Q5, IF(NOT(ISBLANK(Q8)), Q8, IF(NOT(ISBLANK(Q11)), Q11, 0)))+IF(NOT(ISBLANK(R5)), R5, IF(NOT(ISBLANK(R8)), R8, IF(NOT(ISBLANK(R11)), R11, 0)))+IF(NOT(ISBLANK(S5)), S5, IF(NOT(ISBLANK(S8)), S8, IF(NOT(ISBLANK(S11)), S11, 0)))+IF(NOT(ISBLANK(T5)), T5, IF(NOT(ISBLANK(T8)), T8, IF(NOT(ISBLANK(T11)), T11, 0)))+IF(NOT(ISBLANK(U5)), U5, IF(NOT(ISBLANK(U8)), U8, IF(NOT(ISBLANK(U11)), U11, 0))) -> 0 | J3: 45658 | K3: 45689 | L3: 45717 | M3: 45748 | N3: 45778 | O3: 45809 | P3: 45839 | Q3: 45870 | R3: 45901 | S3: 45931 | T3: 45962 | U3: 45992
G4: Roadline | H4: Total production | I4: =IFERROR(SUM(J4:U4)/$W$16,0) -> 0
H5: Days worked
H6: Harvesting Rate
G7: Groundbase | H7: Total production | I7: =IFERROR(SUM(J7:U7)/$W$16,0) -> 0
H8: Days worked
H9: Harvesting Rate
G10: Hauler | H10: Total production | I10: =IFERROR(SUM(J10:U10)/$W$16,0) -> 0
H11: Days worked
H12: Harvesting Rate
G13: Total | H13: Harvested Tonnes | I13: =SUM(I4:I12) -> 0 | J13: =J4+J7+J10 -> 0 | K13: =K4+K7+K10 -> 0 | L13: =L4+L7+L10 -> 0 | M13: =M4+M7+M10 -> 0 | N13: =N4+N7+N10 -> 0 | O13: =O4+O7+O10 -> 0 | P13: =P4+P7+P10 -> 0 | Q13: =Q4+Q7+Q10 -> 0 | ... U13: =U4+U7+U10 -> 0 | W13: =I3 -> 0 | X13: Monthly Working Days
H14: Variance Tones | J14: =J13-J16 -> 0 | K14: =K13-K16 -> 0 | L14: =L13-L16 -> 0 | M14: =M13-M16 -> 0 | N14: =N13-N16 -> 0 | O14: =O13-O16 -> 0 | P14: =P13-P16 -> 0 | Q14: =Q13-Q16 -> 0 | ... U14: =U13-U16 -> 0 | W14: =SUM(J14:U14) -> 0 | X14: =H14 -> Variance Tones
G15: Total | H15: Hectare (ha) | J15: =IFERROR(J13/$I$2,0) -> 0 | K15: =IFERROR(K13/$I$2,0) -> 0 | L15: =IFERROR(L13/$I$2,0) -> 0 | M15: =IFERROR(M13/$I$2,0) -> 0 | N15: =IFERROR(N13/$I$2,0) -> 0 | O15: =IFERROR(O13/$I$2,0) -> 0 | P15: =IFERROR(P13/$I$2,0) -> 0 | Q15: =IFERROR(Q13/$I$2,0) -> 0 | ... U15: =IFERROR(U13/$I$2,0) -> 0 | W15: =SUM(J15:U15) -> 0 | X15: =H15 -> Hectare (ha)
G16: Total | H16: Invoice Tonnes | J16: =Volume_2!D27 -> 0 | K16: =Volume_2!H27 -> 0 | L16: =Volume_2!L27 -> 0 | M16: =Volume_2!P27 -> 0 | N16: =Volume_2!T27 -> 0 | O16: =Volume_2!X27 -> 0 | P16: =Volume_2!AB27 -> 0 | Q16: =Volume_2!AF27 -> 0 | R16: =Volume_2!AJ27 -> 0 | S16: =Volume_2!AN27 -> 0 | T16: =Volume_2!AR27 -> 0 | U16: =Volume_2!AV27 -> 0 | W16: =SUM(J16:U16) -> 0 | X16: =H16 -> Invoice Tonnes
B18: REVENUE
B19: Grade | C19: Grade Mix % | D19: Conversion Rate | E19: Sale unit | F19: Sale unit/t | G19: Price/Unit | H19: TOTAL | J19: 45658 | K19: 45689 | L19: 45717 | M19: 45748 | N19: 45778 | O19: 45809 | P19: 45839 | Q19: 45870 | R19: 45901 | S19: 45931 | T19: 45962 | U19: 45992
B20: P35 | E20: Tonnes | H20: =SUM(J20:U20) -> 0 | J20: =Volume_2!G4 -> 0 | K20: =Volume_2!K4 -> 0 | L20: =Volume_2!O4 -> 0 | M20: =Volume_2!S4 -> 0 | N20: =Volume_2!W4 -> 0 | O20: =Volume_2!AA4 -> 0 | P20: =Volume_2!AE4 -> 0 | Q20: =Volume_2!AI4 -> 0 | R20: =Volume_2!AM4 -> 0 | S20: =Volume_2!AQ4 -> 0 | T20: =Volume_2!AU4 -> 0 | U20: =Volume_2!AY4 -> 0
B21: S30 | E21: Tonnes | H21: =SUM(J21:U21) -> 0 | J21: =Volume_2!G5 -> 0 | K21: =Volume_2!K5 -> 0 | L21: =Volume_2!O5 -> 0 | M21: =Volume_2!S5 -> 0 | N21: =Volume_2!W5 -> 0 | O21: =Volume_2!AA5 -> 0 | P21: =Volume_2!AE5 -> 0 | Q21: =Volume_2!AI5 -> 0 | R21: =Volume_2!AM5 -> 0 | S21: =Volume_2!AQ5 -> 0 | T21: =Volume_2!AU5 -> 0 | U21: =Volume_2!AY5 -> 0
B22: S20 | E22: Tonnes | H22: =SUM(J22:U22) -> 0 | J22: =Volume_2!G6 -> 0 | K22: =Volume_2!K6 -> 0 | L22: =Volume_2!O6 -> 0 | M22: =Volume_2!S6 -> 0 | N22: =Volume_2!W6 -> 0 | O22: =Volume_2!AA6 -> 0 | P22: =Volume_2!AE6 -> 0 | Q22: =Volume_2!AI6 -> 0 | R22: =Volume_2!AM6 -> 0 | S22: =Volume_2!AQ6 -> 0 | T22: =Volume_2!AU6 -> 0 | U22: =Volume_2!AY6 -> 0
B23: Domestic Pulp | E23: Tonnes | H23: =SUM(J23:U23) -> 0 | J23: =Volume_2!G7 -> 0 | K23: =Volume_2!K7 -> 0 | L23: =Volume_2!O7 -> 0 | M23: =Volume_2!S7 -> 0 | N23: =Volume_2!W7 -> 0 | O23: =Volume_2!AA7 -> 0 | P23: =Volume_2!AE7 -> 0 | Q23: =Volume_2!AI7 -> 0 | R23: =Volume_2!AM7 -> 0 | S23: =Volume_2!AQ7 -> 0 | T23: =Volume_2!AU7 -> 0 | U23: =Volume_2!AY7 -> 0
B24: Eucalyptus | E24: Tonnes | H24: =SUM(J24:U24) -> 0 | J24: =Volume_2!G8 -> 0 | K24: =Volume_2!K8 -> 0 | L24: =Volume_2!O8 -> 0 | M24: =Volume_2!S8 -> 0 | N24: =Volume_2!W8 -> 0 | O24: =Volume_2!AA8 -> 0 | P24: =Volume_2!AE8 -> 0 | Q24: =Volume_2!AI8 -> 0 | R24: =Volume_2!AM8 -> 0 | S24: =Volume_2!AQ8 -> 0 | T24: =Volume_2!AU8 -> 0 | U24: =Volume_2!AY8 -> 0
B25: FW | E25: Tonnes | H25: =SUM(J25:U25) -> 0 | J25: =Volume_2!G9 -> 0 | K25: =Volume_2!K9 -> 0 | L25: =Volume_2!O9 -> 0 | M25: =Volume_2!S9 -> 0 | N25: =Volume_2!W9 -> 0 | O25: =Volume_2!AA9 -> 0 | P25: =Volume_2!AE9 -> 0 | Q25: =Volume_2!AI9 -> 0 | R25: =Volume_2!AM9 -> 0 | S25: =Volume_2!AQ9 -> 0 | T25: =Volume_2!AU9 -> 0 | U25: =Volume_2!AY9 -> 0
B26: Euc Pulp | E26: Tonnes | H26: =SUM(J26:U26) -> 0 | J26: =Volume_2!G10 -> 0 | K26: =Volume_2!K10 -> 0 | L26: =Volume_2!O10 -> 0 | M26: =Volume_2!S10 -> 0 | N26: =Volume_2!W10 -> 0 | O26: =Volume_2!AA10 -> 0 | P26: =Volume_2!AE10 -> 0 | Q26: =Volume_2!AI10 -> 0 | R26: =Volume_2!AM10 -> 0 | S26: =Volume_2!AQ10 -> 0 | T26: =Volume_2!AU10 -> 0 | U26: =Volume_2!AY10 -> 0
B27: Binwood | E27: Tonnes | H27: =SUM(J27:U27) -> 0 | J27: =Volume_2!G11 -> 0 | K27: =Volume_2!K11 -> 0 | L27: =Volume_2!O11 -> 0 | M27: =Volume_2!S11 -> 0 | N27: =Volume_2!W11 -> 0 | O27: =Volume_2!AA11 -> 0 | P27: =Volume_2!AE11 -> 0 | Q27: =Volume_2!AI11 -> 0 | R27: =Volume_2!AM11 -> 0 | S27: =Volume_2!AQ11 -> 0 | T27: =Volume_2!AU11 -> 0 | U27: =Volume_2!AY11 -> 0
B28: Spare Grade | E28: Tonnes | H28: =SUM(J28:U28) -> 0 | J28: =Volume_2!G12 -> 0 | K28: =Volume_2!K12 -> 0 | L28: =Volume_2!O12 -> 0 | M28: =Volume_2!S12 -> 0 | N28: =Volume_2!W12 -> 0 | O28: =Volume_2!AA12 -> 0 | P28: =Volume_2!AE12 -> 0 | Q28: =Volume_2!AI12 -> 0 | R28: =Volume_2!AM12 -> 0 | S28: =Volume_2!AQ12 -> 0 | T28: =Volume_2!AU12 -> 0 | U28: =Volume_2!AY12 -> 0
B29: P40 | E29: JAS | H29: =SUM(J29:U29) -> 0 | J29: =Volume_2!G13 -> 0 | K29: =Volume_2!K13 -> 0 | L29: =Volume_2!O13 -> 0 | M29: =Volume_2!S13 -> 0 | N29: =Volume_2!W13 -> 0 | O29: =Volume_2!AA13 -> 0 | P29: =Volume_2!AE13 -> 0 | Q29: =Volume_2!AI13 -> 0 | R29: =Volume_2!AM13 -> 0 | S29: =Volume_2!AQ13 -> 0 | T29: =Volume_2!AU13 -> 0 | U29: =Volume_2!AY13 -> 0
B30: P30 | E30: JAS | H30: =SUM(J30:U30) -> 0 | J30: =Volume_2!G14 -> 0 | K30: =Volume_2!K14 -> 0 | L30: =Volume_2!O14 -> 0 | M30: =Volume_2!S14 -> 0 | N30: =Volume_2!W14 -> 0 | O30: =Volume_2!AA14 -> 0 | P30: =Volume_2!AE14 -> 0 | Q30: =Volume_2!AI14 -> 0 | R30: =Volume_2!AM14 -> 0 | S30: =Volume_2!AQ14 -> 0 | T30: =Volume_2!AU14 -> 0 | U30: =Volume_2!AY14 -> 0
B31: AO | E31: JAS | H31: =SUM(J31:U31) -> 0 | J31: =Volume_2!G15 -> 0 | K31: =Volume_2!K15 -> 0 | L31: =Volume_2!O15 -> 0 | M31: =Volume_2!S15 -> 0 | N31: =Volume_2!W15 -> 0 | O31: =Volume_2!AA15 -> 0 | P31: =Volume_2!AE15 -> 0 | Q31: =Volume_2!AI15 -> 0 | R31: =Volume_2!AM15 -> 0 | S31: =Volume_2!AQ15 -> 0 | T31: =Volume_2!AU15 -> 0 | U31: =Volume_2!AY15 -> 0
... B41: Euc K | E41: JAS | H41: =SUM(J41:U41) -> 0 | J41: =Volume_2!G25 -> 0 | K41: =Volume_2!K25 -> 0 | L41: =Volume_2!O25 -> 0 | M41: =Volume_2!S25 -> 0 | N41: =Volume_2!W25 -> 0 | O41: =Volume_2!AA25 -> 0 | P41: =Volume_2!AE25 -> 0 | Q41: =Volume_2!AI25 -> 0 | R41: =Volume_2!AM25 -> 0 | S41: =Volume_2!AQ25 -> 0 | T41: =Volume_2!AU25 -> 0 | U41: =Volume_2!AY25 -> 0
C42: =SUM(C20:C41) -> 0
B43: Export Sales | C43: =SUMIF(E20:E41,"JAS",C20:C41) -> 0 | H43: =SUM(J43:U43) -> 0 | J43: =SUM(J28:J41) -> 0 | K43: =SUM(K28:K41) -> 0 | L43: =SUM(L28:L41) -> 0 | M43: =SUM(M28:M41) -> 0 | N43: =SUM(N28:N41) -> 0 | O43: =SUM(O28:O41) -> 0 | P43: =SUM(P28:P41) -> 0 | Q43: =SUM(Q28:Q41) -> 0 | ... U43: =SUM(U28:U41) -> 0
B44: Domestic Sales | C44: =SUMIF(E20:E41,"Tonnes",C20:C41) -> 0 | H44: =SUM(J44:U44) -> 0 | J44: =SUM(J20:J27) -> 0 | K44: =SUM(K20:K27) -> 0 | L44: =SUM(L20:L27) -> 0 | M44: =SUM(M20:M27) -> 0 | N44: =SUM(N20:N27) -> 0 | O44: =SUM(O20:O27) -> 0 | P44: =SUM(P20:P27) -> 0 | Q44: =SUM(Q20:Q27) -> 0 | ... U44: =SUM(U20:U27) -> 0
B46: TOTAL | G46: =IFERROR(H46/W16,0) -> 0 | H46: =SUM(H20:H41) -> 0 | J46: =SUM(J20:J41) -> 0 | K46: =SUM(K20:K41) -> 0 | L46: =SUM(L20:L41) -> 0 | M46: =SUM(M20:M41) -> 0 | N46: =SUM(N20:N41) -> 0 | O46: =SUM(O20:O41) -> 0 | P46: =SUM(P20:P41) -> 0 | Q46: =SUM(Q20:Q41) -> 0 | ... U46: =SUM(U20:U41) -> 0 | W46: =SUM(J46:U46) -> 0
B48: COSTS | C48: Op Code | D48: Activity
B49: Log and Load | C49: 300/01 | D49: Logging
H50: TOTAL | J50: 45658 | K50: 45689 | L50: 45717 | M50: 45748 | N50: 45778 | O50: 45809 | P50: 45839 | Q50: 45870 | R50: 45901 | S50: 45931 | T50: 45962 | U50: 45992
G51: =IFERROR(H51/W16,0) -> 0 | H51: =SUM(J51:U51) -> 0 | W51: =SUM(J51:U51) -> 0
B54: Log Transport
B55: Grade | C55: Op Code | D55: Activity | E55: Destination | F55: Destination | G55: Cost/t | H55: TOTAL | J55: 45658 | K55: 45689 | L55: 45717 | M55: 45748 | N55: 45778 | O55: 45809 | P55: 45839 | Q55: 45870 | R55: 45901 | S55: 45931 | T55: 45962 | U55: 45992
B56: P35 | C56: 300/02 | D56: Transport | E56: Domestic | F56: Pukepine | G56: 37.044 | H56: =SUM(J56:U56) -> 0
B57: S30 | C57: 300/02 | D57: Transport | E57: Domestic | F57: CHH | G57: 37.044 | H57: 0
B58: S20 | C58: 300/02 | D58: Transport | E58: Domestic | H58: =SUM(J58:U58) -> 0
B59: Domestic Pulp | C59: 300/02 | D59: Transport | E59: Domestic | F59: Tasman | G59: 35.7 | H59: =SUM(J59:U59) -> 0
B60: Eucalyptus | C60: 300/02 | D60: Transport | E60: Domestic | H60: =SUM(J60:U60) -> 0
B61: FW | C61: 300/02 | D61: Transport | E61: Domestic | H61: =SUM(J61:U61) -> 0
B62: Euc Pulp | C62: 300/02 | D62: Transport | E62: Domestic | H62: =SUM(J62:U62) -> 0
B63: Binwood | C63: 300/02 | D63: Transport | E63: Domestic | H63: =SUM(J63:U63) -> 0
B64: P40 | C64: 300/02 | D64: Transport | E64: AWG | F64: Tauranga | G64: 41.748 | H64: =SUM(J64:U64) -> 0
B65: P30 | C65: 300/02 | D65: Transport | E65: AWG | F65: Tauranga | G65: 41.748 | H65: =SUM(J65:U65) -> 0
B66: AO | C66: 300/02 | D66: Transport | E66: AWG | F66: Tauranga | G66: 41.748 | H66: =SUM(J66:U66) -> 0
B67: A | C67: 300/02 | D67: Transport | E67: AWG | F67: Tauranga | G67: 41.748 | H67: =SUM(J67:U67) -> 0
B68: K | C68: 300/02 | D68: Transport | E68: AWG | F68: Tauranga | G68: 41.748 | H68: =SUM(J68:U68) -> 0
B69: KI | C69: 300/02 | D69: Transport | E69: AWG | F69: Tauranga | G69: 41.748 | H69: =SUM(J69:U69) -> 0
B70: KI stub | C70: 300/02 | D70: Transport | E70: AWG | F70: Tauranga | G70: 41.748 | H70: =SUM(J70:U70) -> 0
B71: KIS | C71: 300/02 | D71: Transport | E71: AWG | F71: Tauranga | G71: 41.748 | H71: =SUM(J71:U71) -> 0
B72: CF+ | C72: 300/02 | D72: Transport | E72: AWG | F72: Tauranga | G72: 41.748 | H72: =SUM(J72:U72) -> 0
B73: CF- | C73: 300/02 | D73: Transport | E73: AWG | F73: Tauranga | G73: 41.748 | H73: =SUM(J73:U73) -> 0
B74: CM | C74: 300/02 | D74: Transport | E74: AWG | F74: Tauranga | G74: 41.748 | H74: =SUM(J74:U74) -> 0
B75: Euc A | C75: 300/02 | D75: Transport | E75: AWG | H75: =SUM(J75:U75) -> 0
B76: Euc K | C76: 300/02 | D76: Transport | H76: =SUM(J76:U76) -> 0
B77: Spare grade | C77: 300/02 | D77: Transport | H77: =SUM(J77:U77) -> 0
G78: =H78/W16 -> #DIV/0! | H78: =SUM(H56:H77) -> 0 | W78: =SUM(J78:U78) -> 0
B80: Non-docket costs
B81: Operation | C81: Op Code | D81: Activity | E81: Resource | F81: Product | G81: Destination | H81: TOTAL | J81: 45658 | K81: 45689 | L81: 45717 | M81: 45748 | N81: 45778 | O81: 45809 | P81: 45839 | Q81: 45870 | R81: 45901 | S81: 45931 | T81: 45962 | U81: 45992
B82: Tracking | C82: 300/04 | D82: Logging | H82: =SUM(J82:U82) -> 0
B83: Logging Machinery establishment/transportation | C83: 300/06 | D83: Logging | E83: 699 | F83: 3675 | H83: =SUM(J83:U83) -> 0
B84: Road control | C84: 300/16 | D84: Logging | E84: 699 | F84: 3691 | H84: =SUM(J84:U84) -> 0
B85: Powerline costs | C85: 300/17 | D85: Logging | E85: 699 | F85: 3677 | H85: =SUM(J85:U85) -> 0
B86: Fencing & gate construction | C86: 721 | D86: Logging | E86: 699 | F86: 3671 | H86: =SUM(J86:U86) -> 0
B87: Deadman | C87: 300/18 | D87: Logging | E87: 699 | F87: 3669 | H87: =SUM(J87:U87) -> 0
B88: Two-stage | C88: 300/19 | D88: Logging | E88: 699 | F88: 3665 | H88: =SUM(J88:U88) -> 0
B89: Harvest Planning | C89: 300/09 | D89: Logging | E89: 699 | F89: 3963 | H89: =SUM(J89:U89) -> 0
B90: Roading machinery establishment/transportation | C90: 300/07 | D90: Infrastructure | H90: =SUM(J90:U90) -> 0
B91: New Road Metalled or sealed | C91: 720 | D91: Infrastructure | H91: =SUM(J91:U91) -> 0 | J91: =J115 -> 0 | K91: =K115 -> 0 | L91: =L115 -> 0 | M91: =M115 -> 0 | N91: =N115 -> 0 | O91: =O115 -> 0 | P91: =P115 -> 0 | Q91: =Q115 -> 0 | ... U91: =U115 -> 0
B92: Upgrade Road metalled or sealed | C92: 720 | D92: Infrastructure | H92: =SUM(J92:U92) -> 0
B93: Other infrastructure | C93: 720 | D93: Infrastructure | H93: =SUM(J93:U93) -> 0
B94: Skid construction | C94: 300/05 | D94: Infrastructure | H94: =SUM(J94:U94) -> 0 | J94: =J119 -> 0 | K94: =K119 -> 0 | L94: =L119 -> 0 | M94: =M119 -> 0 | N94: =N119 -> 0 | O94: =O119 -> 0 | P94: =P119 -> 0 | Q94: =Q119 -> 0 | ... U94: =U119 -> 0
B95: Pad construction | C95: 300/05 | D95: Infrastructure | H95: =SUM(J95:U95) -> 0 | J95: =J120 -> 0 | K95: =K120 -> 0 | L95: =L120 -> 0 | M95: =M120 -> 0 | N95: =N120 -> 0 | O95: =O120 -> 0 | P95: =P120 -> 0 | Q95: =Q120 -> 0 | ... U95: =U120 -> 0
B96: Maintenance Forest Road | C96: 305 | D96: Maintenance | H96: =SUM(J96:U96) -> 0
B97: Maintenance Public Road | C97: 306 | D97: Maintenance | H97: =SUM(J97:U97) -> 0
B98: Skid/Pad maintenance | C98: 300/14 | D98: Post harvest costs | H98: =SUM(J98:U98) -> 0
B99: Post-harvest clean-up | C99: 300/10 | D99: Post harvest costs | H99: =SUM(J99:U99) -> 0
B100: Health and safety and Auditing | C100: 300/11 | D100: Indirect costs | H100: =SUM(J100:U100) -> 0
B101: Weighbridge | C101: 300/03 | D101: Indirect costs | G101: =IFERROR(H101/$W$16,0) -> 0 | H101: =SUM(J101:U101) -> 0
B102: Environmental monitoring/consents | C102: 330/04 | D102: Indirect costs | E102: 365 | H102: =SUM(J102:U102) -> 0
B103: Forest levy | C103: 300/08 | D103: Mgmt/Admin | E103: 338 | G103: 0.33 | H103: =SUM(J103:U103) -> 0 | J103: =$G$103*J16 -> 0 | K103: =$G$103*K16 -> 0 | L103: =$G$103*L16 -> 0 | M103: =$G$103*M16 -> 0 | N103: =$G$103*N16 -> 0 | O103: =$G$103*O16 -> 0 | P103: =$G$103*P16 -> 0 | Q103: =$G$103*Q16 -> 0 | ... U103: =$G$103*U16 -> 0
B104: Insurance Payment protection (domestic sales only) | C104: 351 | D104: Mgmt/Admin | E104: 324 | G104: 0.0016 | H104: =SUM(J104:U104) -> 0 | J104: =$G$104*J46/100 -> 0 | K104: =$G$104*K46/100 -> 0 | L104: =$G$104*L46/100 -> 0 | M104: =$G$104*M46/100 -> 0 | N104: =$G$104*N46/100 -> 0 | O104: =$G$104*O46/100 -> 0 | P104: =$G$104*P46/100 -> 0 | Q104: =$G$104*Q46/100 -> 0 | ... U104: =$G$104*U46/100 -> 0
B105: Harvest management fee | C105: 300/12 | D105: Mgmt/Admin | G105: 3.75 | H105: =SUM(J105:U105) -> 0 | J105: =$G$105*J16 -> 0 | K105: =$G$105*K16 -> 0 | L105: =$G$105*L16 -> 0 | M105: =$G$105*M16 -> 0 | N105: =$G$105*N16 -> 0 | O105: =$G$105*O16 -> 0 | P105: =$G$105*P16 -> 0 | Q105: =$G$105*Q16 -> 0 | ... U105: =$G$105*U16 -> 0
B107: Total non-docket costs | G107: =IFERROR(H107/B127,0) -> 0 | H107: =SUM(H82:H105) -> 0 | J107: =SUM(J82:J105) -> 0 | K107: =SUM(K82:K105) -> 0 | L107: =SUM(L82:L105) -> 0 | M107: =SUM(M82:M105) -> 0 | N107: =SUM(N82:N105) -> 0 | O107: =SUM(O82:O105) -> 0 | P107: =SUM(P82:P105) -> 0 | Q107: =SUM(Q82:Q105) -> 0 | ... U107: =SUM(U82:U105) -> 0
B109: Total Costs | H109: =H51+H78+H107 -> 0 | J109: =J51+J78+J107 -> 0 | K109: =K51+K78+K107 -> 0 | L109: =L51+L78+L107 -> 0 | M109: =M51+M78+M107 -> 0 | N109: =N51+N78+N107 -> 0 | O109: =O51+O78+O107 -> 0 | P109: =P51+P78+P107 -> 0 | Q109: =Q51+Q78+Q107 -> 0 | ... U109: =U51+U78+U107 -> 0 | W109: =SUM(J109:U109) -> 0
B111: Net Harvest Total | H111: =H46-H109 -> 0 | J111: =J46-J109 -> 0 | K111: =K46-K109 -> 0 | L111: =L46-L109 -> 0 | M111: =M46-M109 -> 0 | N111: =N46-N109 -> 0 | O111: =O46-O109 -> 0 | P111: =P46-P109 -> 0 | Q111: =Q46-Q109 -> 0 | ... U111: =U46-U109 -> 0 | W111: =SUM(J111:U111) -> 0
B113: Engineering | C113: Op Code | D113: Activity | E113: Unit | F113: Vol | G113: Unit Rate | J113: Metres constructed or number of skids/pads
B114: Existing road upgrade-Substantially metalled or sealed | C114: 720 | D114: Infrastructure | E114: cost/m
B115: New road construction-Substantially metalled or sealed | C115: 720 | D115: Infrastructure | E115: cost/m | G115: =IFERROR(H115/F115,0) -> 0
B116: Existing road upgrade-Partially metalled or sealed | C116: 720 | D116: Infrastructure | E116: cost/m
B117: New road construction-Partially metalled or sealed | C117: 720 | D117: Infrastructure | E117: cost/m
B118: Other infrastructure | C118: 720 | D118: Infrastructure | E118: cost/unit
B119: Skid construction | C119: 300/05 | D119: Infrastructure | E119: cost/skid | G119: =IFERROR(H119/F119,0) -> 0
...

Sheet Whakatikei Budget
C1: 2025 | D1: Input
B2: Whakatikei | H2: Estimated Tonnes (ha)
B3: PRODUCTION & RATE | G3: Total Monthly Working Days | I3: =IF(NOT(ISBLANK(J5)), J5, IF(NOT(ISBLANK(J8)), J8, IF(NOT(ISBLANK(J11)), J11, 0)))+IF(NOT(ISBLANK(K5)), K5, IF(NOT(ISBLANK(K8)), K8, IF(NOT(ISBLANK(K11)), K11, 0)))+IF(NOT(ISBLANK(L5)), L5, IF(NOT(ISBLANK(L8)), L8, IF(NOT(ISBLANK(L11)), L11, 0)))+IF(NOT(ISBLANK(M5)), M5, IF(NOT(ISBLANK(M8)), M8, IF(NOT(ISBLANK(M11)), M11, 0)))+IF(NOT(ISBLANK(N5)), N5, IF(NOT(ISBLANK(N8)), N8, IF(NOT(ISBLANK(N11)), N11, 0)))+IF(NOT(ISBLANK(O5)), O5, IF(NOT(ISBLANK(O8)), O8, IF(NOT(ISBLANK(O11)), O11, 0)))+IF(NOT(ISBLANK(P5)), P5, IF(NOT(ISBLANK(P8)), P8, IF(NOT(ISBLANK(P11)), P11, 0)))+IF(NOT(ISBLANK(Q5)), Q5, IF(NOT(ISBLANK(Q8)), Q8, IF(NOT(ISBLANK(Q11)), Q11, 0)))+IF(NOT(ISBLANK(R5)), R5, IF(NOT(ISBLANK(R8)), R8, IF(NOT(ISBLANK(R11)), R11, 0)))+IF(NOT(ISBLANK(S5)), S5, IF(NOT(ISBLANK(S8)), S8, IF(NOT(ISBLANK(S11)), S11, 0)))+IF(NOT(ISBLANK(T5)), T5, IF(NOT(ISBLANK(T8)), T8, IF(NOT(ISBLANK(T11)), T11, 0)))+IF(NOT(ISBLANK(U5)), U5, IF(NOT(ISBLANK(U8)), U8, IF(NOT(ISBLANK(U11)), U11, 0))) -> 0 | J3: 45658 | K3: 45689 | L3: 45717 | M3: 45748 | N3: 45778 | O3: 45809 | P3: 45839 | Q3: 45870 | R3: 45901 | S3: 45931 | T3: 45962 | U3: 45992 | W3: Total
G4: Groundbase | H4: Daily production | I4: =IFERROR((J4*J5+K4*K5+L4*L5+M4*M5+N4*N5+O4*O5+P4*P5+Q4*Q5+R4*R5+S4*S5+T4*T5+U4*U5)/$W$16,0) -> 0
H5: Days worked
H6: Harvesting Rate
G7: Roadline | H7: Daily production | I7: =IFERROR((J7*J8+K7*K8+L7*L8+M7*M8+N7*N8+O7*O8+P7*P8+Q7*Q8+R7*R8+S7*S8+T7*T8+U7*U8)/$W$16,0) -> 0
H8: Days worked
H9: Harvesting Rate
G10: Hauler | H10: Daily production | I10: =IFERROR((J10*J11+K10*K11+L10*L11+M10*M11+N10*N11+O10*O11+P10*P11+Q10*Q11+R10*R11+S10*S11+T10*T11+U10*U11)/$W$16,0) -> 0
H11: Days worked
H12: Harvesting Rate
G13: Average | H13: Harvesting Rate | I13: =SUM(I4:I12) -> 0 | J13: =IFERROR((J4*J5*J6+J7*J8*J9+J10*J11*J12)/J16,0) -> 0 | K13: =IFERROR((K4*K5*K6+K7*K8*K9+K10*K11*K12)/K16,0) -> 0 | L13: =IFERROR((L4*L5*L6+L7*L8*L9+L10*L11*L12)/L16,0) -> 0 | M13: =IFERROR((M4*M5*M6+M7*M8*M9+M10*M11*M12)/M16,0) -> 0 | N13: =IFERROR((N4*N5*N6+N7*N8*N9+N10*N11*N12)/N16,0) -> 0 | O13: =IFERROR((O4*O5*O6+O7*O8*O9+O10*O11*O12)/O16,0) -> 0 | P13: =IFERROR((P4*P5*P6+P7*P8*P9+P10*P11*P12)/P16,0) -> 0 | Q13: =IFERROR((Q4*Q5*Q6+Q7*Q8*Q9+Q10*Q11*Q12)/Q16,0) -> 0 | ... U13: =IFERROR((U4*U5*U6+U7*U8*U9+U10*U11*U12)/U16,0) -> 0 | W13: =I3 -> 0 | X13: Monthly Working Days
G14: Average | H14: Daily production | J14: =J4+J7+J10 -> 0 | K14: =K4+K7+K10 -> 0 | L14: =L4+L7+L10 -> 0 | M14: =M4+M7+M10 -> 0 | N14: =N4+N7+N10 -> 0 | O14: =O4+O7+O10 -> 0 | P14: =P4+P7+P10 -> 0 | Q14: =Q4+Q7+Q10 -> 0 | ... U14: =U4+U7+U10 -> 0 | W14: =IF(W16=0,0,W16/W15) -> 0 | X14: =H2 -> Estimated Tonnes (ha)
G15: Total | H15: Hectare (ha) | J15: =IFERROR(J16/$I$2,0) -> 0 | K15: =IFERROR(K16/$I$2,0) -> 0 | L15: =IFERROR(L16/$I$2,0) -> 0 | M15: =IFERROR(M16/$I$2,0) -> 0 | N15: =IFERROR(N16/$I$2,0) -> 0 | O15: =IFERROR(O16/$I$2,0) -> 0 | P15: =IFERROR(P16/$I$2,0) -> 0 | Q15: =IFERROR(Q16/$I$2,0) -> 0 | ... U15: =IFERROR(U16/$I$2,0) -> 0 | W15: =SUM(J15:U15) -> 0 | X15: =H15 -> Hectare (ha)
G16: Total | H16: Tonnes Harvested | J16: =IFERROR((J4*J5+J7*J8+J10*J11),0) -> 0 | K16: =IFERROR((K4*K5+K7*K8+K10*K11),0) -> 0 | L16: =IFERROR((L4*L5+L7*L8+L10*L11),0) -> 0 | M16: =IFERROR((M4*M5+M7*M8+M10*M11),0) -> 0 | N16: =IFERROR((N4*N5+N7*N8+N10*N11),0) -> 0 | O16: =IFERROR((O4*O5+O7*O8+O10*O11),0) -> 0 | P16: =IFERROR((P4*P5+P7*P8+P10*P11),0) -> 0 | Q16: =IFERROR((Q4*Q5+Q7*Q8+Q10*Q11),0) -> 0 | ... U16: =IFERROR((U4*U5+U7*U8+U10*U11),0) -> 0 | W16: =SUM(J16:U16) -> 0 | X16: =H16 -> Tonnes Harvested
W17: =W16/W15 -> #DIV/0! | X17: Vol/ha
B18: REVENUE
B19: Grade | C19: Grade Mix % | D19: Conversion Rate | E19: Sale unit | F19: Sale unit/Vol | G19: Price/Unit | H19: TOTAL | J19: 45658 | K19: 45689 | L19: 45717 | M19: 45748 | N19: 45778 | O19: 45809 | P19: 45839 | Q19: 45870 | R19: 45901 | S19: 45931 | T19: 45962 | U19: 45992
B20: P35 | C20: 0.25 | D20: 1 | E20: Tonnes | F20: =IFERROR(H20/G20,0) -> 0 | H20: =SUM(J20:U20) -> 0 | J20: =J16*$C20*$D20*$G20 -> 0 | K20: =K16*$C$20*$D$20*$G$20 -> 0 | L20: =L16*$C$20*$D$20*$G$20 -> 0 | M20: =M16*$C$20*$D$20*$G$20 -> 0 | N20: =N16*$C$20*$D$20*$G$20 -> 0 | O20: =O16*$C$20*$D$20*$G$20 -> 0 | P20: =P16*$C$20*$D$20*$G$20 -> 0 | Q20: =Q16*$C$20*$D$20*$G$20 -> 0 | R20: =R16*$C$20*$D$20*$G$20 -> 0 | ... U20: =U16*$C$20*$D$20*$G$20 -> 0 | W20: =$W$17*C20 -> #DIV/0! | X20: =B20 -> P35
B21: S30 | C21: 0.06 | D21: 1 | E21: Tonnes | F21: =IFERROR(H21/G21,0) -> 0 | H21: =SUM(J21:U21) -> 0 | J21: =J16*$C$21*$D$21*$G$21 -> 0 | K21: =K16*$C$21*$D$21*$G$21 -> 0 | L21: =L16*$C$21*$D$21*$G$21 -> 0 | M21: =M16*$C$21*$D$21*$G$21 -> 0 | N21: =N16*$C$21*$D$21*$G$21 -> 0 | O21: =O16*$C$21*$D$21*$G$21 -> 0 | P21: =P16*$C$21*$D$21*$G$21 -> 0 | Q21: =Q16*$C$21*$D$21*$G$21 -> 0 | ... U21: =U16*$C$21*$D$21*$G$21 -> 0 | W21: =$W$17*C21 -> #DIV/0! | X21: =B21 -> S30
B22: S20 | C22: 0 | D22: 1 | E22: Tonnes | F22: =IFERROR(H22/G22,0) -> 0 | H22: =SUM(J22:U22) -> 0 | J22: =J16*$C$22*$D$22*$G$22 -> 0 | K22: =K16*$C$22*$D$22*$G$22 -> 0 | L22: =L16*$C$22*$D$22*$G$22 -> 0 | M22: =M16*$C$22*$D$22*$G$22 -> 0 | N22: =N16*$C$22*$D$22*$G$22 -> 0 | O22: =O16*$C$22*$D$22*$G$22 -> 0 | P22: =P16*$C$22*$D$22*$G$22 -> 0 | Q22: =Q16*$C$22*$D$22*$G$22 -> 0 | ... U22: =U16*$C$22*$D$22*$G$22 -> 0 | W22: =$W$17*C22 -> #DIV/0! | X22: =B22 -> S20
B23: Domestic Pulp | C23: 0.02 | D23: 1 | E23: Tonnes | F23: =IFERROR(H23/G23,0) -> 0 | H23: =SUM(J23:U23) -> 0 | J23: =J16*$C$23*$D$23*$G$23 -> 0 | K23: =K16*$C$23*$D$23*$G$23 -> 0 | L23: =L16*$C$23*$D$23*$G$23 -> 0 | M23: =M16*$C$23*$D$23*$G$23 -> 0 | N23: =N16*$C$23*$D$23*$G$23 -> 0 | O23: =O16*$C$23*$D$23*$G$23 -> 0 | P23: =P16*$C$23*$D$23*$G$23 -> 0 | Q23: =Q16*$C$23*$D$23*$G$23 -> 0 | ... U23: =U16*$C$23*$D$23*$G$23 -> 0 | W23: =$W$17*C23 -> #DIV/0! | X23: =B23 -> Domestic Pulp
B24: Eucalyptus | C24: 0 | D24: 1 | E24: Tonnes | F24: =IFERROR(H24/G24,0) -> 0 | H24: =SUM(J24:U24) -> 0 | J24: =J16*$C$24*$D$24*$G$24 -> 0 | K24: =K16*$C$24*$D$24*$G$24 -> 0 | L24: =L16*$C$24*$D$24*$G$24 -> 0 | M24: =M16*$C$24*$D$24*$G$24 -> 0 | N24: =N16*$C$24*$D$24*$G$24 -> 0 | O24: =O16*$C$24*$D$24*$G$24 -> 0 | P24: =P16*$C$24*$D$24*$G$24 -> 0 | Q24: =Q16*$C$24*$D$24*$G$24 -> 0 | ... U24: =U16*$C$24*$D$24*$G$24 -> 0 | W24: =$W$17*C24 -> #DIV/0! | X24: =B24 -> Eucalyptus
B25: FW | C25: 0 | D25: 1 | E25: Tonnes | F25: =IFERROR(H25/G25,0) -> 0 | H25: =SUM(J25:U25) -> 0 | J25: =J16*$C$25*$D$25*$G$25 -> 0 | K25: =K16*$C$25*$D$25*$G$25 -> 0 | L25: =L16*$C$25*$D$25*$G$25 -> 0 | M25: =M16*$C$25*$D$25*$G$25 -> 0 | N25: =N16*$C$25*$D$25*$G$25 -> 0 | O25: =O16*$C$25*$D$25*$G$25 -> 0 | P25: =P16*$C$25*$D$25*$G$25 -> 0 | Q25: =Q16*$C$25*$D$25*$G$25 -> 0 | ... U25: =U16*$C$25*$D$25*$G$25 -> 0 | W25: =$W$17*C25 -> #DIV/0! | X25: =B25 -> FW
B26: Euc Pulp | C26: 0 | D26: 1 | E26: Tonnes | F26: =IFERROR(H26/G26,0) -> 0 | H26: =SUM(J26:U26) -> 0 | J26: =J16*$C$26*$D$26*$G$26 -> 0 | K26: =K16*$C$26*$D$26*$G$26 -> 0 | L26: =L16*$C$26*$D$26*$G$26 -> 0 | M26: =M16*$C$26*$D$26*$G$26 -> 0 | N26: =N16*$C$26*$D$26*$G$26 -> 0 | O26: =O16*$C$26*$D$26*$G$26 -> 0 | P26: =P16*$C$26*$D$26*$G$26 -> 0 | Q26: =Q16*$C$26*$D$26*$G$26 -> 0 | ... U26: =U16*$C$26*$D$26*$G$26 -> 0 | W26: =$W$17*C26 -> #DIV/0! | X26: =B26 -> Euc Pulp
B27: Binwood | C27: 0 | D27: 1 | E27: Tonnes | F27: =IFERROR(H27/G27,0) -> 0 | H27: =SUM(J27:U27) -> 0 | J27: =J16*$C$27*$D$27*$G$27 -> 0 | K27: =K16*$C$27*$D$27*$G$27 -> 0 | L27: =L16*$C$27*$D$27*$G$27 -> 0 | M27: =M16*$C$27*$D$27*$G$27 -> 0 | N27: =N16*$C$27*$D$27*$G$27 -> 0 | O27: =O16*$C$27*$D$27*$G$27 -> 0 | P27: =P16*$C$27*$D$27*$G$27 -> 0 | Q27: =Q16*$C$27*$D$27*$G$27 -> 0 | ... U27: =U16*$C$27*$D$27*$G$27 -> 0 | W27: =$W$17*C27 -> #DIV/0! | X27: =B27 -> Binwood
B28: Spare Grade | C28: 0 | E28: Tonnes | F28: =IFERROR(H28/G28/D28,0) -> 0 | H28: =SUM(J28:U28) -> 0 | J28: =J16*$C$28*$D$28*$G$28 -> 0 | K28: =K16*$C$28*$D$28*$G$28 -> 0 | L28: =L16*$C$28*$D$28*$G$28 -> 0 | M28: =M16*$C$28*$D$28*$G$28 -> 0 | N28: =N16*$C$28*$D$28*$G$28 -> 0 | O28: =O16*$C$28*$D$28*$G$28 -> 0 | P28: =P16*$C$28*$D$28*$G$28 -> 0 | Q28: =Q16*$C$28*$D$28*$G$28 -> 0 | ... U28: =U16*$C$28*$D$28*$G$28 -> 0 | W28: =$W$17*C28 -> #DIV/0! | X28: =B28 -> Spare Grade
B29: P40 | C29: 0 | D29: 0.96946341 | E29: JAS | F29: =IFERROR(H29/G29/D29,0) -> 0 | H29: =SUM(J29:U29) -> 0 | J29: =J16*$C$29*$D$29*$G$29 -> 0 | K29: =K16*$C$29*$D$29*$G$29 -> 0 | L29: =L16*$C$29*$D$29*$G$29 -> 0 | M29: =M16*$C$29*$D$29*$G$29 -> 0 | N29: =N16*$C$29*$D$29*$G$29 -> 0 | O29: =O16*$C$29*$D$29*$G$29 -> 0 | P29: =P16*$C$29*$D$29*$G$29 -> 0 | Q29: =Q16*$C$29*$D$29*$G$29 -> 0 | ... U29: =U16*$C$29*$D$29*$G$29 -> 0 | W29: =$W$17*C29 -> #DIV/0! | X29: =B29 -> P40
B30: P30 | C30: 0.01 | D30: 1 | E30: JAS | F30: =IFERROR(H30/G30/D30,0) -> 0 | H30: =SUM(J30:U30) -> 0 | J30: =J16*$C$30*$D$30*$G$30 -> 0 | K30: =K16*$C$30*$D$30*$G$30 -> 0 | L30: =L16*$C$30*$D$30*$G$30 -> 0 | M30: =M16*$C$30*$D$30*$G$30 -> 0 | N30: =N16*$C$30*$D$30*$G$30 -> 0 | O30: =O16*$C$30*$D$30*$G$30 -> 0 | P30: =P16*$C$30*$D$30*$G$30 -> 0 | Q30: =Q16*$C$30*$D$30*$G$30 -> 0 | ... U30: =U16*$C$30*$D$30*$G$30 -> 0 | W30: =$W$17*C30 -> #DIV/0! | X30: =B30 -> P30
B31: AO | C31: 0.12 | D31: 1 | E31: JAS | F31: =IFERROR(H31/G31/D31,0) -> 0 | H31: =SUM(J31:U31) -> 0 | J31: =J16*$C$31*$D$31*$G$31 -> 0 | K31: =K16*$C$31*$D$31*$G$31 -> 0 | L31: =L16*$C$31*$D$31*$G$31 -> 0 | M31: =M16*$C$31*$D$31*$G$31 -> 0 | N31: =N16*$C$31*$D$31*$G$31 -> 0 | O31: =O16*$C$31*$D$31*$G$31 -> 0 | P31: =P16*$C$31*$D$31*$G$31 -> 0 | Q31: =Q16*$C$31*$D$31*$G$31 -> 0 | ... U31: =U16*$C$31*$D$31*$G$31 -> 0 | W31: =$W$17*C31 -> #DIV/0! | X31: =B31 -> AO
B32: A | C32: 0.26 | D32: 0.97 | E32: JAS | F32: =IFERROR(H32/G32/D32,0) -> 0 | H32: =SUM(J32:U32) -> 0 | J32: =J16*$C$32*$D$32*$G$32 -> 0 | K32: =K16*$C$32*$D$32*$G$32 -> 0 | L32: =L16*$C$32*$D$32*$G$32 -> 0 | M32: =M16*$C$32*$D$32*$G$32 -> 0 | N32: =N16*$C$32*$D$32*$G$32 -> 0 | O32: =O16*$C$32*$D$32*$G$32 -> 0 | P32: =P16*$C$32*$D$32*$G$32 -> 0 | Q32: =Q16*$C$32*$D$32*$G$32 -> 0 | ... U32: =U16*$C$32*$D$32*$G$32 -> 0 | W32: =$W$17*C32 -> #DIV/0! | X32: =B32 -> A
B33: K | C33: 0.2 | D33: 0.93 | E33: JAS | F33: =IFERROR(H33/G33/D33,0) -> 0 | H33: =SUM(J33:U33) -> 0 | J33: =J16*$C$33*$D$33*$G$33 -> 0 | K33: =K16*$C$33*$D$33*$G$33 -> 0 | L33: =L16*$C$33*$D$33*$G$33 -> 0 | M33: =M16*$C$33*$D$33*$G$33 -> 0 | N33: =N16*$C$33*$D$33*$G$33 -> 0 | O33: =O16*$C$33*$D$33*$G$33 -> 0 | P33: =P16*$C$33*$D$33*$G$33 -> 0 | Q33: =Q16*$C$33*$D$33*$G$33 -> 0 | ... U33: =U16*$C$33*$D$33*$G$33 -> 0 | W33: =$W$17*C33 -> #DIV/0! | X33: =B33 -> K
B34: KI | C34: 0.02 | D34: 0.94 | E34: JAS | F34: =IFERROR(H34/G34/D34,0) -> 0 | H34: =SUM(J34:U34) -> 0 | J34: =J16*$C$34*$D$34*$G$34 -> 0 | K34: =K16*$C$34*$D$34*$G$34 -> 0 | L34: =L16*$C$34*$D$34*$G$34 -> 0 | M34: =M16*$C$34*$D$34*$G$34 -> 0 | N34: =N16*$C$34*$D$34*$G$34 -> 0 | O34: =O16*$C$34*$D$34*$G$34 -> 0 | P34: =P16*$C$34*$D$34*$G$34 -> 0 | Q34: =Q16*$C$34*$D$34*$G$34 -> 0 | ... U34: =U16*$C$34*$D$34*$G$34 -> 0 | W34: =$W$17*C34 -> #DIV/0! | X34: =B34 -> KI
B35: KIS | C35: 0.06 | D35: 0.85 | E35: JAS | F35: =IFERROR(H35/G35/D35,0) -> 0 | H35: =SUM(J35:U35) -> 0 | J35: =J16*$C$35*$D$35*$G$35 -> 0 | K35: =K16*$C$35*$D$35*$G$35 -> 0 | L35: =L16*$C$35*$D$35*$G$35 -> 0 | M35: =M16*$C$35*$D$35*$G$35 -> 0 | N35: =N16*$C$35*$D$35*$G$35 -> 0 | O35: =O16*$C$35*$D$35*$G$35 -> 0 | P35: =P16*$C$35*$D$35*$G$35 -> 0 | Q35: =Q16*$C$35*$D$35*$G$35 -> 0 | ... U35: =U16*$C$35*$D$35*$G$35 -> 0 | W35: =$W$17*C35 -> #DIV/0! | X35: =B35 -> KIS
B36: KI stub | E36: JAS | F36: =IFERROR(H36/G36/D36,0) -> 0 | H36: =SUM(J36:U36) -> 0 | J36: =J16*$C$36*$D$36*$G$36 -> 0 | K36: =K16*$C$36*$D$36*$G$36 -> 0 | L36: =L16*$C$36*$D$36*$G$36 -> 0 | M36: =M16*$C$36*$D$36*$G$36 -> 0 | N36: =N16*$C$36*$D$36*$G$36 -> 0 | O36: =O16*$C$36*$D$36*$G$36 -> 0 | P36: =P16*$C$36*$D$36*$G$36 -> 0 | Q36: =Q16*$C$36*$D$36*$G$36 -> 0 | ... U36: =U16*$C$36*$D$36*$G$36 -> 0 | W36: =$W$17*C36 -> #DIV/0! | X36: =B36 -> KI stub
B37: CF+ | E37: JAS | F37: =IFERROR(H37/G37/D37,0) -> 0 | H37: =SUM(J37:U37) -> 0 | J37: =J16*$C$37*$D$37*$G$37 -> 0 | K37: =K16*$C$37*$D$37*$G$37 -> 0 | L37: =L16*$C$37*$D$37*$G$37 -> 0 | M37: =M16*$C$37*$D$37*$G$37 -> 0 | N37: =N16*$C$37*$D$37*$G$37 -> 0 | O37: =O16*$C$37*$D$37*$G$37 -> 0 | P37: =P16*$C$37*$D$37*$G$37 -> 0 | Q37: =Q16*$C$37*$D$37*$G$37 -> 0 | ... U37: =U16*$C$37*$D$37*$G$37 -> 0 | W37: =$W$17*C37 -> #DIV/0! | X37: =B37 -> CF+
B38: CF- | E38: JAS | F38: =IFERROR(H38/G38/D38,0) -> 0 | H38: =SUM(J38:U38) -> 0 | J38: =J16*$C$38*$D$38*$G$38 -> 0 | K38: =K16*$C$38*$D$38*$G$38 -> 0 | L38: =L16*$C$38*$D$38*$G$38 -> 0 | M38: =M16*$C$38*$D$38*$G$38 -> 0 | N38: =N16*$C$38*$D$38*$G$38 -> 0 | O38: =O16*$C$38*$D$38*$G$38 -> 0 | P38: =P16*$C$38*$D$38*$G$38 -> 0 | Q38: =Q16*$C$38*$D$38*$G$38 -> 0 | ... U38: =U16*$C$38*$D$38*$G$38 -> 0 | W38: =$W$17*C38 -> #DIV/0! | X38: =B38 -> CF-
B39: CM | E39: JAS | F39: =IFERROR(H39/G39/D39,0) -> 0 | H39: =SUM(J39:U39) -> 0 | J39: =J16*$C$39*$D$39*$G$39 -> 0 | K39: =K16*$C$39*$D$39*$G$39 -> 0 | L39: =L16*$C$39*$D$39*$G$39 -> 0 | M39: =M16*$C$39*$D$39*$G$39 -> 0 | N39: =N16*$C$39*$D$39*$G$39 -> 0 | O39: =O16*$C$39*$D$39*$G$39 -> 0 | P39: =P16*$C$39*$D$39*$G$39 -> 0 | Q39: =Q16*$C$39*$D$39*$G$39 -> 0 | ... U39: =U16*$C$39*$D$39*$G$39 -> 0 | W39: =$W$17*C39 -> #DIV/0! | X39: =B39 -> CM
B40: Euc A | E40: JAS | F40: =IFERROR(H40/G40/D40,0) -> 0 | H40: =SUM(J40:U40) -> 0 | J40: =J16*$C$40*$D$40*$G$40 -> 0 | K40: =K16*$C$40*$D$40*$G$40 -> 0 | L40: =L16*$C$40*$D$40*$G$40 -> 0 | M40: =M16*$C$40*$D$40*$G$40 -> 0 | N40: =N16*$C$40*$D$40*$G$40 -> 0 | O40: =O16*$C$40*$D$40*$G$40 -> 0 | P40: =P16*$C$40*$D$40*$G$40 -> 0 | Q40: =Q16*$C$40*$D$40*$G$40 -> 0 | ... U40: =U16*$C$40*$D$40*$G$40 -> 0 | W40: =$W$17*C40 -> #DIV/0! | X40: =B40 -> Euc A
B41: Euc K | H41: =SUM(J41:U41) -> 0 | J41: =J16*$C$41*$D$41*$G$41 -> 0 | K41: =K16*$C$41*$D$41*$G$41 -> 0 | L41: =L16*$C$41*$D$41*$G$41 -> 0 | M41: =M16*$C$41*$D$41*$G$41 -> 0 | N41: =N16*$C$41*$D$41*$G$41 -> 0 | O41: =O16*$C$41*$D$41*$G$41 -> 0 | P41: =P16*$C$41*$D$41*$G$41 -> 0 | Q41: =Q16*$C$41*$D$41*$G$41 -> 0 | ... U41: =U16*$C$41*$D$41*$G$41 -> 0 | W41: =$W$17*C41 -> #DIV/0! | X41: =B41 -> Euc K
C42: =SUM(C20:C41) -> 1
B43: Export Sales | C43: =SUMIF(E20:E41,"JAS",C20:C41) -> 0.67 | H43: =SUM(J43:U43) -> 0 | J43: =SUM(J28:J41) -> 0 | K43: =SUM(K28:K41) -> 0 | L43: =SUM(L28:L41) -> 0 | M43: =SUM(M28:M41) -> 0 | N43: =SUM(N28:N41) -> 0 | O43: =SUM(O28:O41) -> 0 | P43: =SUM(P28:P41) -> 0 | Q43: =SUM(Q28:Q41) -> 0 | ... U43: =SUM(U28:U41) -> 0 | W43: =SUM(W20:W42) -> #DIV/0!
B44: Domestic Sales | C44: =SUMIF(E20:E41,"Tonnes",C20:C41) -> 0.33 | H44: =SUM(J44:U44) -> 0 | J44: =SUM(J20:J27) -> 0 | K44: =SUM(K20:K27) -> 0 | L44: =SUM(L20:L27) -> 0 | M44: =SUM(M20:M27) -> 0 | N44: =SUM(N20:N27) -> 0 | O44: =SUM(O20:O27) -> 0 | P44: =SUM(P20:P27) -> 0 | Q44: =SUM(Q20:Q27) -> 0 | ... U44: =SUM(U20:U27) -> 0
B46: TOTAL | G46: =H46/W16 -> #DIV/0! | H46: =SUM(H20:H41) -> 0 | J46: =SUM(J20:J41) -> 0 | K46: =SUM(K20:K41) -> 0 | L46: =SUM(L20:L41) -> 0 | M46: =SUM(M20:M41) -> 0 | N46: =SUM(N20:N41) -> 0 | O46: =SUM(O20:O41) -> 0 | P46: =SUM(P20:P41) -> 0 | Q46: =SUM(Q20:Q41) -> 0 | ... U46: =SUM(U20:U41) -> 0 | W46: =SUM(J46:U46) -> 0
B48: COSTS | C48: Op Code | D48: Activity
B49: Log and Load | C49: 300/01 | D49: Logging
H50: TOTAL | J50: 45658 | K50: 45689 | L50: 45717 | M50: 45748 | N50: 45778 | O50: 45809 | P50: 45839 | Q50: 45870 | R50: 45901 | S50: 45931 | T50: 45962 | U50: 45992
G51: =H51/W16 -> #DIV/0! | H51: =SUM(J51:U51) -> 0 | J51: =J16*J13 -> 0 | K51: =K16*K13 -> 0 | L51: =L16*L13 -> 0 | M51: =M16*M13 -> 0 | N51: =N16*N13 -> 0 | O51: =O16*O13 -> 0 | P51: =P16*P13 -> 0 | Q51: =Q16*Q13 -> 0 | ... U51: =U16*U13 -> 0 | W51: =SUM(J51:U51) -> 0
B54: Log Transport
B55: Grade | C55: Op Code | D55: Activity | E55: Destination | F55: Destination | G55: Cost/t | H55: TOTAL | J55: 45658 | K55: 45689 | L55: 45717 | M55: 45748 | N55: 45778 | O55: 45809 | P55: 45839 | Q55: 45870 | R55: 45901 | S55: 45931 | T55: 45962 | U55: 45992
B56: P35 | C56: 300/02 | D56: Transport | E56: Domestic | H56: =SUM(J56:U56) -> 0 | J56: =IF($C20>0,(J$16*$C20)*$G56,0) -> 0 | K56: =IF($C20>0,(K$16*$C20)*$G56,0) -> 0 | L56: =IF($C20>0,(L$16*$C20)*$G56,0) -> 0 | M56: =IF($C20>0,(M$16*$C20)*$G56,0) -> 0 | N56: =IF($C20>0,(N$16*$C20)*$G56,0) -> 0 | O56: =IF($C20>0,(O$16*$C20)*$G56,0) -> 0 | P56: =IF($C20>0,(P$16*$C20)*$G56,0) -> 0 | Q56: =IF($C20>0,(Q$16*$C20)*$G56,0) -> 0 | ... U56: =IF($C20>0,(U$16*$C20)*$G56,0) -> 0
B57: S30 | C57: 300/02 | D57: Transport | E57: Domestic | H57: =SUM(J57:U57) -> 0 | J57: =IF($C21>0,(J$16*$C21)*$G57,0) -> 0 | K57: =IF($C21>0,(K$16*$C21)*$G57,0) -> 0 | L57: =IF($C21>0,(L$16*$C21)*$G57,0) -> 0 | M57: =IF($C21>0,(M$16*$C21)*$G57,0) -> 0 | N57: =IF($C21>0,(N$16*$C21)*$G57,0) -> 0 | O57: =IF($C21>0,(O$16*$C21)*$G57,0) -> 0 | P57: =IF($C21>0,(P$16*$C21)*$G57,0) -> 0 | Q57: =IF($C21>0,(Q$16*$C21)*$G57,0) -> 0 | ... U57: =IF($C21>0,(U$16*$C21)*$G57,0) -> 0
B58: S20 | C58: 300/02 | D58: Transport | E58: Domestic | H58: =SUM(J58:U58) -> 0 | J58: =IF($C22>0,(J$16*$C22)*$G58,0) -> 0 | K58: =IF($C22>0,(K$16*$C22)*$G58,0) -> 0 | L58: =IF($C22>0,(L$16*$C22)*$G58,0) -> 0 | M58: =IF($C22>0,(M$16*$C22)*$G58,0) -> 0 | N58: =IF($C22>0,(N$16*$C22)*$G58,0) -> 0 | O58: =IF($C22>0,(O$16*$C22)*$G58,0) -> 0 | P58: =IF($C22>0,(P$16*$C22)*$G58,0) -> 0 | Q58: =IF($C22>0,(Q$16*$C22)*$G58,0) -> 0 | ... U58: =IF($C22>0,(U$16*$C22)*$G58,0) -> 0
B59: Domestic Pulp | C59: 300/02 | D59: Transport | E59: Domestic | H59: =SUM(J59:U59) -> 0 | J59: =IF($C23>0,(J$16*$C23)*$G59,0) -> 0 | K59: =IF($C23>0,(K$16*$C23)*$G59,0) -> 0 | L59: =IF($C23>0,(L$16*$C23)*$G59,0) -> 0 | M59: =IF($C23>0,(M$16*$C23)*$G59,0) -> 0 | N59: =IF($C23>0,(N$16*$C23)*$G59,0) -> 0 | O59: =IF($C23>0,(O$16*$C23)*$G59,0) -> 0 | P59: =IF($C23>0,(P$16*$C23)*$G59,0) -> 0 | Q59: =IF($C23>0,(Q$16*$C23)*$G59,0) -> 0 | ... U59: =IF($C23>0,(U$16*$C23)*$G59,0) -> 0
B60: Eucalyptus | C60: 300/02 | D60: Transport | E60: Domestic | H60: =SUM(J60:U60) -> 0 | J60: =IF($C24>0,(J$16*$C24)*$G60,0) -> 0 | K60: =IF($C24>0,(K$16*$C24)*$G60,0) -> 0 | L60: =IF($C24>0,(L$16*$C24)*$G60,0) -> 0 | M60: =IF($C24>0,(M$16*$C24)*$G60,0) -> 0 | N60: =IF($C24>0,(N$16*$C24)*$G60,0) -> 0 | O60: =IF($C24>0,(O$16*$C24)*$G60,0) -> 0 | P60: =IF($C24>0,(P$16*$C24)*$G60,0) -> 0 | Q60: =IF($C24>0,(Q$16*$C24)*$G60,0) -> 0 | ... U60: =IF($C24>0,(U$16*$C24)*$G60,0) -> 0
B61: FW | C61: 300/02 | D61: Transport | E61: Domestic | H61: =SUM(J61:U61) -> 0 | J61: =IF($C25>0,(J$16*$C25)*$G61,0) -> 0 | K61: =IF($C25>0,(K$16*$C25)*$G61,0) -> 0 | L61: =IF($C25>0,(L$16*$C25)*$G61,0) -> 0 | M61: =IF($C25>0,(M$16*$C25)*$G61,0) -> 0 | N61: =IF($C25>0,(N$16*$C25)*$G61,0) -> 0 | O61: =IF($C25>0,(O$16*$C25)*$G61,0) -> 0 | P61: =IF($C25>0,(P$16*$C25)*$G61,0) -> 0 | Q61: =IF($C25>0,(Q$16*$C25)*$G61,0) -> 0 | ... U61: =IF($C25>0,(U$16*$C25)*$G61,0) -> 0
B62: Euc Pulp | C62: 300/02 | D62: Transport | E62: Domestic | H62: =SUM(J62:U62) -> 0 | J62: =IF($C26>0,(J$16*$C26)*$G62,0) -> 0 | K62: =IF($C26>0,(K$16*$C26)*$G62,0) -> 0 | L62: =IF($C26>0,(L$16*$C26)*$G62,0) -> 0 | M62: =IF($C26>0,(M$16*$C26)*$G62,0) -> 0 | N62: =IF($C26>0,(N$16*$C26)*$G62,0) -> 0 | O62: =IF($C26>0,(O$16*$C26)*$G62,0) -> 0 | P62: =IF($C26>0,(P$16*$C26)*$G62,0) -> 0 | Q62: =IF($C26>0,(Q$16*$C26)*$G62,0) -> 0 | ... U62: =IF($C26>0,(U$16*$C26)*$G62,0) -> 0
B63: Binwood | C63: 300/02 | D63: Transport | E63: Domestic | H63: =SUM(J63:U63) -> 0 | J63: =IF($C27>0,(J$16*$C27)*$G63,0) -> 0 | K63: =IF($C27>0,(K$16*$C27)*$G63,0) -> 0 | L63: =IF($C27>0,(L$16*$C27)*$G63,0) -> 0 | M63: =IF($C27>0,(M$16*$C27)*$G63,0) -> 0 | N63: =IF($C27>0,(N$16*$C27)*$G63,0) -> 0 | O63: =IF($C27>0,(O$16*$C27)*$G63,0) -> 0 | P63: =IF($C27>0,(P$16*$C27)*$G63,0) -> 0 | Q63: =IF($C27>0,(Q$16*$C27)*$G63,0) -> 0 | ... U63: =IF($C27>0,(U$16*$C27)*$G63,0) -> 0
B64: P40 | C64: 300/02 | D64: Transport | E64: AWG | H64: =SUM(J64:U64) -> 0 | J64: =IF($C28>0,(J$16*$C28)*$G64,0) -> 0 | K64: =IF($C28>0,(K$16*$C28)*$G64,0) -> 0 | L64: =IF($C28>0,(L$16*$C28)*$G64,0) -> 0 | M64: =IF($C28>0,(M$16*$C28)*$G64,0) -> 0 | N64: =IF($C28>0,(N$16*$C28)*$G64,0) -> 0 | O64: =IF($C28>0,(O$16*$C28)*$G64,0) -> 0 | P64: =IF($C28>0,(P$16*$C28)*$G64,0) -> 0 | Q64: =IF($C28>0,(Q$16*$C28)*$G64,0) -> 0 | ... U64: =IF($C28>0,(U$16*$C28)*$G64,0) -> 0
B65: P30 | C65: 300/02 | D65: Transport | E65: AWG | H65: =SUM(J65:U65) -> 0 | J65: =IF($C29>0,(J$16*$C29)*$G65,0) -> 0 | K65: =IF($C29>0,(K$16*$C29)*$G65,0) -> 0 | L65: =IF($C29>0,(L$16*$C29)*$G65,0) -> 0 | M65: =IF($C29>0,(M$16*$C29)*$G65,0) -> 0 | N65: =IF($C29>0,(N$16*$C29)*$G65,0) -> 0 | O65: =IF($C29>0,(O$16*$C29)*$G65,0) -> 0 | P65: =IF($C29>0,(P$16*$C29)*$G65,0) -> 0 | Q65: =IF($C29>0,(Q$16*$C29)*$G65,0) -> 0 | ... U65: =IF($C29>0,(U$16*$C29)*$G65,0) -> 0
B66: AO | C66: 300/02 | D66: Transport | E66: AWG | H66: =SUM(J66:U66) -> 0 | J66: =IF($C30>0,(J$16*$C30)*$G66,0) -> 0 | K66: =IF($C30>0,(K$16*$C30)*$G66,0) -> 0 | L66: =IF($C30>0,(L$16*$C30)*$G66,0) -> 0 | M66: =IF($C30>0,(M$16*$C30)*$G66,0) -> 0 | N66: =IF($C30>0,(N$16*$C30)*$G66,0) -> 0 | O66: =IF($C30>0,(O$16*$C30)*$G66,0) -> 0 | P66: =IF($C30>0,(P$16*$C30)*$G66,0) -> 0 | Q66: =IF($C30>0,(Q$16*$C30)*$G66,0) -> 0 | ... U66: =IF($C30>0,(U$16*$C30)*$G66,0) -> 0
B67: A | C67: 300/02 | D67: Transport | E67: AWG | H67: =SUM(J67:U67) -> 0 | J67: =IF($C31>0,(J$16*$C31)*$G67,0) -> 0 | K67: =IF($C31>0,(K$16*$C31)*$G67,0) -> 0 | L67: =IF($C31>0,(L$16*$C31)*$G67,0) -> 0 | M67: =IF($C31>0,(M$16*$C31)*$G67,0) -> 0 | N67: =IF($C31>0,(N$16*$C31)*$G67,0) -> 0 | O67: =IF($C31>0,(O$16*$C31)*$G67,0) -> 0 | P67: =IF($C31>0,(P$16*$C31)*$G67,0) -> 0 | Q67: =IF($C31>0,(Q$16*$C31)*$G67,0) -> 0 | ... U67: =IF($C31>0,(U$16*$C31)*$G67,0) -> 0
... B77: Spare grade | C77: 300/02 | D77: Transport | E77: AWG | H77: =SUM(J77:U77) -> 0 | J77: =IF($C41>0,(J$16*$C41)*$G77,0) -> 0 | K77: =IF($C41>0,(K$16*$C41)*$G77,0) -> 0 | L77: =IF($C41>0,(L$16*$C41)*$G77,0) -> 0 | M77: =IF($C41>0,(M$16*$C41)*$G77,0) -> 0 | N77: =IF($C41>0,(N$16*$C41)*$G77,0) -> 0 | O77: =IF($C41>0,(O$16*$C41)*$G77,0) -> 0 | P77: =IF($C41>0,(P$16*$C41)*$G77,0) -> 0 | Q77: =IF($C41>0,(Q$16*$C41)*$G77,0) -> 0 | ... U77: =IF($C41>0,(U$16*$C41)*$G77,0) -> 0
G78: =H78/W16 -> #DIV/0! | H78: =SUM(H56:H77) -> 0 | J78: =SUM(J56:J77) -> 0 | K78: =SUM(K56:K77) -> 0 | L78: =SUM(L56:L77) -> 0 | M78: =SUM(M56:M77) -> 0 | N78: =SUM(N56:N77) -> 0 | O78: =SUM(O56:O77) -> 0 | P78: =SUM(P56:P77) -> 0 | Q78: =SUM(Q56:Q77) -> 0 | ... U78: =SUM(U56:U77) -> 0 | W78: =SUM(J78:U78) -> 0
B80: Non-docket costs
B81: Operation | C81: Op Code | D81: Activity | E81: Resource | F81: Product | G81: Unit Rate | H81: TOTAL | J81: 45658 | K81: 45689 | L81: 45717 | M81: 45748 | N81: 45778 | O81: 45809 | P81: 45839 | Q81: 45870 | R81: 45901 | S81: 45931 | T81: 45962 | U81: 45992
B82: Tracking | C82: 300/04 | D82: Logging | H82: =SUM(J82:U82) -> 0
B83: Logging Machinery establishment/transportation | C83: 300/06 | D83: Logging | E83: 699 | F83: 3675 | H83: =SUM(J83:U83) -> 0
B84: Road control | C84: 300/16 | D84: Logging | E84: 699 | F84: 3691 | H84: =SUM(J84:U84) -> 0
B85: Powerline costs | C85: 300/17 | D85: Logging | E85: 699 | F85: 3677 | H85: =SUM(J85:U85) -> 0
B86: Fencing & gate construction | C86: 721 | D86: Logging | E86: 699 | F86: 3671 | H86: =SUM(J86:U86) -> 0
B87: Deadman | C87: 300/18 | D87: Logging | E87: 699 | F87: 3669 | H87: =SUM(J87:U87) -> 0
B88: Two-stage | C88: 300/19 | D88: Logging | E88: 699 | F88: 3665 | H88: =SUM(J88:U88) -> 0
B89: Harvest Planning | C89: 300/09 | D89: Logging | E89: 699 | F89: 3963 | H89: =SUM(J89:U89) -> 0
B90: Roading machinery establishment/transportation | C90: 300/07 | D90: Infrastructure | H90: =SUM(J90:U90) -> 0
B91: New Road Metalled or sealed | C91: 720 | D91: Infrastructure | H91: =SUM(J91:U91) -> 0 | J91: =J115 -> 0 | K91: =K115 -> 0 | L91: =L115 -> 0 | M91: =M115 -> 0 | N91: =N115 -> 0 | O91: =O115 -> 0 | P91: =P115 -> 0 | Q91: =Q115 -> 0 | ... U91: =U115 -> 0
B92: Upgrade Road metalled or sealed | C92: 720 | D92: Infrastructure | H92: =SUM(J92:U92) -> 0 | J92: =J114 -> 0 | K92: =K114 -> 0 | L92: =L114 -> 0 | M92: =M114 -> 0 | N92: =N114 -> 0 | O92: =O114 -> 0 | P92: =P114 -> 0 | Q92: =Q114 -> 0 | ... U92: =U114 -> 0
B93: Other infrastructure | C93: 720 | D93: Infrastructure | H93: =SUM(J93:U93) -> 0 | J93: =J118 -> 0 | K93: =K118 -> 0 | L93: =L118 -> 0 | M93: =M118 -> 0 | N93: =N118 -> 0 | O93: =O118 -> 0 | P93: =P118 -> 0 | Q93: =Q118 -> 0 | ... U93: =U118 -> 0
B94: Skid construction | C94: 300/05 | D94: Infrastructure | H94: =SUM(J94:U94) -> 0 | J94: =J119 -> 0 | K94: =K119 -> 0 | L94: =L119 -> 0 | M94: =M119 -> 0 | N94: =N119 -> 0 | O94: =O119 -> 0 | P94: =P119 -> 0 | Q94: =Q119 -> 0 | ... U94: =U119 -> 0
B95: Pad construction | C95: 300/05 | D95: Infrastructure | H95: =SUM(J95:U95) -> 0 | J95: =J120 -> 0 | K95: =K120 -> 0 | L95: =L120 -> 0 | M95: =M120 -> 0 | N95: =N120 -> 0 | O95: =O120 -> 0 | P95: =P120 -> 0 | Q95: =Q120 -> 0 | ... U95: =U120 -> 0
B96: Maintenance Forest Road | C96: 305 | D96: Maintenance | H96: =SUM(J96:U96) -> 0
B97: Maintenance Public Road | C97: 306 | D97: Maintenance | H97: =SUM(J97:U97) -> 0
B98: Skid/Pad maintenance | C98: 300/14 | D98: Post harvest costs | H98: =SUM(J98:U98) -> 0
B99: Post-harvest clean-up | C99: 300/10 | D99: Post harvest costs | H99: =SUM(J99:U99) -> 0
B100: Health and safety and Auditing | C100: 300/11 | D100: Indirect costs | H100: =SUM(J100:U100) -> 0
B101: Weighbridge | C101: 300/03 | D101: Indirect costs | G101: =H101/$W$16 -> #DIV/0! | H101: =SUM(J101:U101) -> 0
B102: Environmental monitoring/consents | C102: 330/04 | D102: Indirect costs | E102: 365 | H102: =SUM(J102:U102) -> 0
B103: Forest levy | C103: 300/08 | D103: Mgmt/Admin | E103: 338 | G103: 0.33 | H103: =SUM(J103:U103) -> 0 | J103: =$G$103*J16 -> 0 | K103: =$G$103*K16 -> 0 | L103: =$G$103*L16 -> 0 | M103: =$G$103*M16 -> 0 | N103: =$G$103*N16 -> 0 | O103: =$G$103*O16 -> 0 | P103: =$G$103*P16 -> 0 | Q103: =$G$103*Q16 -> 0 | ... U103: =$G$103*U16 -> 0
B104: Insurance Payment protection (domestic sales only) | C104: 351 | D104: Mgmt/Admin | E104: 324 | G104: 0.0016 | H104: =SUM(J104:U104) -> 0 | J104: =$G$104*J46/100 -> 0 | K104: =$G$104*K46/100 -> 0 | L104: =$G$104*L46/100 -> 0 | M104: =$G$104*M46/100 -> 0 | N104: =$G$104*N46/100 -> 0 | O104: =$G$104*O46/100 -> 0 | P104: =$G$104*P46/100 -> 0 | Q104: =$G$104*Q46/100 -> 0 | ... U104: =$G$104*U46/100 -> 0
B105: Harvest management fee | C105: 300/12 | D105: Mgmt/Admin | G105: 3.75 | H105: =SUM(J105:U105) -> 0 | J105: =$G$105*J16 -> 0 | K105: =$G$105*K16 -> 0 | L105: =$G$105*L16 -> 0 | M105: =$G$105*M16 -> 0 | N105: =$G$105*N16 -> 0 | O105: =$G$105*O16 -> 0 | P105: =$G$105*P16 -> 0 | Q105: =$G$105*Q16 -> 0 | ... U105: =$G$105*U16 -> 0
B107: Total non-docket costs | G107: =H107/B127 -> #DIV/0! | H107: =SUM(H82:H105) -> 0 | J107: =SUM(J82:J105) -> 0 | K107: =SUM(K82:K105) -> 0 | L107: =SUM(L82:L105) -> 0 | M107: =SUM(M82:M105) -> 0 | N107: =SUM(N82:N105) -> 0 | O107: =SUM(O82:O105) -> 0 | P107: =SUM(P82:P105) -> 0 | Q107: =SUM(Q82:Q105) -> 0 | ... U107: =SUM(U82:U105) -> 0
B109: Total Costs | H109: =H51+H78+H107 -> 0 | J109: =J51+J78+J107 -> 0 | K109: =K51+K78+K107 -> 0 | L109: =L51+L78+L107 -> 0 | M109: =M51+M78+M107 -> 0 | N109: =N51+N78+N107 -> 0 | O109: =O51+O78+O107 -> 0 | P109: =P51+P78+P107 -> 0 | Q109: =Q51+Q78+Q107 -> 0 | ... U109: =U51+U78+U107 -> 0 | W109: =SUM(J109:U109) -> 0
B111: Net Harvest Total | H111: =H46-H109 -> 0 | J111: =J46-J109 -> 0 | K111: =K46-K109 -> 0 | L111: =L46-L109 -> 0 | M111: =M46-M109 -> 0 | N111: =N46-N109 -> 0 | O111: =O46-O109 -> 0 | P111: =P46-P109 -> 0 | Q111: =Q46-Q109 -> 0 | ... U111: =U46-U109 -> 0 | W111: =SUM(J111:U111) -> 0
B113: Engineering | C113: Op Code | D113: Activity | E113: Unit | F113: Vol | G113: Unit Rate | J113: Metres constructed or number of skids/pads
B114: Existing road upgrade-Substantially metalled or sealed | C114: 720 | D114: Infrastructure | E114: cost/m | G114: =IFERROR(H114/F114,0) -> 0 | H114: =SUM(J114:U114) -> 0
B115: New road construction-Substantially metalled or sealed | C115: 720 | D115: Infrastructure | E115: cost/m | G115: =IFERROR(H115/F115,0) -> 0 | H115: =SUM(J115:U115) -> 0
B116: Existing road upgrade-Partially metalled or sealed | C116: 720 | D116: Infrastructure | E116: cost/m | G116: =IFERROR(H116/F116,0) -> 0 | H116: =SUM(J116:U116) -> 0
B117: New road construction-Partially metalled or sealed | C117: 720 | D117: Infrastructure | E117: cost/m | G117: =IFERROR(H117/F117,0) -> 0 | H117: =SUM(J117:U117) -> 0
B118: Other infrastructure | C118: 720 | D118: Infrastructure | E118: cost/unit | G118: =IFERROR(H118/F118,0) -> 0 | H118: =SUM(J118:U118) -> 0
...

Sheet Whakatikei Actual
C1: ='Whakatikei Budget'!C1 -> 2025 | D1: Input
B2: ='Whakatikei Budget'!B2 -> Whakatikei | H2: Estimated Tonnes (ha)
B3: PRODUCTION & RATE | G3: Total Monthly Working Days | I3: =IF(NOT(ISBLANK(J5)), J5, IF(NOT(ISBLANK(J8)), J8, IF(NOT(ISBLANK(J11)), J11, 0)))+IF(NOT(ISBLANK(K5)), K5, IF(NOT(ISBLANK(K8)), K8, IF(NOT(ISBLANK(K11)), K11, 0)))+IF(NOT(ISBLANK(L5)), L5, IF(NOT(ISBLANK(L8)), L8, IF(NOT(ISBLANK(L11)), L11, 0)))+IF(NOT(ISBLANK(M5)), M5, IF(NOT(ISBLANK(M8)), M8, IF(NOT(ISBLANK(M11)), M11, 0)))+IF(NOT(ISBLANK(N5)), N5, IF(NOT(ISBLANK(N8)), N8, IF(NOT(ISBLANK(N11)), N11, 0)))+IF(NOT(ISBLANK(O5)), O5, IF(NOT(ISBLANK(O8)), O8, IF(NOT(ISBLANK(O11)), O11, 0)))+IF(NOT(ISBLANK(P5)), P5, IF(NOT(ISBLANK(P8)), P8, IF(NOT(ISBLANK(P11)), P11, 0)))+IF(NOT(ISBLANK(Q5)), Q5, IF(NOT(ISBLANK(Q8)), Q8, IF(NOT(ISBLANK(Q11)), Q11, 0)))+IF(NOT(ISBLANK(R5)), R5, IF(NOT(ISBLANK(R8)), R8, IF(NOT(ISBLANK(R11)), R11, 0)))+IF(NOT(ISBLANK(S5)), S5, IF(NOT(ISBLANK(S8)), S8, IF(NOT(ISBLANK(S11)), S11, 0)))+IF(NOT(ISBLANK(T5)), T5, IF(NOT(ISBLANK(T8)), T8, IF(NOT(ISBLANK(T11)), T11, 0)))+IF(NOT(ISBLANK(U5)), U5, IF(NOT(ISBLANK(U8)), U8, IF(NOT(ISBLANK(U11)), U11, 0))) -> 0 | J3: 45658 | K3: 45689 | L3: 45717 | M3: 45748 | N3: 45778 | O3: 45809 | P3: 45839 | Q3: 45870 | R3: 45901 | S3: 45931 | T3: 45962 | U3: 45992
G4: Roadline | H4: Total production | I4: =IFERROR(SUM(J4:U4)/$W$16,0) -> 0
H5: Days worked
H6: Harvesting Rate
G7: Groundbase | H7: Total production | I7: =IFERROR(SUM(J7:U7)/$W$16,0) -> 0
H8: Days worked
H9: Harvesting Rate
G10: Hauler | H10: Total production | I10: =IFERROR(SUM(J10:U10)/$W$16,0) -> 0
H11: Days worked
H12: Harvesting Rate
G13: Total | H13: Harvested Tonnes | I13: =SUM(I4:I12) -> 0 | J13: =J4+J7+J10 -> 0 | K13: =K4+K7+K10 -> 0 | L13: =L4+L7+L10 -> 0 | M13: =M4+M7+M10 -> 0 | N13: =N4+N7+N10 -> 0 | O13: =O4+O7+O10 -> 0 | P13: =P4+P7+P10 -> 0 | Q13: =Q4+Q7+Q10 -> 0 | ... U13: =U4+U7+U10 -> 0 | W13: =I3 -> 0 | X13: Monthly Working Days
H14: Variance Tones | J14: =J13-J16 -> 0 | K14: =K13-K16 -> 0 | L14: =L13-L16 -> 0 | M14: =M13-M16 -> 0 | N14: =N13-N16 -> 0 | O14: =O13-O16 -> 0 | P14: =P13-P16 -> 0 | Q14: =Q13-Q16 -> 0 | ... U14: =U13-U16 -> 0 | W14: =SUM(J14:U14) -> 0 | X14: =H14 -> Variance Tones
G15: Total | H15: Hectare (ha) | J15: =IFERROR(J13/$I$2,0) -> 0 | K15: =IFERROR(K13/$I$2,0) -> 0 | L15: =IFERROR(L13/$I$2,0) -> 0 | M15: =IFERROR(M13/$I$2,0) -> 0 | N15: =IFERROR(N13/$I$2,0) -> 0 | O15: =IFERROR(O13/$I$2,0) -> 0 | P15: =IFERROR(P13/$I$2,0) -> 0 | Q15: =IFERROR(Q13/$I$2,0) -> 0 | ... U15: =IFERROR(U13/$I$2,0) -> 0 | W15: =SUM(J15:U15) -> 0 | X15: =H15 -> Hectare (ha)
G16: Total | H16: Invoice Tonnes | J16: =Volume_3!D27 -> 0 | K16: =Volume_3!H27 -> 0 | L16: =Volume_3!L27 -> 0 | M16: =Volume_3!P27 -> 0 | N16: =Volume_3!T27 -> 0 | O16: =Volume_3!X27 -> 0 | P16: =Volume_3!AB27 -> 0 | Q16: =Volume_3!AF27 -> 0 | R16: =Volume_3!AJ27 -> 0 | S16: =Volume_3!AN27 -> 0 | T16: =Volume_3!AR27 -> 0 | U16: =Volume_3!AV27 -> 0 | W16: =SUM(J16:U16) -> 0 | X16: =H16 -> Invoice Tonnes
B18: REVENUE
B19: Grade | C19: Grade Mix % | D19: Conversion Rate | E19: Sale unit | F19: Sale unit/t | G19: Price/Unit | H19: TOTAL | J19: 45658 | K19: 45689 | L19: 45717 | M19: 45748 | N19: 45778 | O19: 45809 | P19: 45839 | Q19: 45870 | R19: 45901 | S19: 45931 | T19: 45962 | U19: 45992
B20: P35 | E20: Tonnes | H20: =SUM(J20:U20) -> 0 | J20: =Volume_3!G4 -> 0 | K20: =Volume_3!K4 -> 0 | L20: =Volume_3!O4 -> 0 | M20: =Volume_3!S4 -> 0 | N20: =Volume_3!W4 -> 0 | O20: =Volume_3!AA4 -> 0 | P20: =Volume_3!AE4 -> 0 | Q20: =Volume_3!AI4 -> 0 | R20: =Volume_3!AM4 -> 0 | S20: =Volume_3!AQ4 -> 0 | T20: =Volume_3!AU4 -> 0 | U20: =Volume_3!AY4 -> 0
B21: S30 | E21: Tonnes | H21: =SUM(J21:U21) -> 0 | J21: =Volume_3!G5 -> 0 | K21: =Volume_3!K5 -> 0 | L21: =Volume_3!O5 -> 0 | M21: =Volume_3!S5 -> 0 | N21: =Volume_3!W5 -> 0 | O21: =Volume_3!AA5 -> 0 | P21: =Volume_3!AE5 -> 0 | Q21: =Volume_3!AI5 -> 0 | R21: =Volume_3!AM5 -> 0 | S21: =Volume_3!AQ5 -> 0 | T21: =Volume_3!AU5 -> 0 | U21: =Volume_3!AY5 -> 0
B22: S20 | E22: Tonnes | H22: =SUM(J22:U22) -> 0 | J22: =Volume_3!G6 -> 0 | K22: =Volume_3!K6 -> 0 | L22: =Volume_3!O6 -> 0 | M22: =Volume_3!S6 -> 0 | N22: =Volume_3!W6 -> 0 | O22: =Volume_3!AA6 -> 0 | P22: =Volume_3!AE6 -> 0 | Q22: =Volume_3!AI6 -> 0 | R22: =Volume_3!AM6 -> 0 | S22: =Volume_3!AQ6 -> 0 | T22: =Volume_3!AU6 -> 0 | U22: =Volume_3!AY6 -> 0
B23: Domestic Pulp | E23: Tonnes | H23: =SUM(J23:U23) -> 0 | J23: =Volume_3!G7 -> 0 | K23: =Volume_3!K7 -> 0 | L23: =Volume_3!O7 -> 0 | M23: =Volume_3!S7 -> 0 | N23: =Volume_3!W7 -> 0 | O23: =Volume_3!AA7 -> 0 | P23: =Volume_3!AE7 -> 0 | Q23: =Volume_3!AI7 -> 0 | R23: =Volume_3!AM7 -> 0 | S23: =Volume_3!AQ7 -> 0 | T23: =Volume_3!AU7 -> 0 | U23: =Volume_3!AY7 -> 0
B24: Eucalyptus | E24: Tonnes | H24: =SUM(J24:U24) -> 0 | J24: =Volume_3!G8 -> 0 | K24: =Volume_3!K8 -> 0 | L24: =Volume_3!O8 -> 0 | M24: =Volume_3!S8 -> 0 | N24: =Volume_3!W8 -> 0 | O24: =Volume_3!AA8 -> 0 | P24: =Volume_3!AE8 -> 0 | Q24: =Volume_3!AI8 -> 0 | R24: =Volume_3!AM8 -> 0 | S24: =Volume_3!AQ8 -> 0 | T24: =Volume_3!AU8 -> 0 | U24: =Volume_3!AY8 -> 0
B25: FW | E25: Tonnes | H25: =SUM(J25:U25) -> 0 | J25: =Volume_3!G9 -> 0 | K25: =Volume_3!K9 -> 0 | L25: =Volume_3!O9 -> 0 | M25: =Volume_3!S9 -> 0 | N25: =Volume_3!W9 -> 0 | O25: =Volume_3!AA9 -> 0 | P25: =Volume_3!AE9 -> 0 | Q25: =Volume_3!AI9 -> 0 | R25: =Volume_3!AM9 -> 0 | S25: =Volume_3!AQ9 -> 0 | T25: =Volume_3!AU9 -> 0 | U25: =Volume_3!AY9 -> 0
B26: Euc Pulp | E26: Tonnes | H26: =SUM(J26:U26) -> 0 | J26: =Volume_3!G10 -> 0 | K26: =Volume_3!K10 -> 0 | L26: =Volume_3!O10 -> 0 | M26: =Volume_3!S10 -> 0 | N26: =Volume_3!W10 -> 0 | O26: =Volume_3!AA10 -> 0 | P26: =Volume_3!AE10 -> 0 | Q26: =Volume_3!AI10 -> 0 | R26: =Volume_3!AM10 -> 0 | S26: =Volume_3!AQ10 -> 0 | T26: =Volume_3!AU10 -> 0 | U26: =Volume_3!AY10 -> 0
B27: Binwood | E27: Tonnes | H27: =SUM(J27:U27) -> 0 | J27: =Volume_3!G11 -> 0 | K27: =Volume_3!K11 -> 0 | L27: =Volume_3!O11 -> 0 | M27: =Volume_3!S11 -> 0 | N27: =Volume_3!W11 -> 0 | O27: =Volume_3!AA11 -> 0 | P27: =Volume_3!AE11 -> 0 | Q27: =Volume_3!AI11 -> 0 | R27: =Volume_3!AM11 -> 0 | S27: =Volume_3!AQ11 -> 0 | T27: =Volume_3!AU11 -> 0 | U27: =Volume_3!AY11 -> 0
B28: Spare Grade | E28: Tonnes | H28: =SUM(J28:U28) -> 0 | J28: =Volume_3!G12 -> 0 | K28: =Volume_3!K12 -> 0 | L28: =Volume_3!O12 -> 0 | M28: =Volume_3!S12 -> 0 | N28: =Volume_3!W12 -> 0 | O28: =Volume_3!AA12 -> 0 | P28: =Volume_3!AE12 -> 0 | Q28: =Volume_3!AI12 -> 0 | R28: =Volume_3!AM12 -> 0 | S28: =Volume_3!AQ12 -> 0 | T28: =Volume_3!AU12 -> 0 | U28: =Volume_3!AY12 -> 0
B29: P40 | E29: JAS | H29: =SUM(J29:U29) -> 0 | J29: =Volume_3!G13 -> 0 | K29: =Volume_3!K13 -> 0 | L29: =Volume_3!O13 -> 0 | M29: =Volume_3!S13 -> 0 | N29: =Volume_3!W13 -> 0 | O29: =Volume_3!AA13 -> 0 | P29: =Volume_3!AE13 -> 0 | Q29: =Volume_3!AI13 -> 0 | R29: =Volume_3!AM13 -> 0 | S29: =Volume_3!AQ13 -> 0 | T29: =Volume_3!AU13 -> 0 | U29: =Volume_3!AY13 -> 0
B30: P30 | E30: JAS | H30: =SUM(J30:U30) -> 0 | J30: =Volume_3!G14 -> 0 | K30: =Volume_3!K14 -> 0 | L30: =Volume_3!O14 -> 0 | M30: =Volume_3!S14 -> 0 | N30: =Volume_3!W14 -> 0 | O30: =Volume_3!AA14 -> 0 | P30: =Volume_3!AE14 -> 0 | Q30: =Volume_3!AI14 -> 0 | R30: =Volume_3!AM14 -> 0 | S30: =Volume_3!AQ14 -> 0 | T30: =Volume_3!AU14 -> 0 | U30: =Volume_3!AY14 -> 0
B31: AO | E31: JAS | H31: =SUM(J31:U31) -> 0 | J31: =Volume_3!G15 -> 0 | K31: =Volume_3!K15 -> 0 | L31: =Volume_3!O15 -> 0 | M31: =Volume_3!S15 -> 0 | N31: =Volume_3!W15 -> 0 | O31: =Volume_3!AA15 -> 0 | P31: =Volume_3!AE15 -> 0 | Q31: =Volume_3!AI15 -> 0 | R31: =Volume_3!AM15 -> 0 | S31: =Volume_3!AQ15 -> 0 | T31: =Volume_3!AU15 -> 0 | U31: =Volume_3!AY15 -> 0
... B41: Euc K | E41: JAS | H41: =SUM(J41:U41) -> 0 | J41: =Volume_3!G25 -> 0 | K41: =Volume_3!K25 -> 0 | L41: =Volume_3!O25 -> 0 | M41: =Volume_3!S25 -> 0 | N41: =Volume_3!W25 -> 0 | O41: =Volume_3!AA25 -> 0 | P41: =Volume_3!AE25 -> 0 | Q41: =Volume_3!AI25 -> 0 | R41: =Volume_3!AM25 -> 0 | S41: =Volume_3!AQ25 -> 0 | T41: =Volume_3!AU25 -> 0 | U41: =Volume_3!AY25 -> 0
C42: =SUM(C20:C41) -> 0
B43: Export Sales | C43: =SUMIF(E20:E41,"JAS",C20:C41) -> 0 | H43: =SUM(J43:U43) -> 0 | J43: =SUM(J28:J41) -> 0 | K43: =SUM(K28:K41) -> 0 | L43: =SUM(L28:L41) -> 0 | M43: =SUM(M28:M41) -> 0 | N43: =SUM(N28:N41) -> 0 | O43: =SUM(O28:O41) -> 0 | P43: =SUM(P28:P41) -> 0 | Q43: =SUM(Q28:Q41) -> 0 | ... U43: =SUM(U28:U41) -> 0
B44: Domestic Sales | C44: =SUMIF(E20:E41,"Tonnes",C20:C41) -> 0 | H44: =SUM(J44:U44) -> 0 | J44: =SUM(J20:J27) -> 0 | K44: =SUM(K20:K27) -> 0 | L44: =SUM(L20:L27) -> 0 | M44: =SUM(M20:M27) -> 0 | N44: =SUM(N20:N27) -> 0 | O44: =SUM(O20:O27) -> 0 | P44: =SUM(P20:P27) -> 0 | Q44: =SUM(Q20:Q27) -> 0 | ... U44: =SUM(U20:U27) -> 0
B46: TOTAL | G46: =H46/W16 -> #DIV/0! | H46: =SUM(H20:H41) -> 0 | J46: =SUM(J20:J41) -> 0 | K46: =SUM(K20:K41) -> 0 | L46: =SUM(L20:L41) -> 0 | M46: =SUM(M20:M41) -> 0 | N46: =SUM(N20:N41) -> 0 | O46: =SUM(O20:O41) -> 0 | P46: =SUM(P20:P41) -> 0 | Q46: =SUM(Q20:Q41) -> 0 | ... U46: =SUM(U20:U41) -> 0 | W46: =SUM(J46:U46) -> 0
B48: COSTS | C48: Op Code | D48: Activity
B49: Log and Load | C49: 300/01 | D49: Logging
H50: TOTAL | J50: 45658 | K50: 45689 | L50: 45717 | M50: 45748 | N50: 45778 | O50: 45809 | P50: 45839 | Q50: 45870 | R50: 45901 | S50: 45931 | T50: 45962 | U50: 45992
G51: =H51/W16 -> #DIV/0! | H51: =SUM(J51:U51) -> 0 | W51: =SUM(J51:U51) -> 0
B54: Log Transport
B55: Grade | C55: Op Code | D55: Activity | E55: Destination | F55: Destination | G55: Cost/t | H55: TOTAL | J55: 45658 | K55: 45689 | L55: 45717 | M55: 45748 | N55: 45778 | O55: 45809 | P55: 45839 | Q55: 45870 | R55: 45901 | S55: 45931 | T55: 45962 | U55: 45992
B56: P35 | C56: 300/02 | D56: Transport | E56: Domestic | F56: Katikati | G56: 14.74 | H56: =SUM(J56:U56) -> 0
B57: S30 | C57: 300/02 | D57: Transport | E57: Domestic | F57: Thames | G57: 17 | H57: 0
B58: S20 | C58: 300/02 | D58: Transport | E58: Domestic | G58: 14.19 | H58: =SUM(J58:U58) -> 0
B59: Domestic Pulp | C59: 300/02 | D59: Transport | E59: Domestic | F59: Oji FS | G59: 36.54 | H59: =SUM(J59:U59) -> 0
B60: Eucalyptus | C60: 300/02 | D60: Transport | E60: Domestic | F60: Oji FS | G60: 36.54 | H60: =SUM(J60:U60) -> 0
B61: FW | C61: 300/02 | D61: Transport | E61: Domestic | H61: =SUM(J61:U61) -> 0
B62: Euc Pulp | C62: 300/02 | D62: Transport | E62: Domestic | H62: =SUM(J62:U62) -> 0
B63: Binwood | C63: 300/02 | D63: Transport | E63: Domestic | H63: =SUM(J63:U63) -> 0
B64: P40 | C64: 300/02 | D64: Transport | E64: AWG | F64: Tauranga | G64: 24.13 | H64: =SUM(J64:U64) -> 0
B65: P30 | C65: 300/02 | D65: Transport | E65: AWG | F65: Tauranga | G65: 24.13 | H65: =SUM(J65:U65) -> 0
B66: AO | C66: 300/02 | D66: Transport | E66: AWG | F66: Tauranga | G66: 24.13 | H66: =SUM(J66:U66) -> 0
B67: A | C67: 300/02 | D67: Transport | E67: AWG | F67: Tauranga | G67: 24.13 | H67: =SUM(J67:U67) -> 0
B68: K | C68: 300/02 | D68: Transport | E68: AWG | F68: Tauranga | G68: 24.13 | H68: =SUM(J68:U68) -> 0
B69: KI | C69: 300/02 | D69: Transport | E69: AWG | F69: Tauranga | G69: 24.13 | H69: =SUM(J69:U69) -> 0
B70: KI stub | C70: 300/02 | D70: Transport | E70: AWG | F70: Tauranga | G70: 24.13 | H70: =SUM(J70:U70) -> 0
B71: KIS | C71: 300/02 | D71: Transport | E71: AWG | F71: Tauranga | G71: 24.13 | H71: =SUM(J71:U71) -> 0
B72: CF+ | C72: 300/02 | D72: Transport | E72: AWG | F72: Tauranga | G72: 24.13 | H72: =SUM(J72:U72) -> 0
B73: CF- | C73: 300/02 | D73: Transport | E73: AWG | F73: Tauranga | G73: 24.13 | H73: =SUM(J73:U73) -> 0
B74: CM | C74: 300/02 | D74: Transport | E74: AWG | F74: Tauranga | G74: 24.13 | H74: =SUM(J74:U74) -> 0
B75: Euc A | C75: 300/02 | D75: Transport | H75: =SUM(J75:U75) -> 0
B76: Euc K | C76: 300/02 | D76: Transport | H76: =SUM(J76:U76) -> 0
B77: Spare grade | C77: 300/02 | D77: Transport | H77: =SUM(J77:U77) -> 0
G78: =H78/W16 -> #DIV/0! | H78: =SUM(H56:H77) -> 0 | W78: =SUM(J78:U78) -> 0
B80: Non-docket costs
B81: Operation | C81: Op Code | D81: Activity | E81: Resource | F81: Product | G81: Destination | H81: TOTAL | J81: 45658 | K81: 45689 | L81: 45717 | M81: 45748 | N81: 45778 | O81: 45809 | P81: 45839 | Q81: 45870 | R81: 45901 | S81: 45931 | T81: 45962 | U81: 45992
B82: Tracking | C82: 300/04 | D82: Logging | H82: =SUM(J82:U82) -> 0
B83: Logging Machinery establishment/transportation | C83: 300/06 | D83: Logging | E83: 699 | F83: 3675 | H83: =SUM(J83:U83) -> 0
B84: Road control | C84: 300/16 | D84: Logging | E84: 699 | F84: 3691 | H84: =SUM(J84:U84) -> 0
B85: Powerline costs | C85: 300/17 | D85: Logging | E85: 699 | F85: 3677 | H85: =SUM(J85:U85) -> 0
B86: Fencing & gate construction | C86: 721 | D86: Logging | E86: 699 | F86: 3671 | H86: =SUM(J86:U86) -> 0
B87: Deadman | C87: 300/18 | D87: Logging | E87: 699 | F87: 3669 | H87: =SUM(J87:U87) -> 0
B88: Two-stage | C88: 300/19 | D88: Logging | E88: 699 | F88: 3665 | H88: =SUM(J88:U88) -> 0
B89: Harvest Planning | C89: 300/09 | D89: Logging | E89: 699 | F89: 3963 | H89: =SUM(J89:U89) -> 0
B90: Roading machinery establishment/transportation | C90: 300/07 | D90: Infrastructure | H90: =SUM(J90:U90) -> 0
B91: New Road Metalled or sealed | C91: 720 | D91: Infrastructure | H91: =SUM(J91:U91) -> 0 | J91: =J115 -> 0 | K91: =K115 -> 0 | L91: =L115 -> 0 | M91: =M115 -> 0 | N91: =N115 -> 0 | O91: =O115 -> 0 | P91: =P115 -> 0 | Q91: =Q115 -> 0 | ... U91: =U115 -> 0
B92: Upgrade Road metalled or sealed | C92: 720 | D92: Infrastructure | H92: =SUM(J92:U92) -> 11115 | L92: 11115
B93: Other infrastructure | C93: 720 | D93: Infrastructure | H93: =SUM(J93:U93) -> 0
B94: Skid construction | C94: 300/05 | D94: Infrastructure | H94: =SUM(J94:U94) -> 0 | J94: =J119 -> 0 | K94: =K119 -> 0 | L94: =L119 -> 0 | M94: =M119 -> 0 | N94: =N119 -> 0 | O94: =O119 -> 0 | P94: =P119 -> 0 | Q94: =Q119 -> 0 | ... U94: =U119 -> 0
B95: Pad construction | C95: 300/05 | D95: Infrastructure | H95: =SUM(J95:U95) -> 0 | J95: =J120 -> 0 | K95: =K120 -> 0 | L95: =L120 -> 0 | M95: =M120 -> 0 | N95: =N120 -> 0 | O95: =O120 -> 0 | P95: =P120 -> 0 | Q95: =Q120 -> 0 | ... U95: =U120 -> 0
B96: Maintenance Forest Road | C96: 305 | D96: Maintenance | H96: =SUM(J96:U96) -> 0
B97: Maintenance Public Road | C97: 306 | D97: Maintenance | H97: =SUM(J97:U97) -> 0
B98: Skid/Pad maintenance | C98: 300/14 | D98: Post harvest costs | H98: =SUM(J98:U98) -> 0
B99: Post-harvest clean-up | C99: 300/10 | D99: Post harvest costs | H99: =SUM(J99:U99) -> 0
B100: Health and safety and Auditing | C100: 300/11 | D100: Indirect costs | H100: =SUM(J100:U100) -> 0
B101: Weighbridge | C101: 300/03 | D101: Indirect costs | G101: =H101/$W$16 -> #DIV/0! | H101: =SUM(J101:U101) -> 0
B102: Environmental monitoring/consents | C102: 330/04 | D102: Indirect costs | E102: 365 | H102: =SUM(J102:U102) -> 0
B103: Forest levy | C103: 300/08 | D103: Mgmt/Admin | E103: 338 | G103: 0.33 | H103: =SUM(J103:U103) -> 0 | J103: =$G$103*J16 -> 0 | K103: =$G$103*K16 -> 0 | L103: =$G$103*L16 -> 0 | M103: =$G$103*M16 -> 0 | N103: =$G$103*N16 -> 0 | O103: =$G$103*O16 -> 0 | P103: =$G$103*P16 -> 0 | Q103: =$G$103*Q16 -> 0 | ... U103: =$G$103*U16 -> 0
B104: Insurance Payment protection (domestic sales only) | C104: 351 | D104: Mgmt/Admin | E104: 324 | G104: 0.0016 | H104: =SUM(J104:U104) -> 0 | J104: =$G$104*J46/100 -> 0 | K104: =$G$104*K46/100 -> 0 | L104: =$G$104*L46/100 -> 0 | M104: =$G$104*M46/100 -> 0 | N104: =$G$104*N46/100 -> 0 | O104: =$G$104*O46/100 -> 0 | P104: =$G$104*P46/100 -> 0 | Q104: =$G$104*Q46/100 -> 0 | ... U104: =$G$104*U46/100 -> 0
B105: Harvest management fee | C105: 300/12 | D105: Mgmt/Admin | G105: 3.75 | H105: =SUM(J105:U105) -> 0 | J105: =$G$105*J16 -> 0 | K105: =$G$105*K16 -> 0 | L105: =$G$105*L16 -> 0 | M105: =$G$105*M16 -> 0 | N105: =$G$105*N16 -> 0 | O105: =$G$105*O16 -> 0 | P105: =$G$105*P16 -> 0 | Q105: =$G$105*Q16 -> 0 | ... U105: =$G$105*U16 -> 0
B107: Total non-docket costs | G107: =H107/B127 -> #DIV/0! | H107: =SUM(H82:H105) -> 11115 | J107: =SUM(J82:J105) -> 0 | K107: =SUM(K82:K105) -> 0 | L107: =SUM(L82:L105) -> 11115 | M107: =SUM(M82:M105) -> 0 | N107: =SUM(N82:N105) -> 0 | O107: =SUM(O82:O105) -> 0 | P107: =SUM(P82:P105) -> 0 | Q107: =SUM(Q82:Q105) -> 0 | ... U107: =SUM(U82:U105) -> 0
B109: Total Costs | H109: =H51+H78+H107 -> 11115 | J109: =J51+J78+J107 -> 0 | K109: =K51+K78+K107 -> 0 | L109: =L51+L78+L107 -> 11115 | M109: =M51+M78+M107 -> 0 | N109: =N51+N78+N107 -> 0 | O109: =O51+O78+O107 -> 0 | P109: =P51+P78+P107 -> 0 | Q109: =Q51+Q78+Q107 -> 0 | ... U109: =U51+U78+U107 -> 0 | W109: =SUM(J109:U109) -> 11115
B111: Net Harvest Total | H111: =H46-H109 -> -11115 | J111: =J46-J109 -> 0 | K111: =K46-K109 -> 0 | L111: =L46-L109 -> -11115 | M111: =M46-M109 -> 0 | N111: =N46-N109 -> 0 | O111: =O46-O109 -> 0 | P111: =P46-P109 -> 0 | Q111: =Q46-Q109 -> 0 | ... U111: =U46-U109 -> 0 | W111: =SUM(J111:U111) -> -11115
B113: Engineering | C113: Op Code | D113: Activity | E113: Unit | F113: Vol | G113: Unit Rate | J113: Metres constructed or number of skids/pads
B114: Existing road upgrade-Substantially metalled or sealed | C114: 720 | D114: Infrastructure | E114: cost/m
B115: New road construction-Substantially metalled or sealed | C115: 720 | D115: Infrastructure | E115: cost/m | G115: =IFERROR(H115/F115,0) -> 0
B116: Existing road upgrade-Partially metalled or sealed | C116: 720 | D116: Infrastructure | E116: cost/m
B117: New road construction-Partially metalled or sealed | C117: 720 | D117: Infrastructure | E117: cost/m
B118: Other infrastructure | C118: 720 | D118: Infrastructure | E118: cost/unit
B119: Skid construction | C119: 300/05 | D119: Infrastructure | E119: cost/skid | G119: =IFERROR(H119/F119,0) -> 0
...

Sheet Mount Erin (T&M) Budget
C1: 2025 | D1: Input
B2: Mount Erin | H2: Estimated Tonnes (ha)
B3: PRODUCTION & RATE | G3: Total Monthly Working Days | I3: =IF(NOT(ISBLANK(J5)), J5, IF(NOT(ISBLANK(J8)), J8, IF(NOT(ISBLANK(J11)), J11, 0)))+IF(NOT(ISBLANK(K5)), K5, IF(NOT(ISBLANK(K8)), K8, IF(NOT(ISBLANK(K11)), K11, 0)))+IF(NOT(ISBLANK(L5)), L5, IF(NOT(ISBLANK(L8)), L8, IF(NOT(ISBLANK(L11)), L11, 0)))+IF(NOT(ISBLANK(M5)), M5, IF(NOT(ISBLANK(M8)), M8, IF(NOT(ISBLANK(M11)), M11, 0)))+IF(NOT(ISBLANK(N5)), N5, IF(NOT(ISBLANK(N8)), N8, IF(NOT(ISBLANK(N11)), N11, 0)))+IF(NOT(ISBLANK(O5)), O5, IF(NOT(ISBLANK(O8)), O8, IF(NOT(ISBLANK(O11)), O11, 0)))+IF(NOT(ISBLANK(P5)), P5, IF(NOT(ISBLANK(P8)), P8, IF(NOT(ISBLANK(P11)), P11, 0)))+IF(NOT(ISBLANK(Q5)), Q5, IF(NOT(ISBLANK(Q8)), Q8, IF(NOT(ISBLANK(Q11)), Q11, 0)))+IF(NOT(ISBLANK(R5)), R5, IF(NOT(ISBLANK(R8)), R8, IF(NOT(ISBLANK(R11)), R11, 0)))+IF(NOT(ISBLANK(S5)), S5, IF(NOT(ISBLANK(S8)), S8, IF(NOT(ISBLANK(S11)), S11, 0)))+IF(NOT(ISBLANK(T5)), T5, IF(NOT(ISBLANK(T8)), T8, IF(NOT(ISBLANK(T11)), T11, 0)))+IF(NOT(ISBLANK(U5)), U5, IF(NOT(ISBLANK(U8)), U8, IF(NOT(ISBLANK(U11)), U11, 0))) -> 0 | J3: 45658 | K3: 45689 | L3: 45717 | M3: 45748 | N3: 45778 | O3: 45809 | P3: 45839 | Q3: 45870 | R3: 45901 | S3: 45931 | T3: 45962 | U3: 45992 | W3: Total
G4: Groundbase | H4: Daily production | I4: =IFERROR((J4*J5+K4*K5+L4*L5+M4*M5+N4*N5+O4*O5+P4*P5+Q4*Q5+R4*R5+S4*S5+T4*T5+U4*U5)/$W$16,0) -> 0
H5: Days worked
H6: Harvesting Rate
G7: Roadline | H7: Daily production | I7: =IFERROR((J7*J8+K7*K8+L7*L8+M7*M8+N7*N8+O7*O8+P7*P8+Q7*Q8+R7*R8+S7*S8+T7*T8+U7*U8)/$W$16,0) -> 0
H8: Days worked
H9: Harvesting Rate
G10: Hauler | H10: Daily production | I10: =IFERROR((J10*J11+K10*K11+L10*L11+M10*M11+N10*N11+O10*O11+P10*P11+Q10*Q11+R10*R11+S10*S11+T10*T11+U10*U11)/$W$16,0) -> 0
H11: Days worked
H12: Harvesting Rate
G13: Average | H13: Harvesting Rate | I13: =SUM(I4:I12) -> 0 | J13: =IFERROR((J4*J5*J6+J7*J8*J9+J10*J11*J12)/J16,0) -> 0 | K13: =IFERROR((K4*K5*K6+K7*K8*K9+K10*K11*K12)/K16,0) -> 0 | L13: =IFERROR((L4*L5*L6+L7*L8*L9+L10*L11*L12)/L16,0) -> 0 | M13: =IFERROR((M4*M5*M6+M7*M8*M9+M10*M11*M12)/M16,0) -> 0 | N13: =IFERROR((N4*N5*N6+N7*N8*N9+N10*N11*N12)/N16,0) -> 0 | O13: =IFERROR((O4*O5*O6+O7*O8*O9+O10*O11*O12)/O16,0) -> 0 | P13: =IFERROR((P4*P5*P6+P7*P8*P9+P10*P11*P12)/P16,0) -> 0 | Q13: =IFERROR((Q4*Q5*Q6+Q7*Q8*Q9+Q10*Q11*Q12)/Q16,0) -> 0 | ... U13: =IFERROR((U4*U5*U6+U7*U8*U9+U10*U11*U12)/U16,0) -> 0 | W13: =I3 -> 0 | X13: Monthly Working Days
G14: Average | H14: Daily production | J14: =J4+J7+J10 -> 0 | K14: =K4+K7+K10 -> 0 | L14: =L4+L7+L10 -> 0 | M14: =M4+M7+M10 -> 0 | N14: =N4+N7+N10 -> 0 | O14: =O4+O7+O10 -> 0 | P14: =P4+P7+P10 -> 0 | Q14: =Q4+Q7+Q10 -> 0 | ... U14: =U4+U7+U10 -> 0 | W14: =IF(W16=0,0,W16/W15) -> 0 | X14: =H2 -> Estimated Tonnes (ha)
G15: Total | H15: Hectare (ha) | J15: =IFERROR(J16/$I$2,0) -> 0 | K15: =IFERROR(K16/$I$2,0) -> 0 | L15: =IFERROR(L16/$I$2,0) -> 0 | M15: =IFERROR(M16/$I$2,0) -> 0 | N15: =IFERROR(N16/$I$2,0) -> 0 | O15: =IFERROR(O16/$I$2,0) -> 0 | P15: =IFERROR(P16/$I$2,0) -> 0 | Q15: =IFERROR(Q16/$I$2,0) -> 0 | ... U15: =IFERROR(U16/$I$2,0) -> 0 | W15: =SUM(J15:U15) -> 0 | X15: =H15 -> Hectare (ha)
G16: Total | H16: Tonnes Harvested | J16: =IFERROR((J4*J5+J7*J8+J10*J11),0) -> 0 | K16: =IFERROR((K4*K5+K7*K8+K10*K11),0) -> 0 | L16: =IFERROR((L4*L5+L7*L8+L10*L11),0) -> 0 | M16: =IFERROR((M4*M5+M7*M8+M10*M11),0) -> 0 | N16: =IFERROR((N4*N5+N7*N8+N10*N11),0) -> 0 | O16: =IFERROR((O4*O5+O7*O8+O10*O11),0) -> 0 | P16: =IFERROR((P4*P5+P7*P8+P10*P11),0) -> 0 | Q16: =IFERROR((Q4*Q5+Q7*Q8+Q10*Q11),0) -> 0 | ... U16: =IFERROR((U4*U5+U7*U8+U10*U11),0) -> 0 | W16: =SUM(J16:U16) -> 0 | X16: =H16 -> Tonnes Harvested
W17: =W16/W15 -> #DIV/0! | X17: Vol/ha
B18: REVENUE
B19: Grade | C19: Grade Mix % | D19: Conversion Rate | E19: Sale unit | F19: Sale unit/Vol | G19: Price/Unit | H19: TOTAL | J19: 45658 | K19: 45689 | L19: 45717 | M19: 45748 | N19: 45778 | O19: 45809 | P19: 45839 | Q19: 45870 | R19: 45901 | S19: 45931 | T19: 45962 | U19: 45992
B20: P35 | C20: 0.11412433 | D20: 1 | E20: Tonnes | F20: =IFERROR(H20/G20,0) -> 0 | H20: =SUM(J20:U20) -> 0 | J20: =J16*$C20*$D20*$G20 -> 0 | K20: =K16*$C$20*$D$20*$G$20 -> 0 | L20: =L16*$C$20*$D$20*$G$20 -> 0 | M20: =M16*$C$20*$D$20*$G$20 -> 0 | N20: =N16*$C$20*$D$20*$G$20 -> 0 | O20: =O16*$C$20*$D$20*$G$20 -> 0 | P20: =P16*$C$20*$D$20*$G$20 -> 0 | Q20: =Q16*$C$20*$D$20*$G$20 -> 0 | R20: =R16*$C$20*$D$20*$G$20 -> 0 | ... U20: =U16*$C$20*$D$20*$G$20 -> 0 | W20: =$W$17*C20 -> #DIV/0! | X20: =B20 -> P35
B21: S30 | C21: 0.07 | D21: 1 | E21: Tonnes | F21: =IFERROR(H21/G21,0) -> 0 | H21: =SUM(J21:U21) -> 0 | J21: =J16*$C$21*$D$21*$G$21 -> 0 | K21: =K16*$C$21*$D$21*$G$21 -> 0 | L21: =L16*$C$21*$D$21*$G$21 -> 0 | M21: =M16*$C$21*$D$21*$G$21 -> 0 | N21: =N16*$C$21*$D$21*$G$21 -> 0 | O21: =O16*$C$21*$D$21*$G$21 -> 0 | P21: =P16*$C$21*$D$21*$G$21 -> 0 | Q21: =Q16*$C$21*$D$21*$G$21 -> 0 | ... U21: =U16*$C$21*$D$21*$G$21 -> 0 | W21: =$W$17*C21 -> #DIV/0! | X21: =B21 -> S30
B22: S20 | C22: 0 | D22: 1 | E22: Tonnes | F22: =IFERROR(H22/G22,0) -> 0 | H22: =SUM(J22:U22) -> 0 | J22: =J16*$C$22*$D$22*$G$22 -> 0 | K22: =K16*$C$22*$D$22*$G$22 -> 0 | L22: =L16*$C$22*$D$22*$G$22 -> 0 | M22: =M16*$C$22*$D$22*$G$22 -> 0 | N22: =N16*$C$22*$D$22*$G$22 -> 0 | O22: =O16*$C$22*$D$22*$G$22 -> 0 | P22: =P16*$C$22*$D$22*$G$22 -> 0 | Q22: =Q16*$C$22*$D$22*$G$22 -> 0 | ... U22: =U16*$C$22*$D$22*$G$22 -> 0 | W22: =$W$17*C22 -> #DIV/0! | X22: =B22 -> S20
B23: Domestic Pulp | C23: 0.05 | D23: 1 | E23: Tonnes | F23: =IFERROR(H23/G23,0) -> 0 | H23: =SUM(J23:U23) -> 0 | J23: =J16*$C$23*$D$23*$G$23 -> 0 | K23: =K16*$C$23*$D$23*$G$23 -> 0 | L23: =L16*$C$23*$D$23*$G$23 -> 0 | M23: =M16*$C$23*$D$23*$G$23 -> 0 | N23: =N16*$C$23*$D$23*$G$23 -> 0 | O23: =O16*$C$23*$D$23*$G$23 -> 0 | P23: =P16*$C$23*$D$23*$G$23 -> 0 | Q23: =Q16*$C$23*$D$23*$G$23 -> 0 | ... U23: =U16*$C$23*$D$23*$G$23 -> 0 | W23: =$W$17*C23 -> #DIV/0! | X23: =B23 -> Domestic Pulp
B24: Eucalyptus | C24: 0 | D24: 1 | E24: Tonnes | F24: =IFERROR(H24/G24,0) -> 0 | H24: =SUM(J24:U24) -> 0 | J24: =J16*$C$24*$D$24*$G$24 -> 0 | K24: =K16*$C$24*$D$24*$G$24 -> 0 | L24: =L16*$C$24*$D$24*$G$24 -> 0 | M24: =M16*$C$24*$D$24*$G$24 -> 0 | N24: =N16*$C$24*$D$24*$G$24 -> 0 | O24: =O16*$C$24*$D$24*$G$24 -> 0 | P24: =P16*$C$24*$D$24*$G$24 -> 0 | Q24: =Q16*$C$24*$D$24*$G$24 -> 0 | ... U24: =U16*$C$24*$D$24*$G$24 -> 0 | W24: =$W$17*C24 -> #DIV/0! | X24: =B24 -> Eucalyptus
B25: FW | C25: 0 | D25: 1 | E25: Tonnes | F25: =IFERROR(H25/G25,0) -> 0 | H25: =SUM(J25:U25) -> 0 | J25: =J16*$C$25*$D$25*$G$25 -> 0 | K25: =K16*$C$25*$D$25*$G$25 -> 0 | L25: =L16*$C$25*$D$25*$G$25 -> 0 | M25: =M16*$C$25*$D$25*$G$25 -> 0 | N25: =N16*$C$25*$D$25*$G$25 -> 0 | O25: =O16*$C$25*$D$25*$G$25 -> 0 | P25: =P16*$C$25*$D$25*$G$25 -> 0 | Q25: =Q16*$C$25*$D$25*$G$25 -> 0 | ... U25: =U16*$C$25*$D$25*$G$25 -> 0 | W25: =$W$17*C25 -> #DIV/0! | X25: =B25 -> FW
B26: Euc Pulp | C26: 0 | D26: 1 | E26: Tonnes | F26: =IFERROR(H26/G26,0) -> 0 | H26: =SUM(J26:U26) -> 0 | J26: =J16*$C$26*$D$26*$G$26 -> 0 | K26: =K16*$C$26*$D$26*$G$26 -> 0 | L26: =L16*$C$26*$D$26*$G$26 -> 0 | M26: =M16*$C$26*$D$26*$G$26 -> 0 | N26: =N16*$C$26*$D$26*$G$26 -> 0 | O26: =O16*$C$26*$D$26*$G$26 -> 0 | P26: =P16*$C$26*$D$26*$G$26 -> 0 | Q26: =Q16*$C$26*$D$26*$G$26 -> 0 | ... U26: =U16*$C$26*$D$26*$G$26 -> 0 | W26: =$W$17*C26 -> #DIV/0! | X26: =B26 -> Euc Pulp
B27: Binwood | C27: 0 | D27: 1 | E27: Tonnes | F27: =IFERROR(H27/G27,0) -> 0 | H27: =SUM(J27:U27) -> 0 | J27: =J16*$C$27*$D$27*$G$27 -> 0 | K27: =K16*$C$27*$D$27*$G$27 -> 0 | L27: =L16*$C$27*$D$27*$G$27 -> 0 | M27: =M16*$C$27*$D$27*$G$27 -> 0 | N27: =N16*$C$27*$D$27*$G$27 -> 0 | O27: =O16*$C$27*$D$27*$G$27 -> 0 | P27: =P16*$C$27*$D$27*$G$27 -> 0 | Q27: =Q16*$C$27*$D$27*$G$27 -> 0 | ... U27: =U16*$C$27*$D$27*$G$27 -> 0 | W27: =$W$17*C27 -> #DIV/0! | X27: =B27 -> Binwood
B28: Spare Grade | C28: 0 | E28: Tonnes | F28: =IFERROR(H28/G28/D28,0) -> 0 | H28: =SUM(J28:U28) -> 0 | J28: =J16*$C$28*$D$28*$G$28 -> 0 | K28: =K16*$C$28*$D$28*$G$28 -> 0 | L28: =L16*$C$28*$D$28*$G$28 -> 0 | M28: =M16*$C$28*$D$28*$G$28 -> 0 | N28: =N16*$C$28*$D$28*$G$28 -> 0 | O28: =O16*$C$28*$D$28*$G$28 -> 0 | P28: =P16*$C$28*$D$28*$G$28 -> 0 | Q28: =Q16*$C$28*$D$28*$G$28 -> 0 | ... U28: =U16*$C$28*$D$28*$G$28 -> 0 | W28: =$W$17*C28 -> #DIV/0! | X28: =B28 -> Spare Grade
B29: P40 | C29: 0 | D29: 1 | E29: JAS | F29: =IFERROR(H29/G29/D29,0) -> 0 | H29: =SUM(J29:U29) -> 0 | J29: =J16*$C$29*$D$29*$G$29 -> 0 | K29: =K16*$C$29*$D$29*$G$29 -> 0 | L29: =L16*$C$29*$D$29*$G$29 -> 0 | M29: =M16*$C$29*$D$29*$G$29 -> 0 | N29: =N16*$C$29*$D$29*$G$29 -> 0 | O29: =O16*$C$29*$D$29*$G$29 -> 0 | P29: =P16*$C$29*$D$29*$G$29 -> 0 | Q29: =Q16*$C$29*$D$29*$G$29 -> 0 | ... U29: =U16*$C$29*$D$29*$G$29 -> 0 | W29: =$W$17*C29 -> #DIV/0! | X29: =B29 -> P40
B30: P30 | C30: 0.0019336678 | D30: 1.0288961 | E30: JAS | F30: =IFERROR(H30/G30/D30,0) -> 0 | H30: =SUM(J30:U30) -> 0 | J30: =J16*$C$30*$D$30*$G$30 -> 0 | K30: =K16*$C$30*$D$30*$G$30 -> 0 | L30: =L16*$C$30*$D$30*$G$30 -> 0 | M30: =M16*$C$30*$D$30*$G$30 -> 0 | N30: =N16*$C$30*$D$30*$G$30 -> 0 | O30: =O16*$C$30*$D$30*$G$30 -> 0 | P30: =P16*$C$30*$D$30*$G$30 -> 0 | Q30: =Q16*$C$30*$D$30*$G$30 -> 0 | ... U30: =U16*$C$30*$D$30*$G$30 -> 0 | W30: =$W$17*C30 -> #DIV/0! | X30: =B30 -> P30
B31: AO | C31: 0.15 | D31: 1.04 | E31: JAS | F31: =IFERROR(H31/G31/D31,0) -> 0 | H31: =SUM(J31:U31) -> 0 | J31: =J16*$C$31*$D$31*$G$31 -> 0 | K31: =K16*$C$31*$D$31*$G$31 -> 0 | L31: =L16*$C$31*$D$31*$G$31 -> 0 | M31: =M16*$C$31*$D$31*$G$31 -> 0 | N31: =N16*$C$31*$D$31*$G$31 -> 0 | O31: =O16*$C$31*$D$31*$G$31 -> 0 | P31: =P16*$C$31*$D$31*$G$31 -> 0 | Q31: =Q16*$C$31*$D$31*$G$31 -> 0 | ... U31: =U16*$C$31*$D$31*$G$31 -> 0 | W31: =$W$17*C31 -> #DIV/0! | X31: =B31 -> AO
B32: A | C32: 0.28 | D32: 1.01 | E32: JAS | F32: =IFERROR(H32/G32/D32,0) -> 0 | H32: =SUM(J32:U32) -> 0 | J32: =J16*$C$32*$D$32*$G$32 -> 0 | K32: =K16*$C$32*$D$32*$G$32 -> 0 | L32: =L16*$C$32*$D$32*$G$32 -> 0 | M32: =M16*$C$32*$D$32*$G$32 -> 0 | N32: =N16*$C$32*$D$32*$G$32 -> 0 | O32: =O16*$C$32*$D$32*$G$32 -> 0 | P32: =P16*$C$32*$D$32*$G$32 -> 0 | Q32: =Q16*$C$32*$D$32*$G$32 -> 0 | ... U32: =U16*$C$32*$D$32*$G$32 -> 0 | W32: =$W$17*C32 -> #DIV/0! | X32: =B32 -> A
B33: K | C33: 0.20870336 | D33: 0.96 | E33: JAS | F33: =IFERROR(H33/G33/D33,0) -> 0 | H33: =SUM(J33:U33) -> 0 | J33: =J16*$C$33*$D$33*$G$33 -> 0 | K33: =K16*$C$33*$D$33*$G$33 -> 0 | L33: =L16*$C$33*$D$33*$G$33 -> 0 | M33: =M16*$C$33*$D$33*$G$33 -> 0 | N33: =N16*$C$33*$D$33*$G$33 -> 0 | O33: =O16*$C$33*$D$33*$G$33 -> 0 | P33: =P16*$C$33*$D$33*$G$33 -> 0 | Q33: =Q16*$C$33*$D$33*$G$33 -> 0 | ... U33: =U16*$C$33*$D$33*$G$33 -> 0 | W33: =$W$17*C33 -> #DIV/0! | X33: =B33 -> K
B34: KI | C34: 0.025784396 | D34: 0.97 | E34: JAS | F34: =IFERROR(H34/G34/D34,0) -> 0 | H34: =SUM(J34:U34) -> 0 | J34: =J16*$C$34*$D$34*$G$34 -> 0 | K34: =K16*$C$34*$D$34*$G$34 -> 0 | L34: =L16*$C$34*$D$34*$G$34 -> 0 | M34: =M16*$C$34*$D$34*$G$34 -> 0 | N34: =N16*$C$34*$D$34*$G$34 -> 0 | O34: =O16*$C$34*$D$34*$G$34 -> 0 | P34: =P16*$C$34*$D$34*$G$34 -> 0 | Q34: =Q16*$C$34*$D$34*$G$34 -> 0 | ... U34: =U16*$C$34*$D$34*$G$34 -> 0 | W34: =$W$17*C34 -> #DIV/0! | X34: =B34 -> KI
B35: KIS | C35: 0.1017521 | D35: 0.92 | E35: JAS | F35: =IFERROR(H35/G35/D35,0) -> 0 | H35: =SUM(J35:U35) -> 0 | J35: =J16*$C$35*$D$35*$G$35 -> 0 | K35: =K16*$C$35*$D$35*$G$35 -> 0 | L35: =L16*$C$35*$D$35*$G$35 -> 0 | M35: =M16*$C$35*$D$35*$G$35 -> 0 | N35: =N16*$C$35*$D$35*$G$35 -> 0 | O35: =O16*$C$35*$D$35*$G$35 -> 0 | P35: =P16*$C$35*$D$35*$G$35 -> 0 | Q35: =Q16*$C$35*$D$35*$G$35 -> 0 | ... U35: =U16*$C$35*$D$35*$G$35 -> 0 | W35: =$W$17*C35 -> #DIV/0! | X35: =B35 -> KIS
B36: KI stub | E36: JAS | F36: =IFERROR(H36/G36/D36,0) -> 0 | H36: =SUM(J36:U36) -> 0 | J36: =J16*$C$36*$D$36*$G$36 -> 0 | K36: =K16*$C$36*$D$36*$G$36 -> 0 | L36: =L16*$C$36*$D$36*$G$36 -> 0 | M36: =M16*$C$36*$D$36*$G$36 -> 0 | N36: =N16*$C$36*$D$36*$G$36 -> 0 | O36: =O16*$C$36*$D$36*$G$36 -> 0 | P36: =P16*$C$36*$D$36*$G$36 -> 0 | Q36: =Q16*$C$36*$D$36*$G$36 -> 0 | ... U36: =U16*$C$36*$D$36*$G$36 -> 0 | W36: =$W$17*C36 -> #DIV/0! | X36: =B36 -> KI stub
B37: CF+ | E37: JAS | F37: =IFERROR(H37/G37/D37,0) -> 0 | H37: =SUM(J37:U37) -> 0 | J37: =J16*$C$37*$D$37*$G$37 -> 0 | K37: =K16*$C$37*$D$37*$G$37 -> 0 | L37: =L16*$C$37*$D$37*$G$37 -> 0 | M37: =M16*$C$37*$D$37*$G$37 -> 0 | N37: =N16*$C$37*$D$37*$G$37 -> 0 | O37: =O16*$C$37*$D$37*$G$37 -> 0 | P37: =P16*$C$37*$D$37*$G$37 -> 0 | Q37: =Q16*$C$37*$D$37*$G$37 -> 0 | ... U37: =U16*$C$37*$D$37*$G$37 -> 0 | W37: =$W$17*C37 -> #DIV/0! | X37: =B37 -> CF+
B38: CF- | E38: JAS | F38: =IFERROR(H38/G38/D38,0) -> 0 | H38: =SUM(J38:U38) -> 0 | J38: =J16*$C$38*$D$38*$G$38 -> 0 | K38: =K16*$C$38*$D$38*$G$38 -> 0 | L38: =L16*$C$38*$D$38*$G$38 -> 0 | M38: =M16*$C$38*$D$38*$G$38 -> 0 | N38: =N16*$C$38*$D$38*$G$38 -> 0 | O38: =O16*$C$38*$D$38*$G$38 -> 0 | P38: =P16*$C$38*$D$38*$G$38 -> 0 | Q38: =Q16*$C$38*$D$38*$G$38 -> 0 | ... U38: =U16*$C$38*$D$38*$G$38 -> 0 | W38: =$W$17*C38 -> #DIV/0! | X38: =B38 -> CF-
B39: CM | E39: JAS | F39: =IFERROR(H39/G39/D39,0) -> 0 | H39: =SUM(J39:U39) -> 0 | J39: =J16*$C$39*$D$39*$G$39 -> 0 | K39: =K16*$C$39*$D$39*$G$39 -> 0 | L39: =L16*$C$39*$D$39*$G$39 -> 0 | M39: =M16*$C$39*$D$39*$G$39 -> 0 | N39: =N16*$C$39*$D$39*$G$39 -> 0 | O39: =O16*$C$39*$D$39*$G$39 -> 0 | P39: =P16*$C$39*$D$39*$G$39 -> 0 | Q39: =Q16*$C$39*$D$39*$G$39 -> 0 | ... U39: =U16*$C$39*$D$39*$G$39 -> 0 | W39: =$W$17*C39 -> #DIV/0! | X39: =B39 -> CM
B40: Euc A | E40: JAS | F40: =IFERROR(H40/G40/D40,0) -> 0 | H40: =SUM(J40:U40) -> 0 | J40: =J16*$C$40*$D$40*$G$40 -> 0 | K40: =K16*$C$40*$D$40*$G$40 -> 0 | L40: =L16*$C$40*$D$40*$G$40 -> 0 | M40: =M16*$C$40*$D$40*$G$40 -> 0 | N40: =N16*$C$40*$D$40*$G$40 -> 0 | O40: =O16*$C$40*$D$40*$G$40 -> 0 | P40: =P16*$C$40*$D$40*$G$40 -> 0 | Q40: =Q16*$C$40*$D$40*$G$40 -> 0 | ... U40: =U16*$C$40*$D$40*$G$40 -> 0 | W40: =$W$17*C40 -> #DIV/0! | X40: =B40 -> Euc A
B41: Euc K | H41: =SUM(J41:U41) -> 0 | J41: =J16*$C$41*$D$41*$G$41 -> 0 | K41: =K16*$C$41*$D$41*$G$41 -> 0 | L41: =L16*$C$41*$D$41*$G$41 -> 0 | M41: =M16*$C$41*$D$41*$G$41 -> 0 | N41: =N16*$C$41*$D$41*$G$41 -> 0 | O41: =O16*$C$41*$D$41*$G$41 -> 0 | P41: =P16*$C$41*$D$41*$G$41 -> 0 | Q41: =Q16*$C$41*$D$41*$G$41 -> 0 | ... U41: =U16*$C$41*$D$41*$G$41 -> 0 | W41: =$W$17*C41 -> #DIV/0! | X41: =B41 -> Euc K
